Workbook

Sheet Resumo Executivo
A1: RELATORIO GERENCIAL · CONTAS A PAGAR
A2: AP Aging — Agosto 2026 | T2: cat | U2: val
A3: ="Posicao em "&TEXT(Parametros!$B$6,"DD/MM/YYYY")&" - Fonte: SAP - Administrar itens fornecedor (partidas em aberto)" | T3: Construction Services – Under Litigation | U3: =ABS(SUMIF('Aging por Categoria'!$A$5:$A$21,$T3,'Aging por Categoria'!$I$5:$I$21)) | X3: =TEXT(I8/1000000,"#,##0.0")&"M"&CHAR(10)&"Total Terceiros"
T4: Operational Suppliers (Wind Farms) | U4: =ABS(SUMIF('Aging por Categoria'!$A$5:$A$21,$T4,'Aging por Categoria'!$I$5:$I$21))
T5: Customs Brokerage – Overall | U5: =ABS(SUMIF('Aging por Categoria'!$A$5:$A$21,$T5,'Aging por Categoria'!$I$5:$I$21))
T6: SINOMA | U6: =ABS(SUMIF('Aging por Categoria'!$A$5:$A$21,$T6,'Aging por Categoria'!$I$5:$I$21))
A7: EXPOSICAO TOTAL | E7: INTERCOMPANY | I7: TERCEIROS | M7: VENCIDO | T7: Other Suppliers | U7: =ABS(SUMIF('Aging por Categoria'!$A$5:$A$21,$T7,'Aging por Categoria'!$I$5:$I$21))
A8: =ABS('Aging por Categoria'!$I$22) | E8: =ABS(SUMIF('Aging por Categoria'!$A$5:$A$21,"Intercompany",'Aging por Categoria'!$I$5:$I$21)) | I8: =ABS('Aging por Categoria'!$I$22-SUMIF('Aging por Categoria'!$A$5:$A$21,"Intercompany",'Aging por Categoria'!$I$5:$I$21)) | M8: =ABS(SUMIF(Base[Vencido],1,Base[Montante])) | T8: Demais categorias | U8: =MAX(0,ABS('Aging por Categoria'!I22-SUMIF('Aging por Categoria'!$A$5:$A$21,"Intercompany",'Aging por Categoria'!$I$5:$I$21))-(U3+U4+U5+U6+U7))
A9: Saldo consolidado na data de corte | E9: Empresas do grupo Nordex | I9: Fornecedores externos | M9: Vencimento ja expirado
T12: ano | U12: val
T13: Até 2020 | U13: =ABS('Aging por Categoria'!B22) | V13: =AVERAGE($U$13:$U$19) | X13: =TEXT(ABS('Aging por Categoria'!H22/1000000),"#,##0.0")&"M"&CHAR(10)&"Saldo 2026"
T14: 2021 | U14: =ABS('Aging por Categoria'!C22) | V14: =AVERAGE($U$13:$U$19)
T15: 2022 | U15: =ABS('Aging por Categoria'!D22) | V15: =AVERAGE($U$13:$U$19)
T16: 2023 | U16: =ABS('Aging por Categoria'!E22) | V16: =AVERAGE($U$13:$U$19)
T17: 2024 | U17: =ABS('Aging por Categoria'!F22) | V17: =AVERAGE($U$13:$U$19)
T18: 2025 | U18: =ABS('Aging por Categoria'!G22) | V18: =AVERAGE($U$13:$U$19)
T19: 2026 | U19: =ABS('Aging por Categoria'!H22) | V19: =AVERAGE($U$13:$U$19)
T22: forn | U22: val
T23: 4U CONSTRUCOES LTDA EPP | U23: =ABS(SUMIF(Base[Fornecedor],"101963",Base[Montante]))
T24: SINOMA WIND POWER BLADE (BRAZIL) LT | U24: =ABS(SUMIF(Base[Fornecedor],"103849",Base[Montante]))
T25: 3Z MOVIMENTACAO INTELIGENTE LTDA 94 | U25: =ABS(SUMIF(Base[Fornecedor],"102113",Base[Montante]))
T26: TRADEWORKS SERVICOS DE COMERCIO EXT | U26: =ABS(SUMIF(Base[Fornecedor],"105984",Base[Montante]))
T27: CUSTOM COMERCIO INTERNACIONAL LTDA | U27: =ABS(SUMIF(Base[Fornecedor],"101071",Base[Montante]))
T28: DARCY PACHECO SOLUCOES DE PESO LTDA | U28: =ABS(SUMIF(Base[Fornecedor],"101801",Base[Montante]))
T29: ZURICH MINAS BRASIL SEGUROS S A | U29: =ABS(SUMIF(Base[Fornecedor],"101463",Base[Montante]))

Sheet Base
A1: Conta | B1: Fornecedor | C1: Nome do fornecedor | D1: Tipo doc | E1: Documento | F1: Referência | G1: Moeda | H1: Montante | I1: Data documento | J1: Data vencimento | K1: Texto | L1: Atribuição | M1: Ano | N1: Categoria | O1: Dias atraso | P1: Vencido
A2: 2122100000 | B2: IC1000 | C2: NORDEX ENERGY SE & CO KG | D2: AB | E2: 1008418 | G2: EUR | H2: 33462.83 | I2: 45227 | J2: 45227 | K2: Clearing document NORDEX ENERGY SE & CO. KG | L2: 403000.NORDENER | M2: =IF(YEAR(I2)<=2020,"Até 2020",TEXT(YEAR(I2),"0")) | N2: =IFERROR(INDEX(DePara!$A:$A,MATCH(TEXT(B2,"0"),DePara!$D:$D,0)),"(sem categoria)") | O2: =IF(J2="","",Parametros!$B$6-J2) | P2: =IF(O2="","",IF(O2>0,1,0))
A3: 2122100000 | B3: IC4420 | C3: NORDEX ENERGY SPAIN S A U | D3: AB | E3: 1008419 | G3: EUR | H3: 93546.45 | I3: 45227 | J3: 45227 | K3: Clearing document NORDEX ENERGY SPAIN S.A.U. | L3: intercompany | M3: =IF(YEAR(I3)<=2020,"Até 2020",TEXT(YEAR(I3),"0")) | N3: =IFERROR(INDEX(DePara!$A:$A,MATCH(TEXT(B3,"0"),DePara!$D:$D,0)),"(sem categoria)") | O3: =IF(J3="","",Parametros!$B$6-J3) | P3: =IF(O3="","",IF(O3>0,1,0))
A4: 2122100000 | B4: IC4420 | C4: NORDEX ENERGY SPAIN S A U | D4: AB | E4: 1008419 | G4: EUR | H4: 63508.45 | I4: 45227 | J4: 45227 | K4: Clearing document NORDEX ENERGY SPAIN S.A.U. | L4: intercompany | M4: =IF(YEAR(I4)<=2020,"Até 2020",TEXT(YEAR(I4),"0")) | N4: =IFERROR(INDEX(DePara!$A:$A,MATCH(TEXT(B4,"0"),DePara!$D:$D,0)),"(sem categoria)") | O4: =IF(J4="","",Parametros!$B$6-J4) | P4: =IF(O4="","",IF(O4>0,1,0))
A5: 2122100000 | B5: IC4420 | C5: NORDEX ENERGY SPAIN S A U | D5: RE | E5: 5000001 | F5: 4025008482 | G5: EUR | H5: -181492.25 | I5: 45964 | J5: 45994 | K5: 0846/25 | L5: 4025008482 | M5: =IF(YEAR(I5)<=2020,"Até 2020",TEXT(YEAR(I5),"0")) | N5: =IFERROR(INDEX(DePara!$A:$A,MATCH(TEXT(B5,"0"),DePara!$D:$D,0)),"(sem categoria)") | O5: =IF(J5="","",Parametros!$B$6-J5) | P5: =IF(O5="","",IF(O5>0,1,0))
A6: 2122100000 | B6: IC4420 | C6: NORDEX ENERGY SPAIN S A U | D6: RE | E6: 5000003 | F6: 4025008480 | G6: EUR | H6: -95934.74 | I6: 45964 | J6: 45994 | K6: 0842/25 | L6: 4025008480 | M6: =IF(YEAR(I6)<=2020,"Até 2020",TEXT(YEAR(I6),"0")) | N6: =IFERROR(INDEX(DePara!$A:$A,MATCH(TEXT(B6,"0"),DePara!$D:$D,0)),"(sem categoria)") | O6: =IF(J6="","",Parametros!$B$6-J6) | P6: =IF(O6="","",IF(O6>0,1,0))
A7: 2122100000 | B7: IC4420 | C7: NORDEX ENERGY SPAIN S A U | D7: RE | E7: 5000005 | F7: 4025008261 | G7: EUR | H7: -251289.79 | I7: 45957 | J7: 45987 | K7: 0826/25 | L7: 4025008261 | M7: =IF(YEAR(I7)<=2020,"Até 2020",TEXT(YEAR(I7),"0")) | N7: =IFERROR(INDEX(DePara!$A:$A,MATCH(TEXT(B7,"0"),DePara!$D:$D,0)),"(sem categoria)") | O7: =IF(J7="","",Parametros!$B$6-J7) | P7: =IF(O7="","",IF(O7>0,1,0))
A8: 2122100000 | B8: IC4420 | C8: NORDEX ENERGY SPAIN S A U | D8: RE | E8: 5000072 | F8: 4025008229 | G8: EUR | H8: -3838623.1 | I8: 45954 | J8: 45984 | K8: 0852/25 | L8: 4025008229 | M8: =IF(YEAR(I8)<=2020,"Até 2020",TEXT(YEAR(I8),"0")) | N8: =IFERROR(INDEX(DePara!$A:$A,MATCH(TEXT(B8,"0"),DePara!$D:$D,0)),"(sem categoria)") | O8: =IF(J8="","",Parametros!$B$6-J8) | P8: =IF(O8="","",IF(O8>0,1,0))
A9: 2122100000 | B9: IC4420 | C9: NORDEX ENERGY SPAIN S A U | D9: RE | E9: 5000180 | F9: 4025008478 | G9: EUR | H9: -1330.48 | I9: 45964 | J9: 45994 | K9: 0844/25 | L9: 4025008478 | M9: =IF(YEAR(I9)<=2020,"Até 2020",TEXT(YEAR(I9),"0")) | N9: =IFERROR(INDEX(DePara!$A:$A,MATCH(TEXT(B9,"0"),DePara!$D:$D,0)),"(sem categoria)") | O9: =IF(J9="","",Parametros!$B$6-J9) | P9: =IF(O9="","",IF(O9>0,1,0))
A10: 2122100000 | B10: IC4420 | C10: NORDEX ENERGY SPAIN S A U | D10: RE | E10: 5000181 | F10: 4025008476 | G10: EUR | H10: -118914.41 | I10: 45964 | J10: 45994 | K10: 0844/25 | L10: 4025008476 | M10: =IF(YEAR(I10)<=2020,"Até 2020",TEXT(YEAR(I10),"0")) | N10: =IFERROR(INDEX(DePara!$A:$A,MATCH(TEXT(B10,"0"),DePara!$D:$D,0)),"(sem categoria)") | O10: =IF(J10="","",Parametros!$B$6-J10) | P10: =IF(O10="","",IF(O10>0,1,0))
A11: 2122100000 | B11: IC4420 | C11: NORDEX ENERGY SPAIN S A U | D11: RE | E11: 5000188 | F11: 4025009533 | G11: EUR | H11: -2357 | I11: 46000 | J11: 46030 | K11: 0926/25 | L11: 4025009533 | M11: =IF(YEAR(I11)<=2020,"Até 2020",TEXT(YEAR(I11),"0")) | N11: =IFERROR(INDEX(DePara!$A:$A,MATCH(TEXT(B11,"0"),DePara!$D:$D,0)),"(sem categoria)") | O11: =IF(J11="","",Parametros!$B$6-J11) | P11: =IF(O11="","",IF(O11>0,1,0))
A12: 2122100000 | B12: IC4420 | C12: NORDEX ENERGY SPAIN S A U | D12: RE | E12: 5000190 | F12: 4025009569 | G12: EUR | H12: -6504.31 | I12: 46001 | J12: 46031 | K12: 0921/25 | L12: 4025009569 | M12: =IF(YEAR(I12)<=2020,"Até 2020",TEXT(YEAR(I12),"0")) | N12: =IFERROR(INDEX(DePara!$A:$A,MATCH(TEXT(B12,"0"),DePara!$D:$D,0)),"(sem categoria)") | O12: =IF(J12="","",Parametros!$B$6-J12) | P12: =IF(O12="","",IF(O12>0,1,0))
A13: 2122100000 | B13: IC4420 | C13: NORDEX ENERGY SPAIN S A U | D13: RE | E13: 5000236 | F13: 4025009111 | G13: EUR | H13: -826.41 | I13: 45987 | J13: 46017 | K13: 0890/25 | L13: 4025009111 | M13: =IF(YEAR(I13)<=2020,"Até 2020",TEXT(YEAR(I13),"0")) | N13: =IFERROR(INDEX(DePara!$A:$A,MATCH(TEXT(B13,"0"),DePara!$D:$D,0)),"(sem categoria)") | O13: =IF(J13="","",Parametros!$B$6-J13) | P13: =IF(O13="","",IF(O13>0,1,0))
A14: 2122100000 | B14: IC4420 | C14: NORDEX ENERGY SPAIN S A U | D14: RE | E14: 5000246 | F14: 4025008477 | G14: EUR | H14: -9145.39 | I14: 45964 | J14: 45994 | K14: 0845/25 | L14: 4025008477 | M14: =IF(YEAR(I14)<=2020,"Até 2020",TEXT(YEAR(I14),"0")) | N14: =IFERROR(INDEX(DePara!$A:$A,MATCH(TEXT(B14,"0"),DePara!$D:$D,0)),"(sem categoria)") | O14: =IF(J14="","",Parametros!$B$6-J14) | P14: =IF(O14="","",IF(O14>0,1,0))
A15: 2122100000 | B15: IC4420 | C15: NORDEX ENERGY SPAIN S A U | D15: RE | E15: 5000263 | F15: 4025008479 | G15: EUR | H15: -193802.69 | I15: 45964 | J15: 45994 | K15: 0843/25 | L15: 4025008479 | M15: =IF(YEAR(I15)<=2020,"Até 2020",TEXT(YEAR(I15),"0")) | N15: =IFERROR(INDEX(DePara!$A:$A,MATCH(TEXT(B15,"0"),DePara!$D:$D,0)),"(sem categoria)") | O15: =IF(J15="","",Parametros!$B$6-J15) | P15: =IF(O15="","",IF(O15>0,1,0))
A16: 2122100000 | B16: IC4420 | C16: NORDEX ENERGY SPAIN S A U | D16: RE | E16: 5000284 | F16: 4025009104 | G16: EUR | H16: -33691.24 | I16: 45987 | J16: 46017 | K16: 0908/25 | L16: 4025009104 | M16: =IF(YEAR(I16)<=2020,"Até 2020",TEXT(YEAR(I16),"0")) | N16: =IFERROR(INDEX(DePara!$A:$A,MATCH(TEXT(B16,"0"),DePara!$D:$D,0)),"(sem categoria)") | O16: =IF(J16="","",Parametros!$B$6-J16) | P16: =IF(O16="","",IF(O16>0,1,0))
... A69: 2122100000 | B69: IC4420 | C69: NORDEX ENERGY SPAIN S A U | D69: RE | E69: 5001704 | F69: 4025010003 | G69: EUR | H69: -32587.47 | I69: 46020 | J69: 46050 | K69: 0010/26 | L69: 4025010003 | M69: =IF(YEAR(I69)<=2020,"Até 2020",TEXT(YEAR(I69),"0")) | N69: =IFERROR(INDEX(DePara!$A:$A,MATCH(TEXT(B69,"0"),DePara!$D:$D,0)),"(sem categoria)") | O69: =IF(J69="","",Parametros!$B$6-J69) | P69: =IF(O69="","",IF(O69>0,1,0))
A70: 2122100000 | B70: IC4420 | C70: NORDEX ENERGY SPAIN S A U | D70: KG | E70: 5001799 | F70: 4000013 | G70: EUR | H70: 4427773.7 | I70: 46044 | J70: 46044 | K70: Nota crédito fornec. NORDEX ENERGY SPAIN S A U 400 | M70: =IF(YEAR(I70)<=2020,"Até 2020",TEXT(YEAR(I70),"0")) | N70: =IFERROR(INDEX(DePara!$A:$A,MATCH(TEXT(B70,"0"),DePara!$D:$D,0)),"(sem categoria)") | O70: =IF(J70="","",Parametros!$B$6-J70) | P70: =IF(O70="","",IF(O70>0,1,0))
A71: 2122100000 | B71: IC4420 | C71: NORDEX ENERGY SPAIN S A U | D71: RE | E71: 5001827 | F71: 4026000050 | G71: EUR | H71: -4187.65 | I71: 46029 | J71: 46059 | K71: 0016/26 | L71: 4026000050 | M71: =IF(YEAR(I71)<=2020,"Até 2020",TEXT(YEAR(I71),"0")) | N71: =IFERROR(INDEX(DePara!$A:$A,MATCH(TEXT(B71,"0"),DePara!$D:$D,0)),"(sem categoria)") | O71: =IF(J71="","",Parametros!$B$6-J71) | P71: =IF(O71="","",IF(O71>0,1,0))
A72: 2122100000 | B72: IC4420 | C72: NORDEX ENERGY SPAIN S A U | D72: RE | E72: 5001828 | F72: 4026000027 | G72: EUR | H72: -12947.14 | I72: 46027 | J72: 46057 | K72: 0015/26 | L72: 4026000027 | M72: =IF(YEAR(I72)<=2020,"Até 2020",TEXT(YEAR(I72),"0")) | N72: =IFERROR(INDEX(DePara!$A:$A,MATCH(TEXT(B72,"0"),DePara!$D:$D,0)),"(sem categoria)") | O72: =IF(J72="","",Parametros!$B$6-J72) | P72: =IF(O72="","",IF(O72>0,1,0))
A73: 2122100000 | B73: IC4420 | C73: NORDEX ENERGY SPAIN S A U | D73: RE | E73: 5001829 | F73: 4026000051 | G73: EUR | H73: -259.39 | I73: 46029 | J73: 46059 | K73: 0016/26 | L73: 4026000051 | M73: =IF(YEAR(I73)<=2020,"Até 2020",TEXT(YEAR(I73),"0")) | N73: =IFERROR(INDEX(DePara!$A:$A,MATCH(TEXT(B73,"0"),DePara!$D:$D,0)),"(sem categoria)") | O73: =IF(J73="","",Parametros!$B$6-J73) | P73: =IF(O73="","",IF(O73>0,1,0))
A74: 2122100000 | B74: IC1000 | C74: NORDEX ENERGY SE & CO KG | D74: KR | E74: 5001865 | F74: 624366 | G74: EUR | H74: -63754.33 | I74: 46042 | J74: 46072 | K74: Vendor Invoice NORDEX ENERGY SE & CO KG 624366 | M74: =IF(YEAR(I74)<=2020,"Até 2020",TEXT(YEAR(I74),"0")) | N74: =IFERROR(INDEX(DePara!$A:$A,MATCH(TEXT(B74,"0"),DePara!$D:$D,0)),"(sem categoria)") | O74: =IF(J74="","",Parametros!$B$6-J74) | P74: =IF(O74="","",IF(O74>0,1,0))
A75: 2122100000 | B75: IC4420 | C75: NORDEX ENERGY SPAIN S A U | D75: RE | E75: 5001935 | F75: 4026000283 | G75: EUR | H75: -15956.51 | I75: 46036 | J75: 46066 | K75: 0025/26 | L75: 4026000283 | M75: =IF(YEAR(I75)<=2020,"Até 2020",TEXT(YEAR(I75),"0")) | N75: =IFERROR(INDEX(DePara!$A:$A,MATCH(TEXT(B75,"0"),DePara!$D:$D,0)),"(sem categoria)") | O75: =IF(J75="","",Parametros!$B$6-J75) | P75: =IF(O75="","",IF(O75>0,1,0))
A76: 2122100000 | B76: IC4420 | C76: NORDEX ENERGY SPAIN S A U | D76: RE | E76: 5001937 | F76: 4026000285 | G76: EUR | H76: -5.72 | I76: 46036 | J76: 46066 | K76: 0027/26 | L76: 4026000285 | M76: =IF(YEAR(I76)<=2020,"Até 2020",TEXT(YEAR(I76),"0")) | N76: =IFERROR(INDEX(DePara!$A:$A,MATCH(TEXT(B76,"0"),DePara!$D:$D,0)),"(sem categoria)") | O76: =IF(J76="","",Parametros!$B$6-J76) | P76: =IF(O76="","",IF(O76>0,1,0))
A77: 2122100000 | B77: IC4420 | C77: NORDEX ENERGY SPAIN S A U | D77: RE | E77: 5001974 | F77: 4025007233 | G77: EUR | H77: -2632.09 | I77: 45919 | J77: 45949 | K77: 0782/25 | L77: 4025007233 | M77: =IF(YEAR(I77)<=2020,"Até 2020",TEXT(YEAR(I77),"0")) | N77: =IFERROR(INDEX(DePara!$A:$A,MATCH(TEXT(B77,"0"),DePara!$D:$D,0)),"(sem categoria)") | O77: =IF(J77="","",Parametros!$B$6-J77) | P77: =IF(O77="","",IF(O77>0,1,0))
A78: 2122100000 | B78: IC4420 | C78: NORDEX ENERGY SPAIN S A U | D78: RE | E78: 5001999 | F78: 4025007248 | G78: EUR | H78: -168218.94 | I78: 45919 | J78: 45949 | K78: 0777/25 | L78: 4025007248 | M78: =IF(YEAR(I78)<=2020,"Até 2020",TEXT(YEAR(I78),"0")) | N78: =IFERROR(INDEX(DePara!$A:$A,MATCH(TEXT(B78,"0"),DePara!$D:$D,0)),"(sem categoria)") | O78: =IF(J78="","",Parametros!$B$6-J78) | P78: =IF(O78="","",IF(O78>0,1,0))
A79: 2122100000 | B79: IC4420 | C79: NORDEX ENERGY SPAIN S A U | D79: RE | E79: 5002000 | F79: 4025007244 | G79: EUR | H79: -51550.43 | I79: 45919 | J79: 45949 | K79: 0780/25 | L79: 4025007244 | M79: =IF(YEAR(I79)<=2020,"Até 2020",TEXT(YEAR(I79),"0")) | N79: =IFERROR(INDEX(DePara!$A:$A,MATCH(TEXT(B79,"0"),DePara!$D:$D,0)),"(sem categoria)") | O79: =IF(J79="","",Parametros!$B$6-J79) | P79: =IF(O79="","",IF(O79>0,1,0))
A80: 2122100000 | B80: IC1000 | C80: NORDEX ENERGY SE & CO KG | D80: RE | E80: 5002045 | F80: 4012485638 | G80: BRL | H80: -5367090.2 | I80: 45965 | J80: 45995 | K80: 0911/25 | L80: 4012485638 | M80: =IF(YEAR(I80)<=2020,"Até 2020",TEXT(YEAR(I80),"0")) | N80: =IFERROR(INDEX(DePara!$A:$A,MATCH(TEXT(B80,"0"),DePara!$D:$D,0)),"(sem categoria)") | O80: =IF(J80="","",Parametros!$B$6-J80) | P80: =IF(O80="","",IF(O80>0,1,0))
A81: 2122100000 | B81: IC4420 | C81: NORDEX ENERGY SPAIN S A U | D81: KR | E81: 5002054 | F81: 4023004386 | G81: EUR | H81: -200.59 | I81: 45191 | J81: 45191 | K81: Vendor Invoice NORDEX ENERGY SPAIN S.A.U. 40230043 | M81: =IF(YEAR(I81)<=2020,"Até 2020",TEXT(YEAR(I81),"0")) | N81: =IFERROR(INDEX(DePara!$A:$A,MATCH(TEXT(B81,"0"),DePara!$D:$D,0)),"(sem categoria)") | O81: =IF(J81="","",Parametros!$B$6-J81) | P81: =IF(O81="","",IF(O81>0,1,0))
A82: 2122100000 | B82: IC4420 | C82: NORDEX ENERGY SPAIN S A U | D82: RE | E82: 5002129 | F82: 1957-2 | G82: EUR | H82: -19466.82 | I82: 45166 | J82: 45226 | K82: Fatura - bruto NORDEX ENERGY SPAIN S.A.U. 1957-2 | M82: =IF(YEAR(I82)<=2020,"Até 2020",TEXT(YEAR(I82),"0")) | N82: =IFERROR(INDEX(DePara!$A:$A,MATCH(TEXT(B82,"0"),DePara!$D:$D,0)),"(sem categoria)") | O82: =IF(J82="","",Parametros!$B$6-J82) | P82: =IF(O82="","",IF(O82>0,1,0))
A83: 2122100000 | B83: IC1000 | C83: NORDEX ENERGY SE & CO KG | D83: RE | E83: 5002142 | F83: 4082412983 | G83: EUR | H83: -43259.58 | I83: 45607 | J83: 45637 | K83: 1035/24 | L83: 4082412983 | M83: =IF(YEAR(I83)<=2020,"Até 2020",TEXT(YEAR(I83),"0")) | N83: =IFERROR(INDEX(DePara!$A:$A,MATCH(TEXT(B83,"0"),DePara!$D:$D,0)),"(sem categoria)") | O83: =IF(J83="","",Parametros!$B$6-J83) | P83: =IF(O83="","",IF(O83>0,1,0))
A84: 2122100000 | B84: IC4420 | C84: NORDEX ENERGY SPAIN S A U | D84: RE | E84: 5002175 | F84: 4025008713 | G84: EUR | H84: -257530.17 | I84: 45973 | J84: 46003 | K84: 0869/25 | L84: 4025008713 | M84: =IF(YEAR(I84)<=2020,"Até 2020",TEXT(YEAR(I84),"0")) | N84: =IFERROR(INDEX(DePara!$A:$A,MATCH(TEXT(B84,"0"),DePara!$D:$D,0)),"(sem categoria)") | O84: =IF(J84="","",Parametros!$B$6-J84) | P84: =IF(O84="","",IF(O84>0,1,0))
A85: 2122100000 | B85: IC4420 | C85: NORDEX ENERGY SPAIN S A U | D85: RE | E85: 5002296 | F85: 4025009096 | G85: EUR | H85: -380499.92 | I85: 45987 | J85: 46017 | K85: 0891/25 | L85: 4025009096 | M85: =IF(YEAR(I85)<=2020,"Até 2020",TEXT(YEAR(I85),"0")) | N85: =IFERROR(INDEX(DePara!$A:$A,MATCH(TEXT(B85,"0"),DePara!$D:$D,0)),"(sem categoria)") | O85: =IF(J85="","",Parametros!$B$6-J85) | P85: =IF(O85="","",IF(O85>0,1,0))
A86: 2122100000 | B86: IC1000 | C86: NORDEX ENERGY SE & CO KG | D86: RE | E86: 5002302 | F86: 4012338641 | G86: EUR | H86: -20000.82 | I86: 45092 | J86: 45122 | K86: 0463/23 | L86: 4012338641 | M86: =IF(YEAR(I86)<=2020,"Até 2020",TEXT(YEAR(I86),"0")) | N86: =IFERROR(INDEX(DePara!$A:$A,MATCH(TEXT(B86,"0"),DePara!$D:$D,0)),"(sem categoria)") | O86: =IF(J86="","",Parametros!$B$6-J86) | P86: =IF(O86="","",IF(O86>0,1,0))
A87: 2122100000 | B87: IC1000 | C87: NORDEX ENERGY SE & CO KG | D87: RE | E87: 5002304 | F87: 4012338640 | G87: EUR | H87: -115262.57 | I87: 45092 | J87: 45122 | K87: 0463/23 | L87: 4012338640 | M87: =IF(YEAR(I87)<=2020,"Até 2020",TEXT(YEAR(I87),"0")) | N87: =IFERROR(INDEX(DePara!$A:$A,MATCH(TEXT(B87,"0"),DePara!$D:$D,0)),"(sem categoria)") | O87: =IF(J87="","",Parametros!$B$6-J87) | P87: =IF(O87="","",IF(O87>0,1,0))
A88: 2122100000 | B88: IC1000 | C88: NORDEX ENERGY SE & CO KG | D88: RE | E88: 5002310 | F88: 4012338638 | G88: EUR | H88: -84910.62 | I88: 45092 | J88: 45122 | K88: 0463/23 | L88: 4012338638 | M88: =IF(YEAR(I88)<=2020,"Até 2020",TEXT(YEAR(I88),"0")) | N88: =IFERROR(INDEX(DePara!$A:$A,MATCH(TEXT(B88,"0"),DePara!$D:$D,0)),"(sem categoria)") | O88: =IF(J88="","",Parametros!$B$6-J88) | P88: =IF(O88="","",IF(O88>0,1,0))
A89: 2122100000 | B89: IC1000 | C89: NORDEX ENERGY SE & CO KG | D89: RE | E89: 5002312 | F89: 4012338639 | G89: EUR | H89: -45435.7 | I89: 45092 | J89: 45122 | K89: 0463/23 | L89: 4012338639 | M89: =IF(YEAR(I89)<=2020,"Até 2020",TEXT(YEAR(I89),"0")) | N89: =IFERROR(INDEX(DePara!$A:$A,MATCH(TEXT(B89,"0"),DePara!$D:$D,0)),"(sem categoria)") | O89: =IF(J89="","",Parametros!$B$6-J89) | P89: =IF(O89="","",IF(O89>0,1,0))
A90: 2122100000 | B90: IC1000 | C90: NORDEX ENERGY SE & CO KG | D90: RE | E90: 5002313 | F90: 4012343664 | G90: EUR | H90: -367068.34 | I90: 45097 | J90: 45127 | K90: 0543/23 | L90: 4012343664 | M90: =IF(YEAR(I90)<=2020,"Até 2020",TEXT(YEAR(I90),"0")) | N90: =IFERROR(INDEX(DePara!$A:$A,MATCH(TEXT(B90,"0"),DePara!$D:$D,0)),"(sem categoria)") | O90: =IF(J90="","",Parametros!$B$6-J90) | P90: =IF(O90="","",IF(O90>0,1,0))
A91: 2122100000 | B91: IC4420 | C91: NORDEX ENERGY SPAIN S A U | D91: RE | E91: 5002394 | F91: 4026000275 | G91: EUR | H91: -9662.37 | I91: 46035 | J91: 46065 | K91: 0019/26 | L91: 4026000275 | M91: =IF(YEAR(I91)<=2020,"Até 2020",TEXT(YEAR(I91),"0")) | N91: =IFERROR(INDEX(DePara!$A:$A,MATCH(TEXT(B91,"0"),DePara!$D:$D,0)),"(sem categoria)") | O91: =IF(J91="","",Parametros!$B$6-J91) | P91: =IF(O91="","",IF(O91>0,1,0))
A92: 2122100000 | B92: IC1000 | C92: NORDEX ENERGY SE & CO KG | D92: RE | E92: 5002523 | F92: 4012413022 | G92: EUR | H92: -959152.94 | I92: 45490 | J92: 45520 | K92: 0941/24 | L92: 4012413022 | M92: =IF(YEAR(I92)<=2020,"Até 2020",TEXT(YEAR(I92),"0")) | N92: =IFERROR(INDEX(DePara!$A:$A,MATCH(TEXT(B92,"0"),DePara!$D:$D,0)),"(sem categoria)") | O92: =IF(J92="","",Parametros!$B$6-J92) | P92: =IF(O92="","",IF(O92>0,1,0))
A93: 2122100000 | B93: IC4420 | C93: NORDEX ENERGY SPAIN S A U | D93: RE | E93: 5002557 | F93: 4018000021 | G93: EUR | H93: -844.61 | I93: 46049 | J93: 46079 | K93: 0045/26 | L93: 4018000021 | M93: =IF(YEAR(I93)<=2020,"Até 2020",TEXT(YEAR(I93),"0")) | N93: =IFERROR(INDEX(DePara!$A:$A,MATCH(TEXT(B93,"0"),DePara!$D:$D,0)),"(sem categoria)") | O93: =IF(J93="","",Parametros!$B$6-J93) | P93: =IF(O93="","",IF(O93>0,1,0))
A94: 2122100000 | B94: IC4420 | C94: NORDEX ENERGY SPAIN S A U | D94: RE | E94: 5002572 | F94: 4026000280 | G94: EUR | H94: -10380.62 | I94: 46036 | J94: 46066 | K94: 0024/26 | L94: 4026000280 | M94: =IF(YEAR(I94)<=2020,"Até 2020",TEXT(YEAR(I94),"0")) | N94: =IFERROR(INDEX(DePara!$A:$A,MATCH(TEXT(B94,"0"),DePara!$D:$D,0)),"(sem categoria)") | O94: =IF(J94="","",Parametros!$B$6-J94) | P94: =IF(O94="","",IF(O94>0,1,0))
... A106: 2122100000 | B106: IC4420 | C106: NORDEX ENERGY SPAIN S A U | D106: RE | E106: 5002958 | F106: 4018000180 | G106: EUR | H106: -682265.7 | I106: 45926 | J106: 45956 | K106: 0781/25 | L106: 4018000180 | M106: =IF(YEAR(I106)<=2020,"Até 2020",TEXT(YEAR(I106),"0")) | N106: =IFERROR(INDEX(DePara!$A:$A,MATCH(TEXT(B106,"0"),DePara!$D:$D,0)),"(sem categoria)") | O106: =IF(J106="","",Parametros!$B$6-J106) | P106: =IF(O106="","",IF(O106>0,1,0))
A107: 2122100000 | B107: IC5000 | C107: NORDEX SE | D107: KR | E107: 5002970 | F107: 607297 | G107: EUR | H107: -4525863.5 | I107: 45188 | J107: 45188 | K107: MGM Fee Q3/2023 | M107: =IF(YEAR(I107)<=2020,"Até 2020",TEXT(YEAR(I107),"0")) | N107: =IFERROR(INDEX(DePara!$A:$A,MATCH(TEXT(B107,"0"),DePara!$D:$D,0)),"(sem categoria)") | O107: =IF(J107="","",Parametros!$B$6-J107) | P107: =IF(O107="","",IF(O107>0,1,0))
A108: 2122100000 | B108: IC4420 | C108: NORDEX ENERGY SPAIN S A U | D108: RE | E108: 5002997 | F108: 4025007234 | G108: EUR | H108: -12688.15 | I108: 45919 | J108: 45949 | K108: 0776/25 | L108: 4025007234 | M108: =IF(YEAR(I108)<=2020,"Até 2020",TEXT(YEAR(I108),"0")) | N108: =IFERROR(INDEX(DePara!$A:$A,MATCH(TEXT(B108,"0"),DePara!$D:$D,0)),"(sem categoria)") | O108: =IF(J108="","",Parametros!$B$6-J108) | P108: =IF(O108="","",IF(O108>0,1,0))
A109: 2122100000 | B109: IC4420 | C109: NORDEX ENERGY SPAIN S A U | D109: RE | E109: 5002998 | F109: 4025007227 | G109: EUR | H109: -64624 | I109: 45919 | J109: 45949 | K109: 0776/25 | L109: 4025007227 | M109: =IF(YEAR(I109)<=2020,"Até 2020",TEXT(YEAR(I109),"0")) | N109: =IFERROR(INDEX(DePara!$A:$A,MATCH(TEXT(B109,"0"),DePara!$D:$D,0)),"(sem categoria)") | O109: =IF(J109="","",Parametros!$B$6-J109) | P109: =IF(O109="","",IF(O109>0,1,0))
A110: 2122100000 | B110: IC4420 | C110: NORDEX ENERGY SPAIN S A U | D110: RE | E110: 5002999 | F110: 4025007229 | G110: EUR | H110: -40201.64 | I110: 45919 | J110: 45949 | K110: 0776/25 | L110: 4025007229 | M110: =IF(YEAR(I110)<=2020,"Até 2020",TEXT(YEAR(I110),"0")) | N110: =IFERROR(INDEX(DePara!$A:$A,MATCH(TEXT(B110,"0"),DePara!$D:$D,0)),"(sem categoria)") | O110: =IF(J110="","",Parametros!$B$6-J110) | P110: =IF(O110="","",IF(O110>0,1,0))
A111: 2122100000 | B111: IC4420 | C111: NORDEX ENERGY SPAIN S A U | D111: RE | E111: 5003003 | F111: 4025009058 | G111: EUR | H111: -192284.3 | I111: 45986 | J111: 46016 | K111: 0943/25 | L111: 4025009058 | M111: =IF(YEAR(I111)<=2020,"Até 2020",TEXT(YEAR(I111),"0")) | N111: =IFERROR(INDEX(DePara!$A:$A,MATCH(TEXT(B111,"0"),DePara!$D:$D,0)),"(sem categoria)") | O111: =IF(J111="","",Parametros!$B$6-J111) | P111: =IF(O111="","",IF(O111>0,1,0))
A112: 2122100000 | B112: IC4420 | C112: NORDEX ENERGY SPAIN S A U | D112: RE | E112: 5003007 | F112: 4025008444 | G112: EUR | H112: -259641.39 | I112: 45960 | J112: 45990 | K112: 0864/25 | L112: 4025008444 | M112: =IF(YEAR(I112)<=2020,"Até 2020",TEXT(YEAR(I112),"0")) | N112: =IFERROR(INDEX(DePara!$A:$A,MATCH(TEXT(B112,"0"),DePara!$D:$D,0)),"(sem categoria)") | O112: =IF(J112="","",Parametros!$B$6-J112) | P112: =IF(O112="","",IF(O112>0,1,0))
A113: 2122100000 | B113: IC4420 | C113: NORDEX ENERGY SPAIN S A U | D113: RE | E113: 5003131 | F113: 4026000004 | G113: EUR | H113: -2885.49 | I113: 46024 | J113: 46054 | K113: 0004/26 | L113: 4026000004 | M113: =IF(YEAR(I113)<=2020,"Até 2020",TEXT(YEAR(I113),"0")) | N113: =IFERROR(INDEX(DePara!$A:$A,MATCH(TEXT(B113,"0"),DePara!$D:$D,0)),"(sem categoria)") | O113: =IF(J113="","",Parametros!$B$6-J113) | P113: =IF(O113="","",IF(O113>0,1,0))
A114: 2122100000 | B114: IC1000 | C114: NORDEX ENERGY SE & CO KG | D114: RE | E114: 5003203 | F114: 638-2 | G114: EUR | H114: -106231.15 | I114: 45184 | J114: 45214 | K114: Fatura - bruto NORDEX ENERGY SE & CO. KG 638-2 | M114: =IF(YEAR(I114)<=2020,"Até 2020",TEXT(YEAR(I114),"0")) | N114: =IFERROR(INDEX(DePara!$A:$A,MATCH(TEXT(B114,"0"),DePara!$D:$D,0)),"(sem categoria)") | O114: =IF(J114="","",Parametros!$B$6-J114) | P114: =IF(O114="","",IF(O114>0,1,0))
A115: 2122100000 | B115: IC1000 | C115: NORDEX ENERGY SE & CO KG | D115: RE | E115: 5003256 | F115: 381358 | G115: EUR | H115: -54247.77 | I115: 46050 | J115: 46080 | K115: 0051/26 | L115: 381358 | M115: =IF(YEAR(I115)<=2020,"Até 2020",TEXT(YEAR(I115),"0")) | N115: =IFERROR(INDEX(DePara!$A:$A,MATCH(TEXT(B115,"0"),DePara!$D:$D,0)),"(sem categoria)") | O115: =IF(J115="","",Parametros!$B$6-J115) | P115: =IF(O115="","",IF(O115>0,1,0))
A116: 2122100000 | B116: IC4420 | C116: NORDEX ENERGY SPAIN S A U | D116: RE | E116: 5003257 | F116: 4026000822 | G116: EUR | H116: -59706.3 | I116: 46057 | J116: 46087 | K116: 0055/26 | L116: 4026000822 | M116: =IF(YEAR(I116)<=2020,"Até 2020",TEXT(YEAR(I116),"0")) | N116: =IFERROR(INDEX(DePara!$A:$A,MATCH(TEXT(B116,"0"),DePara!$D:$D,0)),"(sem categoria)") | O116: =IF(J116="","",Parametros!$B$6-J116) | P116: =IF(O116="","",IF(O116>0,1,0))
A117: 2122100000 | B117: IC4420 | C117: NORDEX ENERGY SPAIN S A U | D117: RE | E117: 5003294 | F117: 4025009069 | G117: EUR | H117: -422046.17 | I117: 45986 | J117: 46016 | K117: 0943/25 | L117: 4025009069 | M117: =IF(YEAR(I117)<=2020,"Até 2020",TEXT(YEAR(I117),"0")) | N117: =IFERROR(INDEX(DePara!$A:$A,MATCH(TEXT(B117,"0"),DePara!$D:$D,0)),"(sem categoria)") | O117: =IF(J117="","",Parametros!$B$6-J117) | P117: =IF(O117="","",IF(O117>0,1,0))
A118: 2122100000 | B118: IC4420 | C118: NORDEX ENERGY SPAIN S A U | D118: RE | E118: 5003309 | F118: 4026000825 | G118: EUR | H118: -417730.52 | I118: 46057 | J118: 46087 | K118: 0052/26 | L118: 4026000825 | M118: =IF(YEAR(I118)<=2020,"Até 2020",TEXT(YEAR(I118),"0")) | N118: =IFERROR(INDEX(DePara!$A:$A,MATCH(TEXT(B118,"0"),DePara!$D:$D,0)),"(sem categoria)") | O118: =IF(J118="","",Parametros!$B$6-J118) | P118: =IF(O118="","",IF(O118>0,1,0))
A119: 2122100000 | B119: IC4420 | C119: NORDEX ENERGY SPAIN S A U | D119: RE | E119: 5003310 | F119: 4026000828 | G119: EUR | H119: -1943.11 | I119: 46057 | J119: 46087 | K119: 0052/26 | L119: 4026000828 | M119: =IF(YEAR(I119)<=2020,"Até 2020",TEXT(YEAR(I119),"0")) | N119: =IFERROR(INDEX(DePara!$A:$A,MATCH(TEXT(B119,"0"),DePara!$D:$D,0)),"(sem categoria)") | O119: =IF(J119="","",Parametros!$B$6-J119) | P119: =IF(O119="","",IF(O119>0,1,0))
A120: 2122100000 | B120: IC4420 | C120: NORDEX ENERGY SPAIN S A U | D120: RE | E120: 5003319 | F120: 4026000544 | G120: EUR | H120: -329234.99 | I120: 46048 | J120: 46078 | K120: 0048/26 | L120: 4026000544 | M120: =IF(YEAR(I120)<=2020,"Até 2020",TEXT(YEAR(I120),"0")) | N120: =IFERROR(INDEX(DePara!$A:$A,MATCH(TEXT(B120,"0"),DePara!$D:$D,0)),"(sem categoria)") | O120: =IF(J120="","",Parametros!$B$6-J120) | P120: =IF(O120="","",IF(O120>0,1,0))
A121: 2122100000 | B121: IC4420 | C121: NORDEX ENERGY SPAIN S A U | D121: RE | E121: 5003329 | F121: 4025008825 | G121: EUR | H121: -251067.47 | I121: 45975 | J121: 46005 | K121: 0902/25 | L121: 4025008825 | M121: =IF(YEAR(I121)<=2020,"Até 2020",TEXT(YEAR(I121),"0")) | N121: =IFERROR(INDEX(DePara!$A:$A,MATCH(TEXT(B121,"0"),DePara!$D:$D,0)),"(sem categoria)") | O121: =IF(J121="","",Parametros!$B$6-J121) | P121: =IF(O121="","",IF(O121>0,1,0))
A122: 2122100000 | B122: IC4420 | C122: NORDEX ENERGY SPAIN S A U | D122: RE | E122: 5003330 | F122: 4025008826 | G122: EUR | H122: -251067.47 | I122: 45975 | J122: 46005 | K122: 0902/25 | L122: 4025008826 | M122: =IF(YEAR(I122)<=2020,"Até 2020",TEXT(YEAR(I122),"0")) | N122: =IFERROR(INDEX(DePara!$A:$A,MATCH(TEXT(B122,"0"),DePara!$D:$D,0)),"(sem categoria)") | O122: =IF(J122="","",Parametros!$B$6-J122) | P122: =IF(O122="","",IF(O122>0,1,0))
A123: 2122100000 | B123: IC4420 | C123: NORDEX ENERGY SPAIN S A U | D123: RE | E123: 5003331 | F123: 4025008813 | G123: EUR | H123: -251067.47 | I123: 45975 | J123: 46005 | K123: 0902/25 | L123: 4025008813 | M123: =IF(YEAR(I123)<=2020,"Até 2020",TEXT(YEAR(I123),"0")) | N123: =IFERROR(INDEX(DePara!$A:$A,MATCH(TEXT(B123,"0"),DePara!$D:$D,0)),"(sem categoria)") | O123: =IF(J123="","",Parametros!$B$6-J123) | P123: =IF(O123="","",IF(O123>0,1,0))
A124: 2122100000 | B124: IC4420 | C124: NORDEX ENERGY SPAIN S A U | D124: RE | E124: 5003354 | F124: 4025007246 | G124: EUR | H124: -108495.38 | I124: 45919 | J124: 45949 | K124: 0784/25 | L124: 4025007246 | M124: =IF(YEAR(I124)<=2020,"Até 2020",TEXT(YEAR(I124),"0")) | N124: =IFERROR(INDEX(DePara!$A:$A,MATCH(TEXT(B124,"0"),DePara!$D:$D,0)),"(sem categoria)") | O124: =IF(J124="","",Parametros!$B$6-J124) | P124: =IF(O124="","",IF(O124>0,1,0))
A125: 2122100000 | B125: IC4420 | C125: NORDEX ENERGY SPAIN S A U | D125: RE | E125: 5003367 | F125: 4018000262 | G125: EUR | H125: -833028.94 | I125: 46000 | J125: 46030 | K125: 0928/25 | L125: 4018000262 | M125: =IF(YEAR(I125)<=2020,"Até 2020",TEXT(YEAR(I125),"0")) | N125: =IFERROR(INDEX(DePara!$A:$A,MATCH(TEXT(B125,"0"),DePara!$D:$D,0)),"(sem categoria)") | O125: =IF(J125="","",Parametros!$B$6-J125) | P125: =IF(O125="","",IF(O125>0,1,0))
A126: 2122100000 | B126: IC4420 | C126: NORDEX ENERGY SPAIN S A U | D126: RE | E126: 5003427 | F126: 4024008347 | G126: EUR | H126: -572422.58 | I126: 45616 | J126: 45646 | K126: 1094/24 | L126: 4024008347 | M126: =IF(YEAR(I126)<=2020,"Até 2020",TEXT(YEAR(I126),"0")) | N126: =IFERROR(INDEX(DePara!$A:$A,MATCH(TEXT(B126,"0"),DePara!$D:$D,0)),"(sem categoria)") | O126: =IF(J126="","",Parametros!$B$6-J126) | P126: =IF(O126="","",IF(O126>0,1,0))
... A149: 2122100000 | B149: IC4420 | C149: NORDEX ENERGY SPAIN S A U | D149: RE | E149: 5003851 | F149: 4026000927 | G149: EUR | H149: -40210.4 | I149: 46059 | J149: 46089 | K149: 0067/26 | L149: 4026000927 | M149: =IF(YEAR(I149)<=2020,"Até 2020",TEXT(YEAR(I149),"0")) | N149: =IFERROR(INDEX(DePara!$A:$A,MATCH(TEXT(B149,"0"),DePara!$D:$D,0)),"(sem categoria)") | O149: =IF(J149="","",Parametros!$B$6-J149) | P149: =IF(O149="","",IF(O149>0,1,0))
A150: 2122100000 | B150: IC4420 | C150: NORDEX ENERGY SPAIN S A U | D150: KR | E150: 5003866 | F150: 4025000404 | G150: EUR | H150: -375156.6 | I150: 45677 | J150: 45707 | K150: Vendor Invoice NORDEX ENERGY SPAIN S A U 402500040 | M150: =IF(YEAR(I150)<=2020,"Até 2020",TEXT(YEAR(I150),"0")) | N150: =IFERROR(INDEX(DePara!$A:$A,MATCH(TEXT(B150,"0"),DePara!$D:$D,0)),"(sem categoria)") | O150: =IF(J150="","",Parametros!$B$6-J150) | P150: =IF(O150="","",IF(O150>0,1,0))
A151: 2122100000 | B151: IC4420 | C151: NORDEX ENERGY SPAIN S A U | D151: RE | E151: 5003913 | F151: 4026000821 | G151: EUR | H151: -6135.55 | I151: 46057 | J151: 46087 | K151: 0066/26 | L151: 4026000821 | M151: =IF(YEAR(I151)<=2020,"Até 2020",TEXT(YEAR(I151),"0")) | N151: =IFERROR(INDEX(DePara!$A:$A,MATCH(TEXT(B151,"0"),DePara!$D:$D,0)),"(sem categoria)") | O151: =IF(J151="","",Parametros!$B$6-J151) | P151: =IF(O151="","",IF(O151>0,1,0))
A152: 2122100000 | B152: IC4420 | C152: NORDEX ENERGY SPAIN S A U | D152: RE | E152: 5003914 | F152: 4026000692 | G152: EUR | H152: -105225.4 | I152: 46051 | J152: 46081 | K152: 0050/26 | L152: 4026000692 | M152: =IF(YEAR(I152)<=2020,"Até 2020",TEXT(YEAR(I152),"0")) | N152: =IFERROR(INDEX(DePara!$A:$A,MATCH(TEXT(B152,"0"),DePara!$D:$D,0)),"(sem categoria)") | O152: =IF(J152="","",Parametros!$B$6-J152) | P152: =IF(O152="","",IF(O152>0,1,0))
A153: 2122100000 | B153: IC4420 | C153: NORDEX ENERGY SPAIN S A U | D153: RE | E153: 5003917 | F153: 4026001019 | G153: EUR | H153: -24564.89 | I153: 46063 | J153: 46093 | K153: 0072/26 | L153: 4026001019 | M153: =IF(YEAR(I153)<=2020,"Até 2020",TEXT(YEAR(I153),"0")) | N153: =IFERROR(INDEX(DePara!$A:$A,MATCH(TEXT(B153,"0"),DePara!$D:$D,0)),"(sem categoria)") | O153: =IF(J153="","",Parametros!$B$6-J153) | P153: =IF(O153="","",IF(O153>0,1,0))
A154: 2122100000 | B154: IC4420 | C154: NORDEX ENERGY SPAIN S A U | D154: RE | E154: 5004021 | F154: 4026000602 | G154: EUR | H154: -177.66 | I154: 46049 | J154: 46079 | K154: 0062/26 | L154: 4026000602 | M154: =IF(YEAR(I154)<=2020,"Até 2020",TEXT(YEAR(I154),"0")) | N154: =IFERROR(INDEX(DePara!$A:$A,MATCH(TEXT(B154,"0"),DePara!$D:$D,0)),"(sem categoria)") | O154: =IF(J154="","",Parametros!$B$6-J154) | P154: =IF(O154="","",IF(O154>0,1,0))
A155: 2122100000 | B155: IC1000 | C155: NORDEX ENERGY SE & CO KG | D155: RE | E155: 5004078 | F155: 4012425230 | G155: EUR | H155: -872812.03 | I155: 45637 | J155: 45667 | K155: 1132/24 | L155: 4012425230 | M155: =IF(YEAR(I155)<=2020,"Até 2020",TEXT(YEAR(I155),"0")) | N155: =IFERROR(INDEX(DePara!$A:$A,MATCH(TEXT(B155,"0"),DePara!$D:$D,0)),"(sem categoria)") | O155: =IF(J155="","",Parametros!$B$6-J155) | P155: =IF(O155="","",IF(O155>0,1,0))
A156: 2122100000 | B156: IC1000 | C156: NORDEX ENERGY SE & CO KG | D156: RE | E156: 5004194 | F156: 314841 | G156: EUR | H156: -1260599.9 | I156: 45593 | J156: 45623 | K156: 1102/24 | L156: 314841 | M156: =IF(YEAR(I156)<=2020,"Até 2020",TEXT(YEAR(I156),"0")) | N156: =IFERROR(INDEX(DePara!$A:$A,MATCH(TEXT(B156,"0"),DePara!$D:$D,0)),"(sem categoria)") | O156: =IF(J156="","",Parametros!$B$6-J156) | P156: =IF(O156="","",IF(O156>0,1,0))
A157: 2122100000 | B157: IC4420 | C157: NORDEX ENERGY SPAIN S A U | D157: RE | E157: 5004202 | F157: 4026000447 | G157: EUR | H157: -200808.83 | I157: 46043 | J157: 46073 | K157: 0043/26 | L157: 4026000447 | M157: =IF(YEAR(I157)<=2020,"Até 2020",TEXT(YEAR(I157),"0")) | N157: =IFERROR(INDEX(DePara!$A:$A,MATCH(TEXT(B157,"0"),DePara!$D:$D,0)),"(sem categoria)") | O157: =IF(J157="","",Parametros!$B$6-J157) | P157: =IF(O157="","",IF(O157>0,1,0))
A158: 2122100000 | B158: IC4420 | C158: NORDEX ENERGY SPAIN S A U | D158: RE | E158: 5004203 | F158: 4026000885 | G158: EUR | H158: -44785.21 | I158: 46058 | J158: 46088 | K158: 0058/26 | L158: 4026000885 | M158: =IF(YEAR(I158)<=2020,"Até 2020",TEXT(YEAR(I158),"0")) | N158: =IFERROR(INDEX(DePara!$A:$A,MATCH(TEXT(B158,"0"),DePara!$D:$D,0)),"(sem categoria)") | O158: =IF(J158="","",Parametros!$B$6-J158) | P158: =IF(O158="","",IF(O158>0,1,0))
A159: 2122100000 | B159: IC1000 | C159: NORDEX ENERGY SE & CO KG | D159: KR | E159: 5004214 | F159: 6188993 | G159: EUR | H159: -13397231 | I159: 45316 | J159: 45346 | K159: Fatura do fornecedor NORDEX ENERGY SE & CO. KG 618 | M159: =IF(YEAR(I159)<=2020,"Até 2020",TEXT(YEAR(I159),"0")) | N159: =IFERROR(INDEX(DePara!$A:$A,MATCH(TEXT(B159,"0"),DePara!$D:$D,0)),"(sem categoria)") | O159: =IF(J159="","",Parametros!$B$6-J159) | P159: =IF(O159="","",IF(O159>0,1,0))
A160: 2122100000 | B160: IC4420 | C160: NORDEX ENERGY SPAIN S A U | D160: RE | E160: 5004224 | F160: 4026000827 | G160: EUR | H160: -14.19 | I160: 46026 | J160: 46056 | K160: 0053/26 | L160: 4026000827 | M160: =IF(YEAR(I160)<=2020,"Até 2020",TEXT(YEAR(I160),"0")) | N160: =IFERROR(INDEX(DePara!$A:$A,MATCH(TEXT(B160,"0"),DePara!$D:$D,0)),"(sem categoria)") | O160: =IF(J160="","",Parametros!$B$6-J160) | P160: =IF(O160="","",IF(O160>0,1,0))
A161: 2122100000 | B161: IC4420 | C161: NORDEX ENERGY SPAIN S A U | D161: RE | E161: 5004249 | F161: 4026000020 | G161: EUR | H161: -1357459.6 | I161: 46024 | J161: 46054 | K161: 0013/26 | L161: 4026000020 | M161: =IF(YEAR(I161)<=2020,"Até 2020",TEXT(YEAR(I161),"0")) | N161: =IFERROR(INDEX(DePara!$A:$A,MATCH(TEXT(B161,"0"),DePara!$D:$D,0)),"(sem categoria)") | O161: =IF(J161="","",Parametros!$B$6-J161) | P161: =IF(O161="","",IF(O161>0,1,0))
A162: 2122100000 | B162: IC4420 | C162: NORDEX ENERGY SPAIN S A U | D162: RE | E162: 5004250 | F162: 4018000051 | G162: EUR | H162: -85718.63 | I162: 46080 | J162: 46110 | K162: 0104/26 | L162: 4018000051 | M162: =IF(YEAR(I162)<=2020,"Até 2020",TEXT(YEAR(I162),"0")) | N162: =IFERROR(INDEX(DePara!$A:$A,MATCH(TEXT(B162,"0"),DePara!$D:$D,0)),"(sem categoria)") | O162: =IF(J162="","",Parametros!$B$6-J162) | P162: =IF(O162="","",IF(O162>0,1,0))
A163: 2122100000 | B163: IC4420 | C163: NORDEX ENERGY SPAIN S A U | D163: RE | E163: 5004268 | F163: 4025009235 | G163: EUR | H163: -247651.34 | I163: 45989 | J163: 46019 | K163: 0909/25 | L163: 4025009235 | M163: =IF(YEAR(I163)<=2020,"Até 2020",TEXT(YEAR(I163),"0")) | N163: =IFERROR(INDEX(DePara!$A:$A,MATCH(TEXT(B163,"0"),DePara!$D:$D,0)),"(sem categoria)") | O163: =IF(J163="","",Parametros!$B$6-J163) | P163: =IF(O163="","",IF(O163>0,1,0))
A164: 2122100000 | B164: IC4420 | C164: NORDEX ENERGY SPAIN S A U | D164: RE | E164: 5004269 | F164: 4025009688 | G164: EUR | H164: -834364.1 | I164: 46006 | J164: 46036 | K164: 0933/25 | L164: 4025009688 | M164: =IF(YEAR(I164)<=2020,"Até 2020",TEXT(YEAR(I164),"0")) | N164: =IFERROR(INDEX(DePara!$A:$A,MATCH(TEXT(B164,"0"),DePara!$D:$D,0)),"(sem categoria)") | O164: =IF(J164="","",Parametros!$B$6-J164) | P164: =IF(O164="","",IF(O164>0,1,0))
A165: 2122100000 | B165: IC4420 | C165: NORDEX ENERGY SPAIN S A U | D165: RE | E165: 5004270 | F165: 4025009236 | G165: EUR | H165: -247651.34 | I165: 45989 | J165: 46019 | K165: 0909/25 | L165: 4025009236 | M165: =IF(YEAR(I165)<=2020,"Até 2020",TEXT(YEAR(I165),"0")) | N165: =IFERROR(INDEX(DePara!$A:$A,MATCH(TEXT(B165,"0"),DePara!$D:$D,0)),"(sem categoria)") | O165: =IF(J165="","",Parametros!$B$6-J165) | P165: =IF(O165="","",IF(O165>0,1,0))
A166: 2122100000 | B166: IC4420 | C166: NORDEX ENERGY SPAIN S A U | D166: RE | E166: 5004272 | F166: 4025009234 | G166: EUR | H166: -247651.34 | I166: 45989 | J166: 46019 | K166: 0909/25 | L166: 4025009234 | M166: =IF(YEAR(I166)<=2020,"Até 2020",TEXT(YEAR(I166),"0")) | N166: =IFERROR(INDEX(DePara!$A:$A,MATCH(TEXT(B166,"0"),DePara!$D:$D,0)),"(sem categoria)") | O166: =IF(J166="","",Parametros!$B$6-J166) | P166: =IF(O166="","",IF(O166>0,1,0))
A167: 2122100000 | B167: IC4420 | C167: NORDEX ENERGY SPAIN S A U | D167: RE | E167: 5004310 | F167: 4025008994 | G167: EUR | H167: -1319.03 | I167: 45981 | J167: 46011 | K167: 0879/25 | L167: 4025008994 | M167: =IF(YEAR(I167)<=2020,"Até 2020",TEXT(YEAR(I167),"0")) | N167: =IFERROR(INDEX(DePara!$A:$A,MATCH(TEXT(B167,"0"),DePara!$D:$D,0)),"(sem categoria)") | O167: =IF(J167="","",Parametros!$B$6-J167) | P167: =IF(O167="","",IF(O167>0,1,0))
A168: 2122100000 | B168: IC1000 | C168: NORDEX ENERGY SE & CO KG | D168: RE | E168: 5004456 | F168: 318774 | G168: EUR | H168: -5030.61 | I168: 45636 | J168: 45666 | K168: 1153/24 | L168: 318774 | M168: =IF(YEAR(I168)<=2020,"Até 2020",TEXT(YEAR(I168),"0")) | N168: =IFERROR(INDEX(DePara!$A:$A,MATCH(TEXT(B168,"0"),DePara!$D:$D,0)),"(sem categoria)") | O168: =IF(J168="","",Parametros!$B$6-J168) | P168: =IF(O168="","",IF(O168>0,1,0))
A169: 2122100000 | B169: IC1000 | C169: NORDEX ENERGY SE & CO KG | D169: RE | E169: 5004463 | F169: 322024 | G169: EUR | H169: -28189.61 | I169: 45643 | J169: 45673 | K169: 1168/24 | L169: 322024 | M169: =IF(YEAR(I169)<=2020,"Até 2020",TEXT(YEAR(I169),"0")) | N169: =IFERROR(INDEX(DePara!$A:$A,MATCH(TEXT(B169,"0"),DePara!$D:$D,0)),"(sem categoria)") | O169: =IF(J169="","",Parametros!$B$6-J169) | P169: =IF(O169="","",IF(O169>0,1,0))
A170: 2122100000 | B170: IC4420 | C170: NORDEX ENERGY SPAIN S A U | D170: RE | E170: 5004486 | F170: 4025009054 | G170: EUR | H170: -1095159.3 | I170: 45986 | J170: 46016 | K170: 0854/25 | L170: 4025009054 | M170: =IF(YEAR(I170)<=2020,"Até 2020",TEXT(YEAR(I170),"0")) | N170: =IFERROR(INDEX(DePara!$A:$A,MATCH(TEXT(B170,"0"),DePara!$D:$D,0)),"(sem categoria)") | O170: =IF(J170="","",Parametros!$B$6-J170) | P170: =IF(O170="","",IF(O170>0,1,0))
A171: 2122100000 | B171: IC4420 | C171: NORDEX ENERGY SPAIN S A U | D171: RE | E171: 5004487 | F171: 4025009255 | G171: EUR | H171: -247651.34 | I171: 45989 | J171: 46019 | K171: 0913/25 | L171: 4025009255 | M171: =IF(YEAR(I171)<=2020,"Até 2020",TEXT(YEAR(I171),"0")) | N171: =IFERROR(INDEX(DePara!$A:$A,MATCH(TEXT(B171,"0"),DePara!$D:$D,0)),"(sem categoria)") | O171: =IF(J171="","",Parametros!$B$6-J171) | P171: =IF(O171="","",IF(O171>0,1,0))
... A263: 2122100000 | B263: IC4420 | C263: NORDEX ENERGY SPAIN S A U | D263: RE | E263: 5005869 | F263: 4026001431 | G263: EUR | H263: -42077.9 | I263: 46080 | J263: 46110 | K263: 0110/26 | L263: 4026001431 | M263: =IF(YEAR(I263)<=2020,"Até 2020",TEXT(YEAR(I263),"0")) | N263: =IFERROR(INDEX(DePara!$A:$A,MATCH(TEXT(B263,"0"),DePara!$D:$D,0)),"(sem categoria)") | O263: =IF(J263="","",Parametros!$B$6-J263) | P263: =IF(O263="","",IF(O263>0,1,0))
A264: 2122100000 | B264: IC1000 | C264: NORDEX ENERGY SE & CO KG | D264: KR | E264: 5006054 | F264: 621578 | G264: EUR | H264: -9410958.1 | I264: 45687 | J264: 45717 | K264: Vendor Invoice NORDEX ENERGY SE & CO KG 621578 | M264: =IF(YEAR(I264)<=2020,"Até 2020",TEXT(YEAR(I264),"0")) | N264: =IFERROR(INDEX(DePara!$A:$A,MATCH(TEXT(B264,"0"),DePara!$D:$D,0)),"(sem categoria)") | O264: =IF(J264="","",Parametros!$B$6-J264) | P264: =IF(O264="","",IF(O264>0,1,0))
A265: 2122100000 | B265: IC1000 | C265: NORDEX ENERGY SE & CO KG | D265: RE | E265: 5006105 | F265: 310147 | G265: EUR | H265: -27785.93 | I265: 45560 | J265: 45590 | K265: 0053/25 | L265: 310147 | M265: =IF(YEAR(I265)<=2020,"Até 2020",TEXT(YEAR(I265),"0")) | N265: =IFERROR(INDEX(DePara!$A:$A,MATCH(TEXT(B265,"0"),DePara!$D:$D,0)),"(sem categoria)") | O265: =IF(J265="","",Parametros!$B$6-J265) | P265: =IF(O265="","",IF(O265>0,1,0))
A266: 2122100000 | B266: IC4420 | C266: NORDEX ENERGY SPAIN S A U | D266: RE | E266: 5006122 | F266: 4026001639 | G266: EUR | H266: -64823.54 | I266: 46087 | J266: 46117 | K266: 0148/26 | L266: 4026001639 | M266: =IF(YEAR(I266)<=2020,"Até 2020",TEXT(YEAR(I266),"0")) | N266: =IFERROR(INDEX(DePara!$A:$A,MATCH(TEXT(B266,"0"),DePara!$D:$D,0)),"(sem categoria)") | O266: =IF(J266="","",Parametros!$B$6-J266) | P266: =IF(O266="","",IF(O266>0,1,0))
A267: 2122100000 | B267: IC4420 | C267: NORDEX ENERGY SPAIN S A U | D267: RE | E267: 5006123 | F267: 4026001674 | G267: EUR | H267: -19544.35 | I267: 46090 | J267: 46120 | K267: 0143/26 | L267: 4026001674 | M267: =IF(YEAR(I267)<=2020,"Até 2020",TEXT(YEAR(I267),"0")) | N267: =IFERROR(INDEX(DePara!$A:$A,MATCH(TEXT(B267,"0"),DePara!$D:$D,0)),"(sem categoria)") | O267: =IF(J267="","",Parametros!$B$6-J267) | P267: =IF(O267="","",IF(O267>0,1,0))
A268: 2122100000 | B268: IC4420 | C268: NORDEX ENERGY SPAIN S A U | D268: RE | E268: 5006124 | F268: 4026001434 | G268: EUR | H268: -5585.51 | I268: 46080 | J268: 46110 | K268: 0113/26 | L268: 4026001434 | M268: =IF(YEAR(I268)<=2020,"Até 2020",TEXT(YEAR(I268),"0")) | N268: =IFERROR(INDEX(DePara!$A:$A,MATCH(TEXT(B268,"0"),DePara!$D:$D,0)),"(sem categoria)") | O268: =IF(J268="","",Parametros!$B$6-J268) | P268: =IF(O268="","",IF(O268>0,1,0))
A269: 2122100000 | B269: IC5000 | C269: NORDEX SE | D269: KG | E269: 5006184 | F269: 607864 | G269: EUR | H269: 4518668.5 | I269: 45335 | J269: 45335 | K269: Nota crédito fornec. NORDEX SE 607864 | M269: =IF(YEAR(I269)<=2020,"Até 2020",TEXT(YEAR(I269),"0")) | N269: =IFERROR(INDEX(DePara!$A:$A,MATCH(TEXT(B269,"0"),DePara!$D:$D,0)),"(sem categoria)") | O269: =IF(J269="","",Parametros!$B$6-J269) | P269: =IF(O269="","",IF(O269>0,1,0))
A270: 2122100000 | B270: IC1000 | C270: NORDEX ENERGY SE & CO KG | D270: RE | E270: 5006184 | F270: 326399 | G270: EUR | H270: -6049.37 | I270: 45672 | J270: 45702 | K270: 0080/25 | L270: 326399 | M270: =IF(YEAR(I270)<=2020,"Até 2020",TEXT(YEAR(I270),"0")) | N270: =IFERROR(INDEX(DePara!$A:$A,MATCH(TEXT(B270,"0"),DePara!$D:$D,0)),"(sem categoria)") | O270: =IF(J270="","",Parametros!$B$6-J270) | P270: =IF(O270="","",IF(O270>0,1,0))
A271: 2122100000 | B271: IC4420 | C271: NORDEX ENERGY SPAIN S A U | D271: RE | E271: 5006226 | F271: 4026001682 | G271: EUR | H271: -3652.61 | I271: 46059 | J271: 46089 | K271: 0160/26 | L271: 4026001682 | M271: =IF(YEAR(I271)<=2020,"Até 2020",TEXT(YEAR(I271),"0")) | N271: =IFERROR(INDEX(DePara!$A:$A,MATCH(TEXT(B271,"0"),DePara!$D:$D,0)),"(sem categoria)") | O271: =IF(J271="","",Parametros!$B$6-J271) | P271: =IF(O271="","",IF(O271>0,1,0))
A272: 2122100000 | B272: IC4420 | C272: NORDEX ENERGY SPAIN S A U | D272: RE | E272: 5006252 | F272: 4026001430 | G272: EUR | H272: -45780.64 | I272: 46080 | J272: 46110 | K272: 0109/26 | L272: 4026001430 | M272: =IF(YEAR(I272)<=2020,"Até 2020",TEXT(YEAR(I272),"0")) | N272: =IFERROR(INDEX(DePara!$A:$A,MATCH(TEXT(B272,"0"),DePara!$D:$D,0)),"(sem categoria)") | O272: =IF(J272="","",Parametros!$B$6-J272) | P272: =IF(O272="","",IF(O272>0,1,0))
A273: 2122100000 | B273: IC4420 | C273: NORDEX ENERGY SPAIN S A U | D273: RE | E273: 5006275 | F273: 4026001069 | G273: EUR | H273: -25275.54 | I273: 46065 | J273: 46095 | K273: 0077/26 | L273: 4026001069 | M273: =IF(YEAR(I273)<=2020,"Até 2020",TEXT(YEAR(I273),"0")) | N273: =IFERROR(INDEX(DePara!$A:$A,MATCH(TEXT(B273,"0"),DePara!$D:$D,0)),"(sem categoria)") | O273: =IF(J273="","",Parametros!$B$6-J273) | P273: =IF(O273="","",IF(O273>0,1,0))
A274: 2122100000 | B274: IC4420 | C274: NORDEX ENERGY SPAIN S A U | D274: RE | E274: 5006341 | F274: 4026000892 | G274: EUR | H274: -7066.4 | I274: 46058 | J274: 46088 | K274: 0056/26 | L274: 4026000892 | M274: =IF(YEAR(I274)<=2020,"Até 2020",TEXT(YEAR(I274),"0")) | N274: =IFERROR(INDEX(DePara!$A:$A,MATCH(TEXT(B274,"0"),DePara!$D:$D,0)),"(sem categoria)") | O274: =IF(J274="","",Parametros!$B$6-J274) | P274: =IF(O274="","",IF(O274>0,1,0))
A275: 2122100000 | B275: IC4420 | C275: NORDEX ENERGY SPAIN S A U | D275: RE | E275: 5006342 | F275: 4026000890 | G275: EUR | H275: -20173.51 | I275: 46058 | J275: 46088 | K275: 0056/26 | L275: 4026000890 | M275: =IF(YEAR(I275)<=2020,"Até 2020",TEXT(YEAR(I275),"0")) | N275: =IFERROR(INDEX(DePara!$A:$A,MATCH(TEXT(B275,"0"),DePara!$D:$D,0)),"(sem categoria)") | O275: =IF(J275="","",Parametros!$B$6-J275) | P275: =IF(O275="","",IF(O275>0,1,0))
A276: 2122100000 | B276: IC4420 | C276: NORDEX ENERGY SPAIN S A U | D276: RE | E276: 5006343 | F276: 4026000893 | G276: EUR | H276: -49619.26 | I276: 46058 | J276: 46088 | K276: 0056/26 | L276: 4026000893 | M276: =IF(YEAR(I276)<=2020,"Até 2020",TEXT(YEAR(I276),"0")) | N276: =IFERROR(INDEX(DePara!$A:$A,MATCH(TEXT(B276,"0"),DePara!$D:$D,0)),"(sem categoria)") | O276: =IF(J276="","",Parametros!$B$6-J276) | P276: =IF(O276="","",IF(O276>0,1,0))
...

Sheet DePara
A1: Categoria | B1: Nome do fornecedor | C1: Fornecedor | D1: Fornecedor_txt
A2: Other Suppliers | C2: 100002 | D2: 100002
A3: Other Suppliers | C3: 100003 | D3: 100003
A4: Operational Suppliers (Wind Farms) | C4: 100007 | D4: 100007
A5: Other Suppliers | B5: DB3 SERVICOS DE TELECOMUNICACOES SA | C5: 100008 | D5: 100008
A6: Other Suppliers | B6: TRANSITEX DO BRASIL SERVIÇOS DE LO | C6: 100014 | D6: 100014
A7: Other Suppliers | B7: HOST TECNOLOGIA LTDA | C7: 100018 | D7: 100018
A8: Operational Suppliers (Wind Farms) | B8: PAIVA SERVICOS LTDA | C8: 100026 | D8: 100026
A9: Customs Brokerage – Overall | B9: SUPPLOG PORTO SECO DE IPOJUCA LTDA | C9: 100028 | D9: 100028
A10: Operational Suppliers (Wind Farms) | B10: MEGAWIND INDUSTRIA E COMERCIO | C10: 100031 | D10: 100031
A11: Other Suppliers | C11: 100032 | D11: 100032
A12: Customs Brokerage – Overall | B12: EMBRAPORT EMPRESA BRASILEIRA DE TER | C12: 100036 | D12: 100036
A13: Other Suppliers | C13: 100039 | D13: 100039
A14: Operational Suppliers (Wind Farms) | C14: 100041 | D14: 100041
A15: Other Suppliers | C15: 100049 | D15: 100049
A16: Customs Brokerage – Overall | C16: 100051 | D16: 100051
A17: Other Suppliers | C17: 100094 | D17: 100094
A18: Operational Suppliers (Wind Farms) | C18: 100095 | D18: 100095
A19: Other Suppliers | C19: 100097 | D19: 100097
A20: Other Suppliers | B20: PRESENCA COMERCIAL LTDA | C20: 100099 | D20: 100099
A21: Operational Suppliers (Wind Farms) | C21: 100102 | D21: 100102
A22: Operational Suppliers (Wind Farms) | C22: 100110 | D22: 100110
A23: Other Suppliers | B23: PREDMEC ENGENHARIA DE MANUTENCAO E | C23: 100111 | D23: 100111
A24: Other Suppliers | B24: PERMETAL S A METAIS PERFURADOS | C24: 100124 | D24: 100124
A25: Other Suppliers | B25: LENGUAE LANGUAGE SERVICES LTDA | C25: 100128 | D25: 100128
A26: Other Suppliers | B26: ULTRATECH MONTAGEM E MANUTENCAO LTD | C26: 100149 | D26: 100149
A27: Other Suppliers | B27: CONQUER HOLDING EDUCACIONAL SA | C27: 100152 | D27: 100152
A28: Other Suppliers | B28: CAMARA DE COM E IND BRASIL ALEMANHA | C28: 100161 | D28: 100161
A29: Operational Suppliers (Wind Farms) | C29: 100177 | D29: 100177
A30: Other Suppliers | C30: 100182 | D30: 100182
A31: Customs Brokerage – Overall | B31: AGL TRANSPORTES INTERNACIONAIS LTDA | C31: 100183 | D31: 100183
A32: Other Suppliers | B32: EPHARMA PBM DO BRASIL SA | C32: 100192 | D32: 100192
A33: Other Suppliers | C33: 100194 | D33: 100194
A34: Operational Suppliers (Wind Farms) | C34: 100200 | D34: 100200
A35: Other Suppliers | C35: 100204 | D35: 100204
A36: Other Suppliers | C36: 100206 | D36: 100206
A37: Operational Suppliers (Wind Farms) | C37: 100346 | D37: 100346
A38: LDs Service Payments | C38: 100353 | D38: 100353
A39: Operational Suppliers (Wind Farms) | C39: 100355 | D39: 100355
A40: Other Suppliers | B40: INOVAR LOCACOES MOSSORO LTDA | C40: 100359 | D40: 100359
A41: Vehicle Rental Services | C41: 100361 | D41: 100361
A42: Vehicle Rental Services | C42: 100363 | D42: 100363
A43: Other Suppliers | B43: NUCLEO DE MONITORAMENTO DE DESCARGA | C43: 100369 | D43: 100369
A44: Other Suppliers | C44: 100375 | D44: 100375
A45: Operational Suppliers (Wind Farms) | B45: RAK LOG TRANSPORTES E LOGISTICA EIR | C45: 100379 | D45: 100379
A46: Other Suppliers | B46: ZIRAN SALVADOR TRANSPORTES LTDA | C46: 100385 | D46: 100385
A47: Operational Suppliers (Wind Farms) | C47: 100387 | D47: 100387
A48: Other Suppliers | B48: GREEN ENERGIA SERVICOS TECNICOS DE | C48: 100390 | D48: 100390
A49: Other Suppliers | B49: DISTRIBUIDORA DE PRODUCTOS DE ELEVA | C49: 100393 | D49: 100393
A50: Operational Suppliers (Wind Farms) | B50: DISTRIBUI LOGISTICA LTDA 03592033000166 | C50: 100396 | D50: 100396
A51: Other Suppliers | B51: TECHNICAL UNIVERSITY OF DENMARK DTU | C51: 100400 | D51: 100400
A52: Other Suppliers | B52: APS COMPONENTES ELETRICOS SA | C52: 100406 | D52: 100406
A53: Customs Brokerage – Overall | C53: 100409 | D53: 100409
A54: Customs Brokerage – Overall | C54: 100410 | D54: 100410
A55: Other Suppliers | B55: HOSTFIBER COMUNICACAO MULTIMIDIA LT | C55: 100411 | D55: 100411
A56: Operational Suppliers (Wind Farms) | C56: 100414 | D56: 100414
A57: Other Suppliers | B57: THE WORLD HOTELS ASSESSORIA E ADM | C57: 100419 | D57: 100419
A58: Other Suppliers | C58: 100420 | D58: 100420
A59: Other Suppliers | B59: CENTRO DE ESTAGIOS PPM HUMAN RESOUR | C59: 100421 | D59: 100421
A60: Operational Suppliers (Wind Farms) | C60: 100422 | D60: 100422
A61: Facilities | C61: 100425 | D61: 100425
A62: Other Suppliers | C62: 100426 | D62: 100426
A63: Operational Suppliers (Wind Farms) | C63: 100430 | D63: 100430
A64: Operational Suppliers (Wind Farms) | B64: COVERWIND SOLUTIONS BRASIL LTDA 45580524000137 | C64: 100432 | D64: 100432
A65: Other Suppliers | C65: 100439 | D65: 100439
A66: Other Suppliers | C66: 100442 | D66: 100442
A67: Customs Brokerage – Overall | B67: DSV AIR & SEA BRASIL LTDA | C67: 100446 | D67: 100446
A68: Customs Brokerage – Overall | B68: DSV AIR & SEA BRASIL LTDA | C68: 100447 | D68: 100447
A69: Other Suppliers | B69: SAMLIFE MSC LTDA | C69: 100450 | D69: 100450
A70: Other Suppliers | B70: GEOMATICS GESTAO DE FROTAS LTDA | C70: 100454 | D70: 100454
A71: Other Suppliers | B71: CARNEVALI EQUIPAMENTOS DE PROTECAO | C71: 100456 | D71: 100456
A72: Customs Brokerage – Overall | B72: NELSON HEUSI LOGISTICA E ARMAZENS G | C72: 100469 | D72: 100469
A73: Other Suppliers | C73: 100470 | D73: 100470
A74: Vehicle Rental Services | C74: 100471 | D74: 100471
A75: Other Suppliers | C75: 100475 | D75: 100475
A76: Other Suppliers | B76: POUSADA ITARETAMA LTDA | C76: 100479 | D76: 100479
A77: Operational Suppliers (Wind Farms) | C77: 100480 | D77: 100480
A78: Operational Suppliers (Wind Farms) | B78: FUCHS LUBRIFICANTES DO BRASIL LTDA | C78: 100485 | D78: 100485
A79: Other Suppliers | B79: LAGOA EMPREENDIMENTOS E PARTICIPACO | C79: 100490 | D79: 100490
A80: Other Suppliers | B80: JESSYCA MARIA LIMA DE MOURA | C80: 100498 | D80: 100498
A81: Other Suppliers | B81: PREMA TECNOLOGIA E COMERCIO LTDA | C81: 100512 | D81: 100512
A82: Other Suppliers | C82: 100514 | D82: 100514
A83: Operational Suppliers (Wind Farms) | B83: CORDEIRO TRANSPORTES LTDA 13043748000113 | C83: 100519 | D83: 100519
A84: Operational Suppliers (Wind Farms) | C84: 100520 | D84: 100520
A85: Operational Suppliers (Wind Farms) | C85: 100524 | D85: 100524
A86: Legal Services Suppliers | C86: 100539 | D86: 100539
A87: Operational Suppliers (Wind Farms) | B87: EXTREME WIND SERVICOS DE MANUTENCAO | C87: 100542 | D87: 100542
A88: Operational Suppliers (Wind Farms) | C88: 100543 | D88: 100543
A89: Operational Suppliers (Wind Farms) | B89: POLIMEXE CONCRETOS CONSTRUCOES E SE | C89: 100548 | D89: 100548
A90: Other Suppliers | B90: LYCEG SEGURANCA PATRIMONIAL EIRELI | C90: 100553 | D90: 100553
A91: Other Suppliers | B91: MAC CONSULTORIA E LOGISTICA LTDA | C91: 100555 | D91: 100555
A92: Other Suppliers | B92: REAL SERVICE TRANSPORTE E TURISMO L | C92: 100558 | D92: 100558
A93: Operational Suppliers (Wind Farms) | C93: 100559 | D93: 100559
A94: Other Suppliers | B94: CONECTA TREINE LTDA | C94: 100561 | D94: 100561
A95: Other Suppliers | C95: 100563 | D95: 100563
A96: Other Suppliers | C96: 100564 | D96: 100564
A97: Customs Brokerage – Overall | B97: BRASIL TERMINAL PORTUARIO S.A. | C97: 100566 | D97: 100566
A98: Other Suppliers | B98: FEDERAL EXPRESS CORPORATION | C98: 100573 | D98: 100573
A99: Operational Suppliers (Wind Farms) | C99: 100574 | D99: 100574
A100: Legal Services Suppliers | B100: DNIT DEP NAC DE INFRAEST DE TRANSPO | C100: 100575 | D100: 100575
...

Sheet Parametros
A1: CONFIGURACAO
A2: Parametros da base
A3: Definicoes de extracao e conferencia do relatorio
A5: Empresa | B5: 4690 — Nordex Energy Brasil LTDA
A6: Data de corte | B6: 46265
A7: Relatorio-fonte | B7: Administrar itens fornecedor (SAP Fiori)
A8: Criterio de extracao | B8: Partidas em aberto | Aberto na data fixada = data de corte | Itens normais + Transacoes do Razao Especial
A9: Eixo de envelhecimento | B9: Idade do documento contabil de origem
A11: RECONCILIACAO
A12: Total da base | B12: =SUM(Base[Montante])
A13: Total de conferencia (Razao) | B13: -1.2027407e+09
A14: Diferenca | B14: =B12-B13

Sheet Aging por Categoria
A1: AP AGING
A2: Exposicao por categoria
A3: Envelhecimento pela idade do documento contabil de origem
A4: Categoria | B4: Até 2020 | C4: 2021 | D4: 2022 | E4: 2023 | F4: 2024 | G4: 2025 | H4: 2026 | I4: Total
A5: Construction Services – Under Litigation | B5: =SUMIFS(Base[Montante],Base[Categoria],$A5,Base[Ano],B$4) | C5: =SUMIFS(Base[Montante],Base[Categoria],$A5,Base[Ano],C$4) | D5: =SUMIFS(Base[Montante],Base[Categoria],$A5,Base[Ano],D$4) | E5: =SUMIFS(Base[Montante],Base[Categoria],$A5,Base[Ano],E$4) | F5: =SUMIFS(Base[Montante],Base[Categoria],$A5,Base[Ano],F$4) | G5: =SUMIFS(Base[Montante],Base[Categoria],$A5,Base[Ano],G$4) | H5: =SUMIFS(Base[Montante],Base[Categoria],$A5,Base[Ano],H$4) | I5: =SUM(B5:H5)
A6: Aeris | B6: =SUMIFS(Base[Montante],Base[Categoria],$A6,Base[Ano],B$4) | C6: =SUMIFS(Base[Montante],Base[Categoria],$A6,Base[Ano],C$4) | D6: =SUMIFS(Base[Montante],Base[Categoria],$A6,Base[Ano],D$4) | E6: =SUMIFS(Base[Montante],Base[Categoria],$A6,Base[Ano],E$4) | F6: =SUMIFS(Base[Montante],Base[Categoria],$A6,Base[Ano],F$4) | G6: =SUMIFS(Base[Montante],Base[Categoria],$A6,Base[Ano],G$4) | H6: =SUMIFS(Base[Montante],Base[Categoria],$A6,Base[Ano],H$4) | I6: =SUM(B6:H6)
A7: Consumables Suppliers | B7: =SUMIFS(Base[Montante],Base[Categoria],$A7,Base[Ano],B$4) | C7: =SUMIFS(Base[Montante],Base[Categoria],$A7,Base[Ano],C$4) | D7: =SUMIFS(Base[Montante],Base[Categoria],$A7,Base[Ano],D$4) | E7: =SUMIFS(Base[Montante],Base[Categoria],$A7,Base[Ano],E$4) | F7: =SUMIFS(Base[Montante],Base[Categoria],$A7,Base[Ano],F$4) | G7: =SUMIFS(Base[Montante],Base[Categoria],$A7,Base[Ano],G$4) | H7: =SUMIFS(Base[Montante],Base[Categoria],$A7,Base[Ano],H$4) | I7: =SUM(B7:H7)
A8: Customs Brokerage – Overall | B8: =SUMIFS(Base[Montante],Base[Categoria],$A8,Base[Ano],B$4) | C8: =SUMIFS(Base[Montante],Base[Categoria],$A8,Base[Ano],C$4) | D8: =SUMIFS(Base[Montante],Base[Categoria],$A8,Base[Ano],D$4) | E8: =SUMIFS(Base[Montante],Base[Categoria],$A8,Base[Ano],E$4) | F8: =SUMIFS(Base[Montante],Base[Categoria],$A8,Base[Ano],F$4) | G8: =SUMIFS(Base[Montante],Base[Categoria],$A8,Base[Ano],G$4) | H8: =SUMIFS(Base[Montante],Base[Categoria],$A8,Base[Ano],H$4) | I8: =SUM(B8:H8)
A9: Corporate Card Payments | B9: =SUMIFS(Base[Montante],Base[Categoria],$A9,Base[Ano],B$4) | C9: =SUMIFS(Base[Montante],Base[Categoria],$A9,Base[Ano],C$4) | D9: =SUMIFS(Base[Montante],Base[Categoria],$A9,Base[Ano],D$4) | E9: =SUMIFS(Base[Montante],Base[Categoria],$A9,Base[Ano],E$4) | F9: =SUMIFS(Base[Montante],Base[Categoria],$A9,Base[Ano],F$4) | G9: =SUMIFS(Base[Montante],Base[Categoria],$A9,Base[Ano],G$4) | H9: =SUMIFS(Base[Montante],Base[Categoria],$A9,Base[Ano],H$4) | I9: =SUM(B9:H9)
A10: Facilities | B10: =SUMIFS(Base[Montante],Base[Categoria],$A10,Base[Ano],B$4) | C10: =SUMIFS(Base[Montante],Base[Categoria],$A10,Base[Ano],C$4) | D10: =SUMIFS(Base[Montante],Base[Categoria],$A10,Base[Ano],D$4) | E10: =SUMIFS(Base[Montante],Base[Categoria],$A10,Base[Ano],E$4) | F10: =SUMIFS(Base[Montante],Base[Categoria],$A10,Base[Ano],F$4) | G10: =SUMIFS(Base[Montante],Base[Categoria],$A10,Base[Ano],G$4) | H10: =SUMIFS(Base[Montante],Base[Categoria],$A10,Base[Ano],H$4) | I10: =SUM(B10:H10)
A11: Insurance | B11: =SUMIFS(Base[Montante],Base[Categoria],$A11,Base[Ano],B$4) | C11: =SUMIFS(Base[Montante],Base[Categoria],$A11,Base[Ano],C$4) | D11: =SUMIFS(Base[Montante],Base[Categoria],$A11,Base[Ano],D$4) | E11: =SUMIFS(Base[Montante],Base[Categoria],$A11,Base[Ano],E$4) | F11: =SUMIFS(Base[Montante],Base[Categoria],$A11,Base[Ano],F$4) | G11: =SUMIFS(Base[Montante],Base[Categoria],$A11,Base[Ano],G$4) | H11: =SUMIFS(Base[Montante],Base[Categoria],$A11,Base[Ano],H$4) | I11: =SUM(B11:H11)
A12: Intercompany | B12: =SUMIFS(Base[Montante],Base[Categoria],$A12,Base[Ano],B$4) | C12: =SUMIFS(Base[Montante],Base[Categoria],$A12,Base[Ano],C$4) | D12: =SUMIFS(Base[Montante],Base[Categoria],$A12,Base[Ano],D$4) | E12: =SUMIFS(Base[Montante],Base[Categoria],$A12,Base[Ano],E$4) | F12: =SUMIFS(Base[Montante],Base[Categoria],$A12,Base[Ano],F$4) | G12: =SUMIFS(Base[Montante],Base[Categoria],$A12,Base[Ano],G$4) | H12: =SUMIFS(Base[Montante],Base[Categoria],$A12,Base[Ano],H$4) | I12: =SUM(B12:H12)
A13: Legal Services Suppliers | B13: =SUMIFS(Base[Montante],Base[Categoria],$A13,Base[Ano],B$4) | C13: =SUMIFS(Base[Montante],Base[Categoria],$A13,Base[Ano],C$4) | D13: =SUMIFS(Base[Montante],Base[Categoria],$A13,Base[Ano],D$4) | E13: =SUMIFS(Base[Montante],Base[Categoria],$A13,Base[Ano],E$4) | F13: =SUMIFS(Base[Montante],Base[Categoria],$A13,Base[Ano],F$4) | G13: =SUMIFS(Base[Montante],Base[Categoria],$A13,Base[Ano],G$4) | H13: =SUMIFS(Base[Montante],Base[Categoria],$A13,Base[Ano],H$4) | I13: =SUM(B13:H13)
A14: Nordex Employees | B14: =SUMIFS(Base[Montante],Base[Categoria],$A14,Base[Ano],B$4) | C14: =SUMIFS(Base[Montante],Base[Categoria],$A14,Base[Ano],C$4) | D14: =SUMIFS(Base[Montante],Base[Categoria],$A14,Base[Ano],D$4) | E14: =SUMIFS(Base[Montante],Base[Categoria],$A14,Base[Ano],E$4) | F14: =SUMIFS(Base[Montante],Base[Categoria],$A14,Base[Ano],F$4) | G14: =SUMIFS(Base[Montante],Base[Categoria],$A14,Base[Ano],G$4) | H14: =SUMIFS(Base[Montante],Base[Categoria],$A14,Base[Ano],H$4) | I14: =SUM(B14:H14)
A15: Operational Suppliers (Wind Farms) | B15: =SUMIFS(Base[Montante],Base[Categoria],$A15,Base[Ano],B$4) | C15: =SUMIFS(Base[Montante],Base[Categoria],$A15,Base[Ano],C$4) | D15: =SUMIFS(Base[Montante],Base[Categoria],$A15,Base[Ano],D$4) | E15: =SUMIFS(Base[Montante],Base[Categoria],$A15,Base[Ano],E$4) | F15: =SUMIFS(Base[Montante],Base[Categoria],$A15,Base[Ano],F$4) | G15: =SUMIFS(Base[Montante],Base[Categoria],$A15,Base[Ano],G$4) | H15: =SUMIFS(Base[Montante],Base[Categoria],$A15,Base[Ano],H$4) | I15: =SUM(B15:H15)
A16: Other Suppliers | B16: =SUMIFS(Base[Montante],Base[Categoria],$A16,Base[Ano],B$4) | C16: =SUMIFS(Base[Montante],Base[Categoria],$A16,Base[Ano],C$4) | D16: =SUMIFS(Base[Montante],Base[Categoria],$A16,Base[Ano],D$4) | E16: =SUMIFS(Base[Montante],Base[Categoria],$A16,Base[Ano],E$4) | F16: =SUMIFS(Base[Montante],Base[Categoria],$A16,Base[Ano],F$4) | G16: =SUMIFS(Base[Montante],Base[Categoria],$A16,Base[Ano],G$4) | H16: =SUMIFS(Base[Montante],Base[Categoria],$A16,Base[Ano],H$4) | I16: =SUM(B16:H16)
... A21: (sem categoria) | B21: =SUMIFS(Base[Montante],Base[Categoria],$A21,Base[Ano],B$4) | C21: =SUMIFS(Base[Montante],Base[Categoria],$A21,Base[Ano],C$4) | D21: =SUMIFS(Base[Montante],Base[Categoria],$A21,Base[Ano],D$4) | E21: =SUMIFS(Base[Montante],Base[Categoria],$A21,Base[Ano],E$4) | F21: =SUMIFS(Base[Montante],Base[Categoria],$A21,Base[Ano],F$4) | G21: =SUMIFS(Base[Montante],Base[Categoria],$A21,Base[Ano],G$4) | H21: =SUMIFS(Base[Montante],Base[Categoria],$A21,Base[Ano],H$4) | I21: =SUM(B21:H21)
A22: Total geral | B22: =SUM(B5:B21) | C22: =SUM(C5:C21) | D22: =SUM(D5:D21) | E22: =SUM(E5:E21) | F22: =SUM(F5:F21) | G22: =SUM(G5:G21) | H22: =SUM(H5:H21) | I22: =SUM(I5:I21)

Sheet Aging por Conta
A1: AP AGING
A2: Exposicao por conta contabil
A3: Envelhecimento pela idade do documento contabil de origem
A4: Conta | B4: Descricao | C4: Até 2020 | D4: 2021 | E4: 2022 | F4: 2023 | G4: 2024 | H4: 2025 | I4: 2026 | J4: Total
A5: 1000010000 | B5: FUNDO FIXO DE CAIXA | C5: =SUMIFS(Base[Montante],Base[Conta],$A5,Base[Ano],C$4) | D5: =SUMIFS(Base[Montante],Base[Conta],$A5,Base[Ano],D$4) | E5: =SUMIFS(Base[Montante],Base[Conta],$A5,Base[Ano],E$4) | F5: =SUMIFS(Base[Montante],Base[Conta],$A5,Base[Ano],F$4) | G5: =SUMIFS(Base[Montante],Base[Conta],$A5,Base[Ano],G$4) | H5: =SUMIFS(Base[Montante],Base[Conta],$A5,Base[Ano],H$4) | I5: =SUMIFS(Base[Montante],Base[Conta],$A5,Base[Ano],I$4) | J5: =SUM(C5:I5)
A6: 1117730000 | B6: ADIANTAMENTO DE VIAGENS | C6: =SUMIFS(Base[Montante],Base[Conta],$A6,Base[Ano],C$4) | D6: =SUMIFS(Base[Montante],Base[Conta],$A6,Base[Ano],D$4) | E6: =SUMIFS(Base[Montante],Base[Conta],$A6,Base[Ano],E$4) | F6: =SUMIFS(Base[Montante],Base[Conta],$A6,Base[Ano],F$4) | G6: =SUMIFS(Base[Montante],Base[Conta],$A6,Base[Ano],G$4) | H6: =SUMIFS(Base[Montante],Base[Conta],$A6,Base[Ano],H$4) | I6: =SUMIFS(Base[Montante],Base[Conta],$A6,Base[Ano],I$4) | J6: =SUM(C6:I6)
A7: 1191000000 | B7: ADIANT. FORNECEDORES - TERCEIROS | C7: =SUMIFS(Base[Montante],Base[Conta],$A7,Base[Ano],C$4) | D7: =SUMIFS(Base[Montante],Base[Conta],$A7,Base[Ano],D$4) | E7: =SUMIFS(Base[Montante],Base[Conta],$A7,Base[Ano],E$4) | F7: =SUMIFS(Base[Montante],Base[Conta],$A7,Base[Ano],F$4) | G7: =SUMIFS(Base[Montante],Base[Conta],$A7,Base[Ano],G$4) | H7: =SUMIFS(Base[Montante],Base[Conta],$A7,Base[Ano],H$4) | I7: =SUMIFS(Base[Montante],Base[Conta],$A7,Base[Ano],I$4) | J7: =SUM(C7:I7)
A8: 1193100000 | B8: ADIANT. FORNECEDORES - PARTES RELACIONADAS | C8: =SUMIFS(Base[Montante],Base[Conta],$A8,Base[Ano],C$4) | D8: =SUMIFS(Base[Montante],Base[Conta],$A8,Base[Ano],D$4) | E8: =SUMIFS(Base[Montante],Base[Conta],$A8,Base[Ano],E$4) | F8: =SUMIFS(Base[Montante],Base[Conta],$A8,Base[Ano],F$4) | G8: =SUMIFS(Base[Montante],Base[Conta],$A8,Base[Ano],G$4) | H8: =SUMIFS(Base[Montante],Base[Conta],$A8,Base[Ano],H$4) | I8: =SUMIFS(Base[Montante],Base[Conta],$A8,Base[Ano],I$4) | J8: =SUM(C8:I8)
A9: 1517730000 | B9: ADIANTAMENTO DE VIAGEM | C9: =SUMIFS(Base[Montante],Base[Conta],$A9,Base[Ano],C$4) | D9: =SUMIFS(Base[Montante],Base[Conta],$A9,Base[Ano],D$4) | E9: =SUMIFS(Base[Montante],Base[Conta],$A9,Base[Ano],E$4) | F9: =SUMIFS(Base[Montante],Base[Conta],$A9,Base[Ano],F$4) | G9: =SUMIFS(Base[Montante],Base[Conta],$A9,Base[Ano],G$4) | H9: =SUMIFS(Base[Montante],Base[Conta],$A9,Base[Ano],H$4) | I9: =SUMIFS(Base[Montante],Base[Conta],$A9,Base[Ano],I$4) | J9: =SUM(C9:I9)
A10: 2111000000 | B10: FORNECEDORES NACIONAIS | C10: =SUMIFS(Base[Montante],Base[Conta],$A10,Base[Ano],C$4) | D10: =SUMIFS(Base[Montante],Base[Conta],$A10,Base[Ano],D$4) | E10: =SUMIFS(Base[Montante],Base[Conta],$A10,Base[Ano],E$4) | F10: =SUMIFS(Base[Montante],Base[Conta],$A10,Base[Ano],F$4) | G10: =SUMIFS(Base[Montante],Base[Conta],$A10,Base[Ano],G$4) | H10: =SUMIFS(Base[Montante],Base[Conta],$A10,Base[Ano],H$4) | I10: =SUMIFS(Base[Montante],Base[Conta],$A10,Base[Ano],I$4) | J10: =SUM(C10:I10)
A11: 2112000000 | B11: CONTAS A PAGAR - PAISES ESTRANGEIROS | C11: =SUMIFS(Base[Montante],Base[Conta],$A11,Base[Ano],C$4) | D11: =SUMIFS(Base[Montante],Base[Conta],$A11,Base[Ano],D$4) | E11: =SUMIFS(Base[Montante],Base[Conta],$A11,Base[Ano],E$4) | F11: =SUMIFS(Base[Montante],Base[Conta],$A11,Base[Ano],F$4) | G11: =SUMIFS(Base[Montante],Base[Conta],$A11,Base[Ano],G$4) | H11: =SUMIFS(Base[Montante],Base[Conta],$A11,Base[Ano],H$4) | I11: =SUMIFS(Base[Montante],Base[Conta],$A11,Base[Ano],I$4) | J11: =SUM(C11:I11)
A12: 2114340000 | B12: RESPONSABILIDADES COM EMPREGADOS | C12: =SUMIFS(Base[Montante],Base[Conta],$A12,Base[Ano],C$4) | D12: =SUMIFS(Base[Montante],Base[Conta],$A12,Base[Ano],D$4) | E12: =SUMIFS(Base[Montante],Base[Conta],$A12,Base[Ano],E$4) | F12: =SUMIFS(Base[Montante],Base[Conta],$A12,Base[Ano],F$4) | G12: =SUMIFS(Base[Montante],Base[Conta],$A12,Base[Ano],G$4) | H12: =SUMIFS(Base[Montante],Base[Conta],$A12,Base[Ano],H$4) | I12: =SUMIFS(Base[Montante],Base[Conta],$A12,Base[Ano],I$4) | J12: =SUM(C12:I12)
A13: 2122100000 | B13: FORNECEDORES - PARTES RELACIONADAS | C13: =SUMIFS(Base[Montante],Base[Conta],$A13,Base[Ano],C$4) | D13: =SUMIFS(Base[Montante],Base[Conta],$A13,Base[Ano],D$4) | E13: =SUMIFS(Base[Montante],Base[Conta],$A13,Base[Ano],E$4) | F13: =SUMIFS(Base[Montante],Base[Conta],$A13,Base[Ano],F$4) | G13: =SUMIFS(Base[Montante],Base[Conta],$A13,Base[Ano],G$4) | H13: =SUMIFS(Base[Montante],Base[Conta],$A13,Base[Ano],H$4) | I13: =SUMIFS(Base[Montante],Base[Conta],$A13,Base[Ano],I$4) | J13: =SUM(C13:I13)
A14: Total geral | C14: =SUM(C5:C13) | D14: =SUM(D5:D13) | E14: =SUM(E5:E13) | F14: =SUM(F5:F13) | G14: =SUM(G5:G13) | H14: =SUM(H5:H13) | I14: =SUM(I5:I13) | J14: =SUM(J5:J13)

Sheet Posição por Fornecedor
A1: AP AGING
A2: Posicao por fornecedor
A3: Filtre pela coluna Categoria ou Fornecedor usando as setas do cabecalho
A4: Fornecedor | B4: Nome do fornecedor | C4: Categoria | D4: Até 2020 | E4: 2021 | F4: 2022 | G4: 2023 | H4: 2024 | I4: 2025 | J4: 2026 | K4: Total
A5: 114597 | B5: BLUEWAY TRADING IMPORTAÇAO E EXPORT SA | C5: =IFERROR(INDEX(DePara[Categoria],MATCH(TEXT(A5,"0"),DePara[Fornecedor_txt],0)),"(sem categoria)") | D5: =SUMIFS(Base[Montante],Base[Fornecedor],$A5&"",Base[Ano],D$4) | E5: =SUMIFS(Base[Montante],Base[Fornecedor],$A5&"",Base[Ano],E$4) | F5: =SUMIFS(Base[Montante],Base[Fornecedor],$A5&"",Base[Ano],F$4) | G5: =SUMIFS(Base[Montante],Base[Fornecedor],$A5&"",Base[Ano],G$4) | H5: =SUMIFS(Base[Montante],Base[Fornecedor],$A5&"",Base[Ano],H$4) | I5: =SUMIFS(Base[Montante],Base[Fornecedor],$A5&"",Base[Ano],I$4) | J5: =SUMIFS(Base[Montante],Base[Fornecedor],$A5&"",Base[Ano],J$4) | K5: =SUM(D5:J5)
A6: 115019 | B6: BLUEWAY TRADING IMPORTAÇAO E EXPORT SA | C6: =IFERROR(INDEX(DePara[Categoria],MATCH(TEXT(A6,"0"),DePara[Fornecedor_txt],0)),"(sem categoria)") | D6: =SUMIFS(Base[Montante],Base[Fornecedor],$A6&"",Base[Ano],D$4) | E6: =SUMIFS(Base[Montante],Base[Fornecedor],$A6&"",Base[Ano],E$4) | F6: =SUMIFS(Base[Montante],Base[Fornecedor],$A6&"",Base[Ano],F$4) | G6: =SUMIFS(Base[Montante],Base[Fornecedor],$A6&"",Base[Ano],G$4) | H6: =SUMIFS(Base[Montante],Base[Fornecedor],$A6&"",Base[Ano],H$4) | I6: =SUMIFS(Base[Montante],Base[Fornecedor],$A6&"",Base[Ano],I$4) | J6: =SUMIFS(Base[Montante],Base[Fornecedor],$A6&"",Base[Ano],J$4) | K6: =SUM(D6:J6)
A7: 100446 | B7: DSV AIR & SEA BRASIL LTDA | C7: =IFERROR(INDEX(DePara[Categoria],MATCH(TEXT(A7,"0"),DePara[Fornecedor_txt],0)),"(sem categoria)") | D7: =SUMIFS(Base[Montante],Base[Fornecedor],$A7&"",Base[Ano],D$4) | E7: =SUMIFS(Base[Montante],Base[Fornecedor],$A7&"",Base[Ano],E$4) | F7: =SUMIFS(Base[Montante],Base[Fornecedor],$A7&"",Base[Ano],F$4) | G7: =SUMIFS(Base[Montante],Base[Fornecedor],$A7&"",Base[Ano],G$4) | H7: =SUMIFS(Base[Montante],Base[Fornecedor],$A7&"",Base[Ano],H$4) | I7: =SUMIFS(Base[Montante],Base[Fornecedor],$A7&"",Base[Ano],I$4) | J7: =SUMIFS(Base[Montante],Base[Fornecedor],$A7&"",Base[Ano],J$4) | K7: =SUM(D7:J7)
A8: 100447 | B8: DSV AIR & SEA BRASIL LTDA | C8: =IFERROR(INDEX(DePara[Categoria],MATCH(TEXT(A8,"0"),DePara[Fornecedor_txt],0)),"(sem categoria)") | D8: =SUMIFS(Base[Montante],Base[Fornecedor],$A8&"",Base[Ano],D$4) | E8: =SUMIFS(Base[Montante],Base[Fornecedor],$A8&"",Base[Ano],E$4) | F8: =SUMIFS(Base[Montante],Base[Fornecedor],$A8&"",Base[Ano],F$4) | G8: =SUMIFS(Base[Montante],Base[Fornecedor],$A8&"",Base[Ano],G$4) | H8: =SUMIFS(Base[Montante],Base[Fornecedor],$A8&"",Base[Ano],H$4) | I8: =SUMIFS(Base[Montante],Base[Fornecedor],$A8&"",Base[Ano],I$4) | J8: =SUMIFS(Base[Montante],Base[Fornecedor],$A8&"",Base[Ano],J$4) | K8: =SUM(D8:J8)
A9: 100805 | B9: EXPRESSO VALE REAL LTDA | C9: =IFERROR(INDEX(DePara[Categoria],MATCH(TEXT(A9,"0"),DePara[Fornecedor_txt],0)),"(sem categoria)") | D9: =SUMIFS(Base[Montante],Base[Fornecedor],$A9&"",Base[Ano],D$4) | E9: =SUMIFS(Base[Montante],Base[Fornecedor],$A9&"",Base[Ano],E$4) | F9: =SUMIFS(Base[Montante],Base[Fornecedor],$A9&"",Base[Ano],F$4) | G9: =SUMIFS(Base[Montante],Base[Fornecedor],$A9&"",Base[Ano],G$4) | H9: =SUMIFS(Base[Montante],Base[Fornecedor],$A9&"",Base[Ano],H$4) | I9: =SUMIFS(Base[Montante],Base[Fornecedor],$A9&"",Base[Ano],I$4) | J9: =SUMIFS(Base[Montante],Base[Fornecedor],$A9&"",Base[Ano],J$4) | K9: =SUM(D9:J9)
A10: 100830 | B10: EXPRESSO VALE REAL LTDA | C10: =IFERROR(INDEX(DePara[Categoria],MATCH(TEXT(A10,"0"),DePara[Fornecedor_txt],0)),"(sem categoria)") | D10: =SUMIFS(Base[Montante],Base[Fornecedor],$A10&"",Base[Ano],D$4) | E10: =SUMIFS(Base[Montante],Base[Fornecedor],$A10&"",Base[Ano],E$4) | F10: =SUMIFS(Base[Montante],Base[Fornecedor],$A10&"",Base[Ano],F$4) | G10: =SUMIFS(Base[Montante],Base[Fornecedor],$A10&"",Base[Ano],G$4) | H10: =SUMIFS(Base[Montante],Base[Fornecedor],$A10&"",Base[Ano],H$4) | I10: =SUMIFS(Base[Montante],Base[Fornecedor],$A10&"",Base[Ano],I$4) | J10: =SUMIFS(Base[Montante],Base[Fornecedor],$A10&"",Base[Ano],J$4) | K10: =SUM(D10:J10)
A11: 100929 | B11: EXPRESSO VALE REAL LTDA | C11: =IFERROR(INDEX(DePara[Categoria],MATCH(TEXT(A11,"0"),DePara[Fornecedor_txt],0)),"(sem categoria)") | D11: =SUMIFS(Base[Montante],Base[Fornecedor],$A11&"",Base[Ano],D$4) | E11: =SUMIFS(Base[Montante],Base[Fornecedor],$A11&"",Base[Ano],E$4) | F11: =SUMIFS(Base[Montante],Base[Fornecedor],$A11&"",Base[Ano],F$4) | G11: =SUMIFS(Base[Montante],Base[Fornecedor],$A11&"",Base[Ano],G$4) | H11: =SUMIFS(Base[Montante],Base[Fornecedor],$A11&"",Base[Ano],H$4) | I11: =SUMIFS(Base[Montante],Base[Fornecedor],$A11&"",Base[Ano],I$4) | J11: =SUMIFS(Base[Montante],Base[Fornecedor],$A11&"",Base[Ano],J$4) | K11: =SUM(D11:J11)
A12: 100573 | B12: FEDERAL EXPRESS CORPORATION | C12: =IFERROR(INDEX(DePara[Categoria],MATCH(TEXT(A12,"0"),DePara[Fornecedor_txt],0)),"(sem categoria)") | D12: =SUMIFS(Base[Montante],Base[Fornecedor],$A12&"",Base[Ano],D$4) | E12: =SUMIFS(Base[Montante],Base[Fornecedor],$A12&"",Base[Ano],E$4) | F12: =SUMIFS(Base[Montante],Base[Fornecedor],$A12&"",Base[Ano],F$4) | G12: =SUMIFS(Base[Montante],Base[Fornecedor],$A12&"",Base[Ano],G$4) | H12: =SUMIFS(Base[Montante],Base[Fornecedor],$A12&"",Base[Ano],H$4) | I12: =SUMIFS(Base[Montante],Base[Fornecedor],$A12&"",Base[Ano],I$4) | J12: =SUMIFS(Base[Montante],Base[Fornecedor],$A12&"",Base[Ano],J$4) | K12: =SUM(D12:J12)
A13: 103886 | B13: FEDERAL EXPRESS CORPORATION | C13: =IFERROR(INDEX(DePara[Categoria],MATCH(TEXT(A13,"0"),DePara[Fornecedor_txt],0)),"(sem categoria)") | D13: =SUMIFS(Base[Montante],Base[Fornecedor],$A13&"",Base[Ano],D$4) | E13: =SUMIFS(Base[Montante],Base[Fornecedor],$A13&"",Base[Ano],E$4) | F13: =SUMIFS(Base[Montante],Base[Fornecedor],$A13&"",Base[Ano],F$4) | G13: =SUMIFS(Base[Montante],Base[Fornecedor],$A13&"",Base[Ano],G$4) | H13: =SUMIFS(Base[Montante],Base[Fornecedor],$A13&"",Base[Ano],H$4) | I13: =SUMIFS(Base[Montante],Base[Fornecedor],$A13&"",Base[Ano],I$4) | J13: =SUMIFS(Base[Montante],Base[Fornecedor],$A13&"",Base[Ano],J$4) | K13: =SUM(D13:J13)
A14: 101777 | B14: INGRAM MICRO BRASIL LTDA | C14: =IFERROR(INDEX(DePara[Categoria],MATCH(TEXT(A14,"0"),DePara[Fornecedor_txt],0)),"(sem categoria)") | D14: =SUMIFS(Base[Montante],Base[Fornecedor],$A14&"",Base[Ano],D$4) | E14: =SUMIFS(Base[Montante],Base[Fornecedor],$A14&"",Base[Ano],E$4) | F14: =SUMIFS(Base[Montante],Base[Fornecedor],$A14&"",Base[Ano],F$4) | G14: =SUMIFS(Base[Montante],Base[Fornecedor],$A14&"",Base[Ano],G$4) | H14: =SUMIFS(Base[Montante],Base[Fornecedor],$A14&"",Base[Ano],H$4) | I14: =SUMIFS(Base[Montante],Base[Fornecedor],$A14&"",Base[Ano],I$4) | J14: =SUMIFS(Base[Montante],Base[Fornecedor],$A14&"",Base[Ano],J$4) | K14: =SUM(D14:J14)
A15: 102099 | B15: INGRAM MICRO BRASIL LTDA | C15: =IFERROR(INDEX(DePara[Categoria],MATCH(TEXT(A15,"0"),DePara[Fornecedor_txt],0)),"(sem categoria)") | D15: =SUMIFS(Base[Montante],Base[Fornecedor],$A15&"",Base[Ano],D$4) | E15: =SUMIFS(Base[Montante],Base[Fornecedor],$A15&"",Base[Ano],E$4) | F15: =SUMIFS(Base[Montante],Base[Fornecedor],$A15&"",Base[Ano],F$4) | G15: =SUMIFS(Base[Montante],Base[Fornecedor],$A15&"",Base[Ano],G$4) | H15: =SUMIFS(Base[Montante],Base[Fornecedor],$A15&"",Base[Ano],H$4) | I15: =SUMIFS(Base[Montante],Base[Fornecedor],$A15&"",Base[Ano],I$4) | J15: =SUMIFS(Base[Montante],Base[Fornecedor],$A15&"",Base[Ano],J$4) | K15: =SUM(D15:J15)
A16: 101611 | B16: SECRETARIA DA FAZENDA BAHIA | C16: =IFERROR(INDEX(DePara[Categoria],MATCH(TEXT(A16,"0"),DePara[Fornecedor_txt],0)),"(sem categoria)") | D16: =SUMIFS(Base[Montante],Base[Fornecedor],$A16&"",Base[Ano],D$4) | E16: =SUMIFS(Base[Montante],Base[Fornecedor],$A16&"",Base[Ano],E$4) | F16: =SUMIFS(Base[Montante],Base[Fornecedor],$A16&"",Base[Ano],F$4) | G16: =SUMIFS(Base[Montante],Base[Fornecedor],$A16&"",Base[Ano],G$4) | H16: =SUMIFS(Base[Montante],Base[Fornecedor],$A16&"",Base[Ano],H$4) | I16: =SUMIFS(Base[Montante],Base[Fornecedor],$A16&"",Base[Ano],I$4) | J16: =SUMIFS(Base[Montante],Base[Fornecedor],$A16&"",Base[Ano],J$4) | K16: =SUM(D16:J16)
... A28: 101178 | B28: ACTUANT GMBH | C28: =IFERROR(INDEX(DePara[Categoria],MATCH(TEXT(A28,"0"),DePara[Fornecedor_txt],0)),"(sem categoria)") | D28: =SUMIFS(Base[Montante],Base[Fornecedor],$A28&"",Base[Ano],D$4) | E28: =SUMIFS(Base[Montante],Base[Fornecedor],$A28&"",Base[Ano],E$4) | F28: =SUMIFS(Base[Montante],Base[Fornecedor],$A28&"",Base[Ano],F$4) | G28: =SUMIFS(Base[Montante],Base[Fornecedor],$A28&"",Base[Ano],G$4) | H28: =SUMIFS(Base[Montante],Base[Fornecedor],$A28&"",Base[Ano],H$4) | I28: =SUMIFS(Base[Montante],Base[Fornecedor],$A28&"",Base[Ano],I$4) | J28: =SUMIFS(Base[Montante],Base[Fornecedor],$A28&"",Base[Ano],J$4) | K28: =SUM(D28:J28)
A29: EM000826 | B29: ADALBERTO COELHO DE SOUSA | C29: =IFERROR(INDEX(DePara[Categoria],MATCH(TEXT(A29,"0"),DePara[Fornecedor_txt],0)),"(sem categoria)") | D29: =SUMIFS(Base[Montante],Base[Fornecedor],$A29&"",Base[Ano],D$4) | E29: =SUMIFS(Base[Montante],Base[Fornecedor],$A29&"",Base[Ano],E$4) | F29: =SUMIFS(Base[Montante],Base[Fornecedor],$A29&"",Base[Ano],F$4) | G29: =SUMIFS(Base[Montante],Base[Fornecedor],$A29&"",Base[Ano],G$4) | H29: =SUMIFS(Base[Montante],Base[Fornecedor],$A29&"",Base[Ano],H$4) | I29: =SUMIFS(Base[Montante],Base[Fornecedor],$A29&"",Base[Ano],I$4) | J29: =SUMIFS(Base[Montante],Base[Fornecedor],$A29&"",Base[Ano],J$4) | K29: =SUM(D29:J29)
A30: 102057 | B30: AERIS INDUSTRIA E COM EQUI GERACAO | C30: =IFERROR(INDEX(DePara[Categoria],MATCH(TEXT(A30,"0"),DePara[Fornecedor_txt],0)),"(sem categoria)") | D30: =SUMIFS(Base[Montante],Base[Fornecedor],$A30&"",Base[Ano],D$4) | E30: =SUMIFS(Base[Montante],Base[Fornecedor],$A30&"",Base[Ano],E$4) | F30: =SUMIFS(Base[Montante],Base[Fornecedor],$A30&"",Base[Ano],F$4) | G30: =SUMIFS(Base[Montante],Base[Fornecedor],$A30&"",Base[Ano],G$4) | H30: =SUMIFS(Base[Montante],Base[Fornecedor],$A30&"",Base[Ano],H$4) | I30: =SUMIFS(Base[Montante],Base[Fornecedor],$A30&"",Base[Ano],I$4) | J30: =SUMIFS(Base[Montante],Base[Fornecedor],$A30&"",Base[Ano],J$4) | K30: =SUM(D30:J30)
A31: 101043 | B31: AEROPORTO BRASIL VIRACOPOS SA | C31: =IFERROR(INDEX(DePara[Categoria],MATCH(TEXT(A31,"0"),DePara[Fornecedor_txt],0)),"(sem categoria)") | D31: =SUMIFS(Base[Montante],Base[Fornecedor],$A31&"",Base[Ano],D$4) | E31: =SUMIFS(Base[Montante],Base[Fornecedor],$A31&"",Base[Ano],E$4) | F31: =SUMIFS(Base[Montante],Base[Fornecedor],$A31&"",Base[Ano],F$4) | G31: =SUMIFS(Base[Montante],Base[Fornecedor],$A31&"",Base[Ano],G$4) | H31: =SUMIFS(Base[Montante],Base[Fornecedor],$A31&"",Base[Ano],H$4) | I31: =SUMIFS(Base[Montante],Base[Fornecedor],$A31&"",Base[Ano],I$4) | J31: =SUMIFS(Base[Montante],Base[Fornecedor],$A31&"",Base[Ano],J$4) | K31: =SUM(D31:J31)
A32: 101494 | B32: AG SOLVE MONITORAMENTO AMBIENTAL LT | C32: =IFERROR(INDEX(DePara[Categoria],MATCH(TEXT(A32,"0"),DePara[Fornecedor_txt],0)),"(sem categoria)") | D32: =SUMIFS(Base[Montante],Base[Fornecedor],$A32&"",Base[Ano],D$4) | E32: =SUMIFS(Base[Montante],Base[Fornecedor],$A32&"",Base[Ano],E$4) | F32: =SUMIFS(Base[Montante],Base[Fornecedor],$A32&"",Base[Ano],F$4) | G32: =SUMIFS(Base[Montante],Base[Fornecedor],$A32&"",Base[Ano],G$4) | H32: =SUMIFS(Base[Montante],Base[Fornecedor],$A32&"",Base[Ano],H$4) | I32: =SUMIFS(Base[Montante],Base[Fornecedor],$A32&"",Base[Ano],I$4) | J32: =SUMIFS(Base[Montante],Base[Fornecedor],$A32&"",Base[Ano],J$4) | K32: =SUM(D32:J32)
A33: 101254 | B33: AGENCIA BRASILEIRA DE METEOROLOGIA | C33: =IFERROR(INDEX(DePara[Categoria],MATCH(TEXT(A33,"0"),DePara[Fornecedor_txt],0)),"(sem categoria)") | D33: =SUMIFS(Base[Montante],Base[Fornecedor],$A33&"",Base[Ano],D$4) | E33: =SUMIFS(Base[Montante],Base[Fornecedor],$A33&"",Base[Ano],E$4) | F33: =SUMIFS(Base[Montante],Base[Fornecedor],$A33&"",Base[Ano],F$4) | G33: =SUMIFS(Base[Montante],Base[Fornecedor],$A33&"",Base[Ano],G$4) | H33: =SUMIFS(Base[Montante],Base[Fornecedor],$A33&"",Base[Ano],H$4) | I33: =SUMIFS(Base[Montante],Base[Fornecedor],$A33&"",Base[Ano],I$4) | J33: =SUMIFS(Base[Montante],Base[Fornecedor],$A33&"",Base[Ano],J$4) | K33: =SUM(D33:J33)
A34: 101688 | B34: AGIS EQUIPAMENTOS E SERVIÇOS DE INFORMATICA LTDA | C34: =IFERROR(INDEX(DePara[Categoria],MATCH(TEXT(A34,"0"),DePara[Fornecedor_txt],0)),"(sem categoria)") | D34: =SUMIFS(Base[Montante],Base[Fornecedor],$A34&"",Base[Ano],D$4) | E34: =SUMIFS(Base[Montante],Base[Fornecedor],$A34&"",Base[Ano],E$4) | F34: =SUMIFS(Base[Montante],Base[Fornecedor],$A34&"",Base[Ano],F$4) | G34: =SUMIFS(Base[Montante],Base[Fornecedor],$A34&"",Base[Ano],G$4) | H34: =SUMIFS(Base[Montante],Base[Fornecedor],$A34&"",Base[Ano],H$4) | I34: =SUMIFS(Base[Montante],Base[Fornecedor],$A34&"",Base[Ano],I$4) | J34: =SUMIFS(Base[Montante],Base[Fornecedor],$A34&"",Base[Ano],J$4) | K34: =SUM(D34:J34)
A35: 100183 | B35: AGL TRANSPORTES INTERNACIONAIS LTDA | C35: =IFERROR(INDEX(DePara[Categoria],MATCH(TEXT(A35,"0"),DePara[Fornecedor_txt],0)),"(sem categoria)") | D35: =SUMIFS(Base[Montante],Base[Fornecedor],$A35&"",Base[Ano],D$4) | E35: =SUMIFS(Base[Montante],Base[Fornecedor],$A35&"",Base[Ano],E$4) | F35: =SUMIFS(Base[Montante],Base[Fornecedor],$A35&"",Base[Ano],F$4) | G35: =SUMIFS(Base[Montante],Base[Fornecedor],$A35&"",Base[Ano],G$4) | H35: =SUMIFS(Base[Montante],Base[Fornecedor],$A35&"",Base[Ano],H$4) | I35: =SUMIFS(Base[Montante],Base[Fornecedor],$A35&"",Base[Ano],I$4) | J35: =SUMIFS(Base[Montante],Base[Fornecedor],$A35&"",Base[Ano],J$4) | K35: =SUM(D35:J35)
A36: 101222 | B36: AGROPECUARIA CANOA MIRIM SA | C36: =IFERROR(INDEX(DePara[Categoria],MATCH(TEXT(A36,"0"),DePara[Fornecedor_txt],0)),"(sem categoria)") | D36: =SUMIFS(Base[Montante],Base[Fornecedor],$A36&"",Base[Ano],D$4) | E36: =SUMIFS(Base[Montante],Base[Fornecedor],$A36&"",Base[Ano],E$4) | F36: =SUMIFS(Base[Montante],Base[Fornecedor],$A36&"",Base[Ano],F$4) | G36: =SUMIFS(Base[Montante],Base[Fornecedor],$A36&"",Base[Ano],G$4) | H36: =SUMIFS(Base[Montante],Base[Fornecedor],$A36&"",Base[Ano],H$4) | I36: =SUMIFS(Base[Montante],Base[Fornecedor],$A36&"",Base[Ano],I$4) | J36: =SUMIFS(Base[Montante],Base[Fornecedor],$A36&"",Base[Ano],J$4) | K36: =SUM(D36:J36)
A37: 103745 | B37: AIR LIDER COMERCIO E TRANSPORTE DE | C37: =IFERROR(INDEX(DePara[Categoria],MATCH(TEXT(A37,"0"),DePara[Fornecedor_txt],0)),"(sem categoria)") | D37: =SUMIFS(Base[Montante],Base[Fornecedor],$A37&"",Base[Ano],D$4) | E37: =SUMIFS(Base[Montante],Base[Fornecedor],$A37&"",Base[Ano],E$4) | F37: =SUMIFS(Base[Montante],Base[Fornecedor],$A37&"",Base[Ano],F$4) | G37: =SUMIFS(Base[Montante],Base[Fornecedor],$A37&"",Base[Ano],G$4) | H37: =SUMIFS(Base[Montante],Base[Fornecedor],$A37&"",Base[Ano],H$4) | I37: =SUMIFS(Base[Montante],Base[Fornecedor],$A37&"",Base[Ano],I$4) | J37: =SUMIFS(Base[Montante],Base[Fornecedor],$A37&"",Base[Ano],J$4) | K37: =SUM(D37:J37)
A38: 115200 | B38: AIR LIDER GROUP COMERCIO DE GASES | C38: =IFERROR(INDEX(DePara[Categoria],MATCH(TEXT(A38,"0"),DePara[Fornecedor_txt],0)),"(sem categoria)") | D38: =SUMIFS(Base[Montante],Base[Fornecedor],$A38&"",Base[Ano],D$4) | E38: =SUMIFS(Base[Montante],Base[Fornecedor],$A38&"",Base[Ano],E$4) | F38: =SUMIFS(Base[Montante],Base[Fornecedor],$A38&"",Base[Ano],F$4) | G38: =SUMIFS(Base[Montante],Base[Fornecedor],$A38&"",Base[Ano],G$4) | H38: =SUMIFS(Base[Montante],Base[Fornecedor],$A38&"",Base[Ano],H$4) | I38: =SUMIFS(Base[Montante],Base[Fornecedor],$A38&"",Base[Ano],I$4) | J38: =SUMIFS(Base[Montante],Base[Fornecedor],$A38&"",Base[Ano],J$4) | K38: =SUM(D38:J38)
A39: EM000147 | B39: AIRTON SHARLES E SILVA PESSOA | C39: =IFERROR(INDEX(DePara[Categoria],MATCH(TEXT(A39,"0"),DePara[Fornecedor_txt],0)),"(sem categoria)") | D39: =SUMIFS(Base[Montante],Base[Fornecedor],$A39&"",Base[Ano],D$4) | E39: =SUMIFS(Base[Montante],Base[Fornecedor],$A39&"",Base[Ano],E$4) | F39: =SUMIFS(Base[Montante],Base[Fornecedor],$A39&"",Base[Ano],F$4) | G39: =SUMIFS(Base[Montante],Base[Fornecedor],$A39&"",Base[Ano],G$4) | H39: =SUMIFS(Base[Montante],Base[Fornecedor],$A39&"",Base[Ano],H$4) | I39: =SUMIFS(Base[Montante],Base[Fornecedor],$A39&"",Base[Ano],I$4) | J39: =SUMIFS(Base[Montante],Base[Fornecedor],$A39&"",Base[Ano],J$4) | K39: =SUM(D39:J39)
A40: EM000542 | B40: AKIM FELTRIM CARDOSO | C40: =IFERROR(INDEX(DePara[Categoria],MATCH(TEXT(A40,"0"),DePara[Fornecedor_txt],0)),"(sem categoria)") | D40: =SUMIFS(Base[Montante],Base[Fornecedor],$A40&"",Base[Ano],D$4) | E40: =SUMIFS(Base[Montante],Base[Fornecedor],$A40&"",Base[Ano],E$4) | F40: =SUMIFS(Base[Montante],Base[Fornecedor],$A40&"",Base[Ano],F$4) | G40: =SUMIFS(Base[Montante],Base[Fornecedor],$A40&"",Base[Ano],G$4) | H40: =SUMIFS(Base[Montante],Base[Fornecedor],$A40&"",Base[Ano],H$4) | I40: =SUMIFS(Base[Montante],Base[Fornecedor],$A40&"",Base[Ano],I$4) | J40: =SUMIFS(Base[Montante],Base[Fornecedor],$A40&"",Base[Ano],J$4) | K40: =SUM(D40:J40)
A41: 101226 | B41: AL WIND SOLUCOES LTDA | C41: =IFERROR(INDEX(DePara[Categoria],MATCH(TEXT(A41,"0"),DePara[Fornecedor_txt],0)),"(sem categoria)") | D41: =SUMIFS(Base[Montante],Base[Fornecedor],$A41&"",Base[Ano],D$4) | E41: =SUMIFS(Base[Montante],Base[Fornecedor],$A41&"",Base[Ano],E$4) | F41: =SUMIFS(Base[Montante],Base[Fornecedor],$A41&"",Base[Ano],F$4) | G41: =SUMIFS(Base[Montante],Base[Fornecedor],$A41&"",Base[Ano],G$4) | H41: =SUMIFS(Base[Montante],Base[Fornecedor],$A41&"",Base[Ano],H$4) | I41: =SUMIFS(Base[Montante],Base[Fornecedor],$A41&"",Base[Ano],I$4) | J41: =SUMIFS(Base[Montante],Base[Fornecedor],$A41&"",Base[Ano],J$4) | K41: =SUM(D41:J41)
A42: EM000171 | B42: ALESSANDRA RAFFO SCHNEIDER | C42: =IFERROR(INDEX(DePara[Categoria],MATCH(TEXT(A42,"0"),DePara[Fornecedor_txt],0)),"(sem categoria)") | D42: =SUMIFS(Base[Montante],Base[Fornecedor],$A42&"",Base[Ano],D$4) | E42: =SUMIFS(Base[Montante],Base[Fornecedor],$A42&"",Base[Ano],E$4) | F42: =SUMIFS(Base[Montante],Base[Fornecedor],$A42&"",Base[Ano],F$4) | G42: =SUMIFS(Base[Montante],Base[Fornecedor],$A42&"",Base[Ano],G$4) | H42: =SUMIFS(Base[Montante],Base[Fornecedor],$A42&"",Base[Ano],H$4) | I42: =SUMIFS(Base[Montante],Base[Fornecedor],$A42&"",Base[Ano],I$4) | J42: =SUMIFS(Base[Montante],Base[Fornecedor],$A42&"",Base[Ano],J$4) | K42: =SUM(D42:J42)
A43: EM000018 | B43: ALESSANDRO SANTANA CORTES | C43: =IFERROR(INDEX(DePara[Categoria],MATCH(TEXT(A43,"0"),DePara[Fornecedor_txt],0)),"(sem categoria)") | D43: =SUMIFS(Base[Montante],Base[Fornecedor],$A43&"",Base[Ano],D$4) | E43: =SUMIFS(Base[Montante],Base[Fornecedor],$A43&"",Base[Ano],E$4) | F43: =SUMIFS(Base[Montante],Base[Fornecedor],$A43&"",Base[Ano],F$4) | G43: =SUMIFS(Base[Montante],Base[Fornecedor],$A43&"",Base[Ano],G$4) | H43: =SUMIFS(Base[Montante],Base[Fornecedor],$A43&"",Base[Ano],H$4) | I43: =SUMIFS(Base[Montante],Base[Fornecedor],$A43&"",Base[Ano],I$4) | J43: =SUMIFS(Base[Montante],Base[Fornecedor],$A43&"",Base[Ano],J$4) | K43: =SUM(D43:J43)
A44: EM000451 | B44: ALEX DA SILVA CONCEIÇÃO | C44: =IFERROR(INDEX(DePara[Categoria],MATCH(TEXT(A44,"0"),DePara[Fornecedor_txt],0)),"(sem categoria)") | D44: =SUMIFS(Base[Montante],Base[Fornecedor],$A44&"",Base[Ano],D$4) | E44: =SUMIFS(Base[Montante],Base[Fornecedor],$A44&"",Base[Ano],E$4) | F44: =SUMIFS(Base[Montante],Base[Fornecedor],$A44&"",Base[Ano],F$4) | G44: =SUMIFS(Base[Montante],Base[Fornecedor],$A44&"",Base[Ano],G$4) | H44: =SUMIFS(Base[Montante],Base[Fornecedor],$A44&"",Base[Ano],H$4) | I44: =SUMIFS(Base[Montante],Base[Fornecedor],$A44&"",Base[Ano],I$4) | J44: =SUMIFS(Base[Montante],Base[Fornecedor],$A44&"",Base[Ano],J$4) | K44: =SUM(D44:J44)
A45: EM000035 | B45: ALEXANDRE SILVEIRA TRINDADE | C45: =IFERROR(INDEX(DePara[Categoria],MATCH(TEXT(A45,"0"),DePara[Fornecedor_txt],0)),"(sem categoria)") | D45: =SUMIFS(Base[Montante],Base[Fornecedor],$A45&"",Base[Ano],D$4) | E45: =SUMIFS(Base[Montante],Base[Fornecedor],$A45&"",Base[Ano],E$4) | F45: =SUMIFS(Base[Montante],Base[Fornecedor],$A45&"",Base[Ano],F$4) | G45: =SUMIFS(Base[Montante],Base[Fornecedor],$A45&"",Base[Ano],G$4) | H45: =SUMIFS(Base[Montante],Base[Fornecedor],$A45&"",Base[Ano],H$4) | I45: =SUMIFS(Base[Montante],Base[Fornecedor],$A45&"",Base[Ano],I$4) | J45: =SUMIFS(Base[Montante],Base[Fornecedor],$A45&"",Base[Ano],J$4) | K45: =SUM(D45:J45)
A46: EM000549 | B46: ALISSON ALEXANDRE CARVALHO ARAUJO | C46: =IFERROR(INDEX(DePara[Categoria],MATCH(TEXT(A46,"0"),DePara[Fornecedor_txt],0)),"(sem categoria)") | D46: =SUMIFS(Base[Montante],Base[Fornecedor],$A46&"",Base[Ano],D$4) | E46: =SUMIFS(Base[Montante],Base[Fornecedor],$A46&"",Base[Ano],E$4) | F46: =SUMIFS(Base[Montante],Base[Fornecedor],$A46&"",Base[Ano],F$4) | G46: =SUMIFS(Base[Montante],Base[Fornecedor],$A46&"",Base[Ano],G$4) | H46: =SUMIFS(Base[Montante],Base[Fornecedor],$A46&"",Base[Ano],H$4) | I46: =SUMIFS(Base[Montante],Base[Fornecedor],$A46&"",Base[Ano],I$4) | J46: =SUMIFS(Base[Montante],Base[Fornecedor],$A46&"",Base[Ano],J$4) | K46: =SUM(D46:J46)
A47: 101133 | B47: ALLIANZ SEGUROS SA USD | C47: =IFERROR(INDEX(DePara[Categoria],MATCH(TEXT(A47,"0"),DePara[Fornecedor_txt],0)),"(sem categoria)") | D47: =SUMIFS(Base[Montante],Base[Fornecedor],$A47&"",Base[Ano],D$4) | E47: =SUMIFS(Base[Montante],Base[Fornecedor],$A47&"",Base[Ano],E$4) | F47: =SUMIFS(Base[Montante],Base[Fornecedor],$A47&"",Base[Ano],F$4) | G47: =SUMIFS(Base[Montante],Base[Fornecedor],$A47&"",Base[Ano],G$4) | H47: =SUMIFS(Base[Montante],Base[Fornecedor],$A47&"",Base[Ano],H$4) | I47: =SUMIFS(Base[Montante],Base[Fornecedor],$A47&"",Base[Ano],I$4) | J47: =SUMIFS(Base[Montante],Base[Fornecedor],$A47&"",Base[Ano],J$4) | K47: =SUM(D47:J47)
A48: EM000511 | B48: ALLISON DE OLIVEIRA COSTA | C48: =IFERROR(INDEX(DePara[Categoria],MATCH(TEXT(A48,"0"),DePara[Fornecedor_txt],0)),"(sem categoria)") | D48: =SUMIFS(Base[Montante],Base[Fornecedor],$A48&"",Base[Ano],D$4) | E48: =SUMIFS(Base[Montante],Base[Fornecedor],$A48&"",Base[Ano],E$4) | F48: =SUMIFS(Base[Montante],Base[Fornecedor],$A48&"",Base[Ano],F$4) | G48: =SUMIFS(Base[Montante],Base[Fornecedor],$A48&"",Base[Ano],G$4) | H48: =SUMIFS(Base[Montante],Base[Fornecedor],$A48&"",Base[Ano],H$4) | I48: =SUMIFS(Base[Montante],Base[Fornecedor],$A48&"",Base[Ano],I$4) | J48: =SUMIFS(Base[Montante],Base[Fornecedor],$A48&"",Base[Ano],J$4) | K48: =SUM(D48:J48)
A49: EM000262 | B49: ALLYSSON LAURENTINO DE MELO RAMOS | C49: =IFERROR(INDEX(DePara[Categoria],MATCH(TEXT(A49,"0"),DePara[Fornecedor_txt],0)),"(sem categoria)") | D49: =SUMIFS(Base[Montante],Base[Fornecedor],$A49&"",Base[Ano],D$4) | E49: =SUMIFS(Base[Montante],Base[Fornecedor],$A49&"",Base[Ano],E$4) | F49: =SUMIFS(Base[Montante],Base[Fornecedor],$A49&"",Base[Ano],F$4) | G49: =SUMIFS(Base[Montante],Base[Fornecedor],$A49&"",Base[Ano],G$4) | H49: =SUMIFS(Base[Montante],Base[Fornecedor],$A49&"",Base[Ano],H$4) | I49: =SUMIFS(Base[Montante],Base[Fornecedor],$A49&"",Base[Ano],I$4) | J49: =SUMIFS(Base[Montante],Base[Fornecedor],$A49&"",Base[Ano],J$4) | K49: =SUM(D49:J49)
A50: 101937 | B50: ALONSO DOLDAN INGENIERIA Y SERVICIO | C50: =IFERROR(INDEX(DePara[Categoria],MATCH(TEXT(A50,"0"),DePara[Fornecedor_txt],0)),"(sem categoria)") | D50: =SUMIFS(Base[Montante],Base[Fornecedor],$A50&"",Base[Ano],D$4) | E50: =SUMIFS(Base[Montante],Base[Fornecedor],$A50&"",Base[Ano],E$4) | F50: =SUMIFS(Base[Montante],Base[Fornecedor],$A50&"",Base[Ano],F$4) | G50: =SUMIFS(Base[Montante],Base[Fornecedor],$A50&"",Base[Ano],G$4) | H50: =SUMIFS(Base[Montante],Base[Fornecedor],$A50&"",Base[Ano],H$4) | I50: =SUMIFS(Base[Montante],Base[Fornecedor],$A50&"",Base[Ano],I$4) | J50: =SUMIFS(Base[Montante],Base[Fornecedor],$A50&"",Base[Ano],J$4) | K50: =SUM(D50:J50)
A51: 101340 | B51: ALS TRIBOLOGY BRASIL ANALISE DE FLU | C51: =IFERROR(INDEX(DePara[Categoria],MATCH(TEXT(A51,"0"),DePara[Fornecedor_txt],0)),"(sem categoria)") | D51: =SUMIFS(Base[Montante],Base[Fornecedor],$A51&"",Base[Ano],D$4) | E51: =SUMIFS(Base[Montante],Base[Fornecedor],$A51&"",Base[Ano],E$4) | F51: =SUMIFS(Base[Montante],Base[Fornecedor],$A51&"",Base[Ano],F$4) | G51: =SUMIFS(Base[Montante],Base[Fornecedor],$A51&"",Base[Ano],G$4) | H51: =SUMIFS(Base[Montante],Base[Fornecedor],$A51&"",Base[Ano],H$4) | I51: =SUMIFS(Base[Montante],Base[Fornecedor],$A51&"",Base[Ano],I$4) | J51: =SUMIFS(Base[Montante],Base[Fornecedor],$A51&"",Base[Ano],J$4) | K51: =SUM(D51:J51)
A52: 101558 | B52: ALTRA INDUSTRIAL MOTION B E I LTDA | C52: =IFERROR(INDEX(DePara[Categoria],MATCH(TEXT(A52,"0"),DePara[Fornecedor_txt],0)),"(sem categoria)") | D52: =SUMIFS(Base[Montante],Base[Fornecedor],$A52&"",Base[Ano],D$4) | E52: =SUMIFS(Base[Montante],Base[Fornecedor],$A52&"",Base[Ano],E$4) | F52: =SUMIFS(Base[Montante],Base[Fornecedor],$A52&"",Base[Ano],F$4) | G52: =SUMIFS(Base[Montante],Base[Fornecedor],$A52&"",Base[Ano],G$4) | H52: =SUMIFS(Base[Montante],Base[Fornecedor],$A52&"",Base[Ano],H$4) | I52: =SUMIFS(Base[Montante],Base[Fornecedor],$A52&"",Base[Ano],I$4) | J52: =SUMIFS(Base[Montante],Base[Fornecedor],$A52&"",Base[Ano],J$4) | K52: =SUM(D52:J52)
A53: 101253 | B53: ALTUS SISTEMAS DE AUTOMACAO SA | C53: =IFERROR(INDEX(DePara[Categoria],MATCH(TEXT(A53,"0"),DePara[Fornecedor_txt],0)),"(sem categoria)") | D53: =SUMIFS(Base[Montante],Base[Fornecedor],$A53&"",Base[Ano],D$4) | E53: =SUMIFS(Base[Montante],Base[Fornecedor],$A53&"",Base[Ano],E$4) | F53: =SUMIFS(Base[Montante],Base[Fornecedor],$A53&"",Base[Ano],F$4) | G53: =SUMIFS(Base[Montante],Base[Fornecedor],$A53&"",Base[Ano],G$4) | H53: =SUMIFS(Base[Montante],Base[Fornecedor],$A53&"",Base[Ano],H$4) | I53: =SUMIFS(Base[Montante],Base[Fornecedor],$A53&"",Base[Ano],I$4) | J53: =SUMIFS(Base[Montante],Base[Fornecedor],$A53&"",Base[Ano],J$4) | K53: =SUM(D53:J53)
A54: 107759 | B54: AMBAR INOVAÇÕES SPE LTDA | C54: =IFERROR(INDEX(DePara[Categoria],MATCH(TEXT(A54,"0"),DePara[Fornecedor_txt],0)),"(sem categoria)") | D54: =SUMIFS(Base[Montante],Base[Fornecedor],$A54&"",Base[Ano],D$4) | E54: =SUMIFS(Base[Montante],Base[Fornecedor],$A54&"",Base[Ano],E$4) | F54: =SUMIFS(Base[Montante],Base[Fornecedor],$A54&"",Base[Ano],F$4) | G54: =SUMIFS(Base[Montante],Base[Fornecedor],$A54&"",Base[Ano],G$4) | H54: =SUMIFS(Base[Montante],Base[Fornecedor],$A54&"",Base[Ano],H$4) | I54: =SUMIFS(Base[Montante],Base[Fornecedor],$A54&"",Base[Ano],I$4) | J54: =SUMIFS(Base[Montante],Base[Fornecedor],$A54&"",Base[Ano],J$4) | K54: =SUM(D54:J54)
A55: 102069 | B55: AMBAR PATRIMONIAL LTDA | C55: =IFERROR(INDEX(DePara[Categoria],MATCH(TEXT(A55,"0"),DePara[Fornecedor_txt],0)),"(sem categoria)") | D55: =SUMIFS(Base[Montante],Base[Fornecedor],$A55&"",Base[Ano],D$4) | E55: =SUMIFS(Base[Montante],Base[Fornecedor],$A55&"",Base[Ano],E$4) | F55: =SUMIFS(Base[Montante],Base[Fornecedor],$A55&"",Base[Ano],F$4) | G55: =SUMIFS(Base[Montante],Base[Fornecedor],$A55&"",Base[Ano],G$4) | H55: =SUMIFS(Base[Montante],Base[Fornecedor],$A55&"",Base[Ano],H$4) | I55: =SUMIFS(Base[Montante],Base[Fornecedor],$A55&"",Base[Ano],I$4) | J55: =SUMIFS(Base[Montante],Base[Fornecedor],$A55&"",Base[Ano],J$4) | K55: =SUM(D55:J55)
A56: 102473 | B56: AMBIENTESEE COMERCIO E SERVICOS LTD 19246312000108 | C56: =IFERROR(INDEX(DePara[Categoria],MATCH(TEXT(A56,"0"),DePara[Fornecedor_txt],0)),"(sem categoria)") | D56: =SUMIFS(Base[Montante],Base[Fornecedor],$A56&"",Base[Ano],D$4) | E56: =SUMIFS(Base[Montante],Base[Fornecedor],$A56&"",Base[Ano],E$4) | F56: =SUMIFS(Base[Montante],Base[Fornecedor],$A56&"",Base[Ano],F$4) | G56: =SUMIFS(Base[Montante],Base[Fornecedor],$A56&"",Base[Ano],G$4) | H56: =SUMIFS(Base[Montante],Base[Fornecedor],$A56&"",Base[Ano],H$4) | I56: =SUMIFS(Base[Montante],Base[Fornecedor],$A56&"",Base[Ano],I$4) | J56: =SUMIFS(Base[Montante],Base[Fornecedor],$A56&"",Base[Ano],J$4) | K56: =SUM(D56:J56)
A57: EM000964 | B57: ANA MARIA BOTELHO FONSECA | C57: =IFERROR(INDEX(DePara[Categoria],MATCH(TEXT(A57,"0"),DePara[Fornecedor_txt],0)),"(sem categoria)") | D57: =SUMIFS(Base[Montante],Base[Fornecedor],$A57&"",Base[Ano],D$4) | E57: =SUMIFS(Base[Montante],Base[Fornecedor],$A57&"",Base[Ano],E$4) | F57: =SUMIFS(Base[Montante],Base[Fornecedor],$A57&"",Base[Ano],F$4) | G57: =SUMIFS(Base[Montante],Base[Fornecedor],$A57&"",Base[Ano],G$4) | H57: =SUMIFS(Base[Montante],Base[Fornecedor],$A57&"",Base[Ano],H$4) | I57: =SUMIFS(Base[Montante],Base[Fornecedor],$A57&"",Base[Ano],I$4) | J57: =SUMIFS(Base[Montante],Base[Fornecedor],$A57&"",Base[Ano],J$4) | K57: =SUM(D57:J57)
A58: EM000057 | B58: ANA PATRICIA MORAIS DA SILVA | C58: =IFERROR(INDEX(DePara[Categoria],MATCH(TEXT(A58,"0"),DePara[Fornecedor_txt],0)),"(sem categoria)") | D58: =SUMIFS(Base[Montante],Base[Fornecedor],$A58&"",Base[Ano],D$4) | E58: =SUMIFS(Base[Montante],Base[Fornecedor],$A58&"",Base[Ano],E$4) | F58: =SUMIFS(Base[Montante],Base[Fornecedor],$A58&"",Base[Ano],F$4) | G58: =SUMIFS(Base[Montante],Base[Fornecedor],$A58&"",Base[Ano],G$4) | H58: =SUMIFS(Base[Montante],Base[Fornecedor],$A58&"",Base[Ano],H$4) | I58: =SUMIFS(Base[Montante],Base[Fornecedor],$A58&"",Base[Ano],I$4) | J58: =SUMIFS(Base[Montante],Base[Fornecedor],$A58&"",Base[Ano],J$4) | K58: =SUM(D58:J58)
A59: EM000167 | B59: ANDERSON DE LIMA AFFONSO | C59: =IFERROR(INDEX(DePara[Categoria],MATCH(TEXT(A59,"0"),DePara[Fornecedor_txt],0)),"(sem categoria)") | D59: =SUMIFS(Base[Montante],Base[Fornecedor],$A59&"",Base[Ano],D$4) | E59: =SUMIFS(Base[Montante],Base[Fornecedor],$A59&"",Base[Ano],E$4) | F59: =SUMIFS(Base[Montante],Base[Fornecedor],$A59&"",Base[Ano],F$4) | G59: =SUMIFS(Base[Montante],Base[Fornecedor],$A59&"",Base[Ano],G$4) | H59: =SUMIFS(Base[Montante],Base[Fornecedor],$A59&"",Base[Ano],H$4) | I59: =SUMIFS(Base[Montante],Base[Fornecedor],$A59&"",Base[Ano],I$4) | J59: =SUMIFS(Base[Montante],Base[Fornecedor],$A59&"",Base[Ano],J$4) | K59: =SUM(D59:J59)
A60: EM000083 | B60: ANDERSON DE SOUZA MOTA | C60: =IFERROR(INDEX(DePara[Categoria],MATCH(TEXT(A60,"0"),DePara[Fornecedor_txt],0)),"(sem categoria)") | D60: =SUMIFS(Base[Montante],Base[Fornecedor],$A60&"",Base[Ano],D$4) | E60: =SUMIFS(Base[Montante],Base[Fornecedor],$A60&"",Base[Ano],E$4) | F60: =SUMIFS(Base[Montante],Base[Fornecedor],$A60&"",Base[Ano],F$4) | G60: =SUMIFS(Base[Montante],Base[Fornecedor],$A60&"",Base[Ano],G$4) | H60: =SUMIFS(Base[Montante],Base[Fornecedor],$A60&"",Base[Ano],H$4) | I60: =SUMIFS(Base[Montante],Base[Fornecedor],$A60&"",Base[Ano],I$4) | J60: =SUMIFS(Base[Montante],Base[Fornecedor],$A60&"",Base[Ano],J$4) | K60: =SUM(D60:J60)
A61: EM000488 | B61: ANDRE LIRA SILVA DA COSTA | C61: =IFERROR(INDEX(DePara[Categoria],MATCH(TEXT(A61,"0"),DePara[Fornecedor_txt],0)),"(sem categoria)") | D61: =SUMIFS(Base[Montante],Base[Fornecedor],$A61&"",Base[Ano],D$4) | E61: =SUMIFS(Base[Montante],Base[Fornecedor],$A61&"",Base[Ano],E$4) | F61: =SUMIFS(Base[Montante],Base[Fornecedor],$A61&"",Base[Ano],F$4) | G61: =SUMIFS(Base[Montante],Base[Fornecedor],$A61&"",Base[Ano],G$4) | H61: =SUMIFS(Base[Montante],Base[Fornecedor],$A61&"",Base[Ano],H$4) | I61: =SUMIFS(Base[Montante],Base[Fornecedor],$A61&"",Base[Ano],I$4) | J61: =SUMIFS(Base[Montante],Base[Fornecedor],$A61&"",Base[Ano],J$4) | K61: =SUM(D61:J61)
A62: EM000039 | B62: ANDRE LUIS MENDES VELOSO | C62: =IFERROR(INDEX(DePara[Categoria],MATCH(TEXT(A62,"0"),DePara[Fornecedor_txt],0)),"(sem categoria)") | D62: =SUMIFS(Base[Montante],Base[Fornecedor],$A62&"",Base[Ano],D$4) | E62: =SUMIFS(Base[Montante],Base[Fornecedor],$A62&"",Base[Ano],E$4) | F62: =SUMIFS(Base[Montante],Base[Fornecedor],$A62&"",Base[Ano],F$4) | G62: =SUMIFS(Base[Montante],Base[Fornecedor],$A62&"",Base[Ano],G$4) | H62: =SUMIFS(Base[Montante],Base[Fornecedor],$A62&"",Base[Ano],H$4) | I62: =SUMIFS(Base[Montante],Base[Fornecedor],$A62&"",Base[Ano],I$4) | J62: =SUMIFS(Base[Montante],Base[Fornecedor],$A62&"",Base[Ano],J$4) | K62: =SUM(D62:J62)
A63: 102452 | B63: ANTONIO FERNANDES VIEIRA | C63: =IFERROR(INDEX(DePara[Categoria],MATCH(TEXT(A63,"0"),DePara[Fornecedor_txt],0)),"(sem categoria)") | D63: =SUMIFS(Base[Montante],Base[Fornecedor],$A63&"",Base[Ano],D$4) | E63: =SUMIFS(Base[Montante],Base[Fornecedor],$A63&"",Base[Ano],E$4) | F63: =SUMIFS(Base[Montante],Base[Fornecedor],$A63&"",Base[Ano],F$4) | G63: =SUMIFS(Base[Montante],Base[Fornecedor],$A63&"",Base[Ano],G$4) | H63: =SUMIFS(Base[Montante],Base[Fornecedor],$A63&"",Base[Ano],H$4) | I63: =SUMIFS(Base[Montante],Base[Fornecedor],$A63&"",Base[Ano],I$4) | J63: =SUMIFS(Base[Montante],Base[Fornecedor],$A63&"",Base[Ano],J$4) | K63: =SUM(D63:J63)
A64: EM000862 | B64: ANTONIO FREIRE MENDES FILHO | C64: =IFERROR(INDEX(DePara[Categoria],MATCH(TEXT(A64,"0"),DePara[Fornecedor_txt],0)),"(sem categoria)") | D64: =SUMIFS(Base[Montante],Base[Fornecedor],$A64&"",Base[Ano],D$4) | E64: =SUMIFS(Base[Montante],Base[Fornecedor],$A64&"",Base[Ano],E$4) | F64: =SUMIFS(Base[Montante],Base[Fornecedor],$A64&"",Base[Ano],F$4) | G64: =SUMIFS(Base[Montante],Base[Fornecedor],$A64&"",Base[Ano],G$4) | H64: =SUMIFS(Base[Montante],Base[Fornecedor],$A64&"",Base[Ano],H$4) | I64: =SUMIFS(Base[Montante],Base[Fornecedor],$A64&"",Base[Ano],I$4) | J64: =SUMIFS(Base[Montante],Base[Fornecedor],$A64&"",Base[Ano],J$4) | K64: =SUM(D64:J64)
A65: 101377 | B65: APAGUE EQUIP DE COMBATE A INCENDIO | C65: =IFERROR(INDEX(DePara[Categoria],MATCH(TEXT(A65,"0"),DePara[Fornecedor_txt],0)),"(sem categoria)") | D65: =SUMIFS(Base[Montante],Base[Fornecedor],$A65&"",Base[Ano],D$4) | E65: =SUMIFS(Base[Montante],Base[Fornecedor],$A65&"",Base[Ano],E$4) | F65: =SUMIFS(Base[Montante],Base[Fornecedor],$A65&"",Base[Ano],F$4) | G65: =SUMIFS(Base[Montante],Base[Fornecedor],$A65&"",Base[Ano],G$4) | H65: =SUMIFS(Base[Montante],Base[Fornecedor],$A65&"",Base[Ano],H$4) | I65: =SUMIFS(Base[Montante],Base[Fornecedor],$A65&"",Base[Ano],I$4) | J65: =SUMIFS(Base[Montante],Base[Fornecedor],$A65&"",Base[Ano],J$4) | K65: =SUM(D65:J65)
A66: 101973 | B66: APM TERMINALS PECEM OPERACOES P LTD | C66: =IFERROR(INDEX(DePara[Categoria],MATCH(TEXT(A66,"0"),DePara[Fornecedor_txt],0)),"(sem categoria)") | D66: =SUMIFS(Base[Montante],Base[Fornecedor],$A66&"",Base[Ano],D$4) | E66: =SUMIFS(Base[Montante],Base[Fornecedor],$A66&"",Base[Ano],E$4) | F66: =SUMIFS(Base[Montante],Base[Fornecedor],$A66&"",Base[Ano],F$4) | G66: =SUMIFS(Base[Montante],Base[Fornecedor],$A66&"",Base[Ano],G$4) | H66: =SUMIFS(Base[Montante],Base[Fornecedor],$A66&"",Base[Ano],H$4) | I66: =SUMIFS(Base[Montante],Base[Fornecedor],$A66&"",Base[Ano],I$4) | J66: =SUMIFS(Base[Montante],Base[Fornecedor],$A66&"",Base[Ano],J$4) | K66: =SUM(D66:J66)
A67: 100406 | B67: APS COMPONENTES ELETRICOS SA | C67: =IFERROR(INDEX(DePara[Categoria],MATCH(TEXT(A67,"0"),DePara[Fornecedor_txt],0)),"(sem categoria)") | D67: =SUMIFS(Base[Montante],Base[Fornecedor],$A67&"",Base[Ano],D$4) | E67: =SUMIFS(Base[Montante],Base[Fornecedor],$A67&"",Base[Ano],E$4) | F67: =SUMIFS(Base[Montante],Base[Fornecedor],$A67&"",Base[Ano],F$4) | G67: =SUMIFS(Base[Montante],Base[Fornecedor],$A67&"",Base[Ano],G$4) | H67: =SUMIFS(Base[Montante],Base[Fornecedor],$A67&"",Base[Ano],H$4) | I67: =SUMIFS(Base[Montante],Base[Fornecedor],$A67&"",Base[Ano],I$4) | J67: =SUMIFS(Base[Montante],Base[Fornecedor],$A67&"",Base[Ano],J$4) | K67: =SUM(D67:J67)
A68: EM000297 | B68: ARIEL VANZETTO DUARTE | C68: =IFERROR(INDEX(DePara[Categoria],MATCH(TEXT(A68,"0"),DePara[Fornecedor_txt],0)),"(sem categoria)") | D68: =SUMIFS(Base[Montante],Base[Fornecedor],$A68&"",Base[Ano],D$4) | E68: =SUMIFS(Base[Montante],Base[Fornecedor],$A68&"",Base[Ano],E$4) | F68: =SUMIFS(Base[Montante],Base[Fornecedor],$A68&"",Base[Ano],F$4) | G68: =SUMIFS(Base[Montante],Base[Fornecedor],$A68&"",Base[Ano],G$4) | H68: =SUMIFS(Base[Montante],Base[Fornecedor],$A68&"",Base[Ano],H$4) | I68: =SUMIFS(Base[Montante],Base[Fornecedor],$A68&"",Base[Ano],I$4) | J68: =SUMIFS(Base[Montante],Base[Fornecedor],$A68&"",Base[Ano],J$4) | K68: =SUM(D68:J68)
A69: EM000161 | B69: ARIOVALDO COSTA FILHO | C69: =IFERROR(INDEX(DePara[Categoria],MATCH(TEXT(A69,"0"),DePara[Fornecedor_txt],0)),"(sem categoria)") | D69: =SUMIFS(Base[Montante],Base[Fornecedor],$A69&"",Base[Ano],D$4) | E69: =SUMIFS(Base[Montante],Base[Fornecedor],$A69&"",Base[Ano],E$4) | F69: =SUMIFS(Base[Montante],Base[Fornecedor],$A69&"",Base[Ano],F$4) | G69: =SUMIFS(Base[Montante],Base[Fornecedor],$A69&"",Base[Ano],G$4) | H69: =SUMIFS(Base[Montante],Base[Fornecedor],$A69&"",Base[Ano],H$4) | I69: =SUMIFS(Base[Montante],Base[Fornecedor],$A69&"",Base[Ano],I$4) | J69: =SUMIFS(Base[Montante],Base[Fornecedor],$A69&"",Base[Ano],J$4) | K69: =SUM(D69:J69)
A70: 102282 | B70: ARISTOTELES MARCIO SOUZA ARAUJO | C70: =IFERROR(INDEX(DePara[Categoria],MATCH(TEXT(A70,"0"),DePara[Fornecedor_txt],0)),"(sem categoria)") | D70: =SUMIFS(Base[Montante],Base[Fornecedor],$A70&"",Base[Ano],D$4) | E70: =SUMIFS(Base[Montante],Base[Fornecedor],$A70&"",Base[Ano],E$4) | F70: =SUMIFS(Base[Montante],Base[Fornecedor],$A70&"",Base[Ano],F$4) | G70: =SUMIFS(Base[Montante],Base[Fornecedor],$A70&"",Base[Ano],G$4) | H70: =SUMIFS(Base[Montante],Base[Fornecedor],$A70&"",Base[Ano],H$4) | I70: =SUMIFS(Base[Montante],Base[Fornecedor],$A70&"",Base[Ano],I$4) | J70: =SUMIFS(Base[Montante],Base[Fornecedor],$A70&"",Base[Ano],J$4) | K70: =SUM(D70:J70)
A71: 101703 | B71: ARK TEC GUARDA DE DOCUMENTOS LTDA | C71: =IFERROR(INDEX(DePara[Categoria],MATCH(TEXT(A71,"0"),DePara[Fornecedor_txt],0)),"(sem categoria)") | D71: =SUMIFS(Base[Montante],Base[Fornecedor],$A71&"",Base[Ano],D$4) | E71: =SUMIFS(Base[Montante],Base[Fornecedor],$A71&"",Base[Ano],E$4) | F71: =SUMIFS(Base[Montante],Base[Fornecedor],$A71&"",Base[Ano],F$4) | G71: =SUMIFS(Base[Montante],Base[Fornecedor],$A71&"",Base[Ano],G$4) | H71: =SUMIFS(Base[Montante],Base[Fornecedor],$A71&"",Base[Ano],H$4) | I71: =SUMIFS(Base[Montante],Base[Fornecedor],$A71&"",Base[Ano],I$4) | J71: =SUMIFS(Base[Montante],Base[Fornecedor],$A71&"",Base[Ano],J$4) | K71: =SUM(D71:J71)
A72: EM000048 | B72: ARLINDO ASTYZEM REGO | C72: =IFERROR(INDEX(DePara[Categoria],MATCH(TEXT(A72,"0"),DePara[Fornecedor_txt],0)),"(sem categoria)") | D72: =SUMIFS(Base[Montante],Base[Fornecedor],$A72&"",Base[Ano],D$4) | E72: =SUMIFS(Base[Montante],Base[Fornecedor],$A72&"",Base[Ano],E$4) | F72: =SUMIFS(Base[Montante],Base[Fornecedor],$A72&"",Base[Ano],F$4) | G72: =SUMIFS(Base[Montante],Base[Fornecedor],$A72&"",Base[Ano],G$4) | H72: =SUMIFS(Base[Montante],Base[Fornecedor],$A72&"",Base[Ano],H$4) | I72: =SUMIFS(Base[Montante],Base[Fornecedor],$A72&"",Base[Ano],I$4) | J72: =SUMIFS(Base[Montante],Base[Fornecedor],$A72&"",Base[Ano],J$4) | K72: =SUM(D72:J72)
A73: 101290 | B73: ARTH WIND SERVICES&CONSULTING EIREL | C73: =IFERROR(INDEX(DePara[Categoria],MATCH(TEXT(A73,"0"),DePara[Fornecedor_txt],0)),"(sem categoria)") | D73: =SUMIFS(Base[Montante],Base[Fornecedor],$A73&"",Base[Ano],D$4) | E73: =SUMIFS(Base[Montante],Base[Fornecedor],$A73&"",Base[Ano],E$4) | F73: =SUMIFS(Base[Montante],Base[Fornecedor],$A73&"",Base[Ano],F$4) | G73: =SUMIFS(Base[Montante],Base[Fornecedor],$A73&"",Base[Ano],G$4) | H73: =SUMIFS(Base[Montante],Base[Fornecedor],$A73&"",Base[Ano],H$4) | I73: =SUMIFS(Base[Montante],Base[Fornecedor],$A73&"",Base[Ano],I$4) | J73: =SUMIFS(Base[Montante],Base[Fornecedor],$A73&"",Base[Ano],J$4) | K73: =SUM(D73:J73)
A74: 102068 | B74: ASSESSORIA TECNICA ATENE LIMITADA | C74: =IFERROR(INDEX(DePara[Categoria],MATCH(TEXT(A74,"0"),DePara[Fornecedor_txt],0)),"(sem categoria)") | D74: =SUMIFS(Base[Montante],Base[Fornecedor],$A74&"",Base[Ano],D$4) | E74: =SUMIFS(Base[Montante],Base[Fornecedor],$A74&"",Base[Ano],E$4) | F74: =SUMIFS(Base[Montante],Base[Fornecedor],$A74&"",Base[Ano],F$4) | G74: =SUMIFS(Base[Montante],Base[Fornecedor],$A74&"",Base[Ano],G$4) | H74: =SUMIFS(Base[Montante],Base[Fornecedor],$A74&"",Base[Ano],H$4) | I74: =SUMIFS(Base[Montante],Base[Fornecedor],$A74&"",Base[Ano],I$4) | J74: =SUMIFS(Base[Montante],Base[Fornecedor],$A74&"",Base[Ano],J$4) | K74: =SUM(D74:J74)
A75: 101869 | B75: ASSOCIACAO BRASILEIRA DA IND DE MAQ | C75: =IFERROR(INDEX(DePara[Categoria],MATCH(TEXT(A75,"0"),DePara[Fornecedor_txt],0)),"(sem categoria)") | D75: =SUMIFS(Base[Montante],Base[Fornecedor],$A75&"",Base[Ano],D$4) | E75: =SUMIFS(Base[Montante],Base[Fornecedor],$A75&"",Base[Ano],E$4) | F75: =SUMIFS(Base[Montante],Base[Fornecedor],$A75&"",Base[Ano],F$4) | G75: =SUMIFS(Base[Montante],Base[Fornecedor],$A75&"",Base[Ano],G$4) | H75: =SUMIFS(Base[Montante],Base[Fornecedor],$A75&"",Base[Ano],H$4) | I75: =SUMIFS(Base[Montante],Base[Fornecedor],$A75&"",Base[Ano],I$4) | J75: =SUMIFS(Base[Montante],Base[Fornecedor],$A75&"",Base[Ano],J$4) | K75: =SUM(D75:J75)
A76: 102086 | B76: ASSOCIACAO BRASILEIRA E E ABEEOLICA | C76: =IFERROR(INDEX(DePara[Categoria],MATCH(TEXT(A76,"0"),DePara[Fornecedor_txt],0)),"(sem categoria)") | D76: =SUMIFS(Base[Montante],Base[Fornecedor],$A76&"",Base[Ano],D$4) | E76: =SUMIFS(Base[Montante],Base[Fornecedor],$A76&"",Base[Ano],E$4) | F76: =SUMIFS(Base[Montante],Base[Fornecedor],$A76&"",Base[Ano],F$4) | G76: =SUMIFS(Base[Montante],Base[Fornecedor],$A76&"",Base[Ano],G$4) | H76: =SUMIFS(Base[Montante],Base[Fornecedor],$A76&"",Base[Ano],H$4) | I76: =SUMIFS(Base[Montante],Base[Fornecedor],$A76&"",Base[Ano],I$4) | J76: =SUMIFS(Base[Montante],Base[Fornecedor],$A76&"",Base[Ano],J$4) | K76: =SUM(D76:J76)
A77: EM000162 | B77: ASSUERO SAVIO TEIXEIRA SOUSA | C77: =IFERROR(INDEX(DePara[Categoria],MATCH(TEXT(A77,"0"),DePara[Fornecedor_txt],0)),"(sem categoria)") | D77: =SUMIFS(Base[Montante],Base[Fornecedor],$A77&"",Base[Ano],D$4) | E77: =SUMIFS(Base[Montante],Base[Fornecedor],$A77&"",Base[Ano],E$4) | F77: =SUMIFS(Base[Montante],Base[Fornecedor],$A77&"",Base[Ano],F$4) | G77: =SUMIFS(Base[Montante],Base[Fornecedor],$A77&"",Base[Ano],G$4) | H77: =SUMIFS(Base[Montante],Base[Fornecedor],$A77&"",Base[Ano],H$4) | I77: =SUMIFS(Base[Montante],Base[Fornecedor],$A77&"",Base[Ano],I$4) | J77: =SUMIFS(Base[Montante],Base[Fornecedor],$A77&"",Base[Ano],J$4) | K77: =SUM(D77:J77)
A78: 101387 | B78: AZEVEDO ENGENHARIA E PARTICIPAÇÕES | C78: =IFERROR(INDEX(DePara[Categoria],MATCH(TEXT(A78,"0"),DePara[Fornecedor_txt],0)),"(sem categoria)") | D78: =SUMIFS(Base[Montante],Base[Fornecedor],$A78&"",Base[Ano],D$4) | E78: =SUMIFS(Base[Montante],Base[Fornecedor],$A78&"",Base[Ano],E$4) | F78: =SUMIFS(Base[Montante],Base[Fornecedor],$A78&"",Base[Ano],F$4) | G78: =SUMIFS(Base[Montante],Base[Fornecedor],$A78&"",Base[Ano],G$4) | H78: =SUMIFS(Base[Montante],Base[Fornecedor],$A78&"",Base[Ano],H$4) | I78: =SUMIFS(Base[Montante],Base[Fornecedor],$A78&"",Base[Ano],I$4) | J78: =SUMIFS(Base[Montante],Base[Fornecedor],$A78&"",Base[Ano],J$4) | K78: =SUM(D78:J78)
A79: 104134 | B79: B&M LOGISTICA INTERNACIONAL LTDA 07720307000106 | C79: =IFERROR(INDEX(DePara[Categoria],MATCH(TEXT(A79,"0"),DePara[Fornecedor_txt],0)),"(sem categoria)") | D79: =SUMIFS(Base[Montante],Base[Fornecedor],$A79&"",Base[Ano],D$4) | E79: =SUMIFS(Base[Montante],Base[Fornecedor],$A79&"",Base[Ano],E$4) | F79: =SUMIFS(Base[Montante],Base[Fornecedor],$A79&"",Base[Ano],F$4) | G79: =SUMIFS(Base[Montante],Base[Fornecedor],$A79&"",Base[Ano],G$4) | H79: =SUMIFS(Base[Montante],Base[Fornecedor],$A79&"",Base[Ano],H$4) | I79: =SUMIFS(Base[Montante],Base[Fornecedor],$A79&"",Base[Ano],I$4) | J79: =SUMIFS(Base[Montante],Base[Fornecedor],$A79&"",Base[Ano],J$4) | K79: =SUM(D79:J79)
A80: 101622 | B80: BAGAREL COMERCIO DE INSTRUMENTOS LT | C80: =IFERROR(INDEX(DePara[Categoria],MATCH(TEXT(A80,"0"),DePara[Fornecedor_txt],0)),"(sem categoria)") | D80: =SUMIFS(Base[Montante],Base[Fornecedor],$A80&"",Base[Ano],D$4) | E80: =SUMIFS(Base[Montante],Base[Fornecedor],$A80&"",Base[Ano],E$4) | F80: =SUMIFS(Base[Montante],Base[Fornecedor],$A80&"",Base[Ano],F$4) | G80: =SUMIFS(Base[Montante],Base[Fornecedor],$A80&"",Base[Ano],G$4) | H80: =SUMIFS(Base[Montante],Base[Fornecedor],$A80&"",Base[Ano],H$4) | I80: =SUMIFS(Base[Montante],Base[Fornecedor],$A80&"",Base[Ano],I$4) | J80: =SUMIFS(Base[Montante],Base[Fornecedor],$A80&"",Base[Ano],J$4) | K80: =SUM(D80:J80)
A81: 102472 | B81: BALASKA EQUIPE INDUSTRIA E COMERCIO | C81: =IFERROR(INDEX(DePara[Categoria],MATCH(TEXT(A81,"0"),DePara[Fornecedor_txt],0)),"(sem categoria)") | D81: =SUMIFS(Base[Montante],Base[Fornecedor],$A81&"",Base[Ano],D$4) | E81: =SUMIFS(Base[Montante],Base[Fornecedor],$A81&"",Base[Ano],E$4) | F81: =SUMIFS(Base[Montante],Base[Fornecedor],$A81&"",Base[Ano],F$4) | G81: =SUMIFS(Base[Montante],Base[Fornecedor],$A81&"",Base[Ano],G$4) | H81: =SUMIFS(Base[Montante],Base[Fornecedor],$A81&"",Base[Ano],H$4) | I81: =SUMIFS(Base[Montante],Base[Fornecedor],$A81&"",Base[Ano],I$4) | J81: =SUMIFS(Base[Montante],Base[Fornecedor],$A81&"",Base[Ano],J$4) | K81: =SUM(D81:J81)
A82: 101888 | B82: BANCO SANTANDER BRASIL SA | C82: =IFERROR(INDEX(DePara[Categoria],MATCH(TEXT(A82,"0"),DePara[Fornecedor_txt],0)),"(sem categoria)") | D82: =SUMIFS(Base[Montante],Base[Fornecedor],$A82&"",Base[Ano],D$4) | E82: =SUMIFS(Base[Montante],Base[Fornecedor],$A82&"",Base[Ano],E$4) | F82: =SUMIFS(Base[Montante],Base[Fornecedor],$A82&"",Base[Ano],F$4) | G82: =SUMIFS(Base[Montante],Base[Fornecedor],$A82&"",Base[Ano],G$4) | H82: =SUMIFS(Base[Montante],Base[Fornecedor],$A82&"",Base[Ano],H$4) | I82: =SUMIFS(Base[Montante],Base[Fornecedor],$A82&"",Base[Ano],I$4) | J82: =SUMIFS(Base[Montante],Base[Fornecedor],$A82&"",Base[Ano],J$4) | K82: =SUM(D82:J82)
A83: 101547 | B83: BARRACUDA PRODUTOS MATERIAIS C LTDA | C83: =IFERROR(INDEX(DePara[Categoria],MATCH(TEXT(A83,"0"),DePara[Fornecedor_txt],0)),"(sem categoria)") | D83: =SUMIFS(Base[Montante],Base[Fornecedor],$A83&"",Base[Ano],D$4) | E83: =SUMIFS(Base[Montante],Base[Fornecedor],$A83&"",Base[Ano],E$4) | F83: =SUMIFS(Base[Montante],Base[Fornecedor],$A83&"",Base[Ano],F$4) | G83: =SUMIFS(Base[Montante],Base[Fornecedor],$A83&"",Base[Ano],G$4) | H83: =SUMIFS(Base[Montante],Base[Fornecedor],$A83&"",Base[Ano],H$4) | I83: =SUMIFS(Base[Montante],Base[Fornecedor],$A83&"",Base[Ano],I$4) | J83: =SUMIFS(Base[Montante],Base[Fornecedor],$A83&"",Base[Ano],J$4) | K83: =SUM(D83:J83)
A84: 102433 | B84: BECOMEX CONSULTORIA LTDA | C84: =IFERROR(INDEX(DePara[Categoria],MATCH(TEXT(A84,"0"),DePara[Fornecedor_txt],0)),"(sem categoria)") | D84: =SUMIFS(Base[Montante],Base[Fornecedor],$A84&"",Base[Ano],D$4) | E84: =SUMIFS(Base[Montante],Base[Fornecedor],$A84&"",Base[Ano],E$4) | F84: =SUMIFS(Base[Montante],Base[Fornecedor],$A84&"",Base[Ano],F$4) | G84: =SUMIFS(Base[Montante],Base[Fornecedor],$A84&"",Base[Ano],G$4) | H84: =SUMIFS(Base[Montante],Base[Fornecedor],$A84&"",Base[Ano],H$4) | I84: =SUMIFS(Base[Montante],Base[Fornecedor],$A84&"",Base[Ano],I$4) | J84: =SUMIFS(Base[Montante],Base[Fornecedor],$A84&"",Base[Ano],J$4) | K84: =SUM(D84:J84)
A85: 103936 | B85: BELA VISTA RENOVAVEIS II LTDA | C85: =IFERROR(INDEX(DePara[Categoria],MATCH(TEXT(A85,"0"),DePara[Fornecedor_txt],0)),"(sem categoria)") | D85: =SUMIFS(Base[Montante],Base[Fornecedor],$A85&"",Base[Ano],D$4) | E85: =SUMIFS(Base[Montante],Base[Fornecedor],$A85&"",Base[Ano],E$4) | F85: =SUMIFS(Base[Montante],Base[Fornecedor],$A85&"",Base[Ano],F$4) | G85: =SUMIFS(Base[Montante],Base[Fornecedor],$A85&"",Base[Ano],G$4) | H85: =SUMIFS(Base[Montante],Base[Fornecedor],$A85&"",Base[Ano],H$4) | I85: =SUMIFS(Base[Montante],Base[Fornecedor],$A85&"",Base[Ano],I$4) | J85: =SUMIFS(Base[Montante],Base[Fornecedor],$A85&"",Base[Ano],J$4) | K85: =SUM(D85:J85)
A86: EM000868 | B86: BERNARDO SÉRGIO MENDONÇA | C86: =IFERROR(INDEX(DePara[Categoria],MATCH(TEXT(A86,"0"),DePara[Fornecedor_txt],0)),"(sem categoria)") | D86: =SUMIFS(Base[Montante],Base[Fornecedor],$A86&"",Base[Ano],D$4) | E86: =SUMIFS(Base[Montante],Base[Fornecedor],$A86&"",Base[Ano],E$4) | F86: =SUMIFS(Base[Montante],Base[Fornecedor],$A86&"",Base[Ano],F$4) | G86: =SUMIFS(Base[Montante],Base[Fornecedor],$A86&"",Base[Ano],G$4) | H86: =SUMIFS(Base[Montante],Base[Fornecedor],$A86&"",Base[Ano],H$4) | I86: =SUMIFS(Base[Montante],Base[Fornecedor],$A86&"",Base[Ano],I$4) | J86: =SUMIFS(Base[Montante],Base[Fornecedor],$A86&"",Base[Ano],J$4) | K86: =SUM(D86:J86)
A87: 107723 | B87: BLUEWAY TRADING IMPORTACAO E EXPORT S.A | C87: =IFERROR(INDEX(DePara[Categoria],MATCH(TEXT(A87,"0"),DePara[Fornecedor_txt],0)),"(sem categoria)") | D87: =SUMIFS(Base[Montante],Base[Fornecedor],$A87&"",Base[Ano],D$4) | E87: =SUMIFS(Base[Montante],Base[Fornecedor],$A87&"",Base[Ano],E$4) | F87: =SUMIFS(Base[Montante],Base[Fornecedor],$A87&"",Base[Ano],F$4) | G87: =SUMIFS(Base[Montante],Base[Fornecedor],$A87&"",Base[Ano],G$4) | H87: =SUMIFS(Base[Montante],Base[Fornecedor],$A87&"",Base[Ano],H$4) | I87: =SUMIFS(Base[Montante],Base[Fornecedor],$A87&"",Base[Ano],I$4) | J87: =SUMIFS(Base[Montante],Base[Fornecedor],$A87&"",Base[Ano],J$4) | K87: =SUM(D87:J87)
A88: 100631 | B88: BRANDAO FILHOS FORTSHIP AGENCIA MAR 11826476000100 | C88: =IFERROR(INDEX(DePara[Categoria],MATCH(TEXT(A88,"0"),DePara[Fornecedor_txt],0)),"(sem categoria)") | D88: =SUMIFS(Base[Montante],Base[Fornecedor],$A88&"",Base[Ano],D$4) | E88: =SUMIFS(Base[Montante],Base[Fornecedor],$A88&"",Base[Ano],E$4) | F88: =SUMIFS(Base[Montante],Base[Fornecedor],$A88&"",Base[Ano],F$4) | G88: =SUMIFS(Base[Montante],Base[Fornecedor],$A88&"",Base[Ano],G$4) | H88: =SUMIFS(Base[Montante],Base[Fornecedor],$A88&"",Base[Ano],H$4) | I88: =SUMIFS(Base[Montante],Base[Fornecedor],$A88&"",Base[Ano],I$4) | J88: =SUMIFS(Base[Montante],Base[Fornecedor],$A88&"",Base[Ano],J$4) | K88: =SUM(D88:J88)
A89: 100566 | B89: BRASIL TERMINAL PORTUARIO S.A. | C89: =IFERROR(INDEX(DePara[Categoria],MATCH(TEXT(A89,"0"),DePara[Fornecedor_txt],0)),"(sem categoria)") | D89: =SUMIFS(Base[Montante],Base[Fornecedor],$A89&"",Base[Ano],D$4) | E89: =SUMIFS(Base[Montante],Base[Fornecedor],$A89&"",Base[Ano],E$4) | F89: =SUMIFS(Base[Montante],Base[Fornecedor],$A89&"",Base[Ano],F$4) | G89: =SUMIFS(Base[Montante],Base[Fornecedor],$A89&"",Base[Ano],G$4) | H89: =SUMIFS(Base[Montante],Base[Fornecedor],$A89&"",Base[Ano],H$4) | I89: =SUMIFS(Base[Montante],Base[Fornecedor],$A89&"",Base[Ano],I$4) | J89: =SUMIFS(Base[Montante],Base[Fornecedor],$A89&"",Base[Ano],J$4) | K89: =SUM(D89:J89)
A90: 103772 | B90: BRASPRESS TRANSPORTES URGENTES LTDA | C90: =IFERROR(INDEX(DePara[Categoria],MATCH(TEXT(A90,"0"),DePara[Fornecedor_txt],0)),"(sem categoria)") | D90: =SUMIFS(Base[Montante],Base[Fornecedor],$A90&"",Base[Ano],D$4) | E90: =SUMIFS(Base[Montante],Base[Fornecedor],$A90&"",Base[Ano],E$4) | F90: =SUMIFS(Base[Montante],Base[Fornecedor],$A90&"",Base[Ano],F$4) | G90: =SUMIFS(Base[Montante],Base[Fornecedor],$A90&"",Base[Ano],G$4) | H90: =SUMIFS(Base[Montante],Base[Fornecedor],$A90&"",Base[Ano],H$4) | I90: =SUMIFS(Base[Montante],Base[Fornecedor],$A90&"",Base[Ano],I$4) | J90: =SUMIFS(Base[Montante],Base[Fornecedor],$A90&"",Base[Ano],J$4) | K90: =SUM(D90:J90)
A91: 100956 | B91: BREMER LLOYD BRAZIL LOGISTICS LTDA | C91: =IFERROR(INDEX(DePara[Categoria],MATCH(TEXT(A91,"0"),DePara[Fornecedor_txt],0)),"(sem categoria)") | D91: =SUMIFS(Base[Montante],Base[Fornecedor],$A91&"",Base[Ano],D$4) | E91: =SUMIFS(Base[Montante],Base[Fornecedor],$A91&"",Base[Ano],E$4) | F91: =SUMIFS(Base[Montante],Base[Fornecedor],$A91&"",Base[Ano],F$4) | G91: =SUMIFS(Base[Montante],Base[Fornecedor],$A91&"",Base[Ano],G$4) | H91: =SUMIFS(Base[Montante],Base[Fornecedor],$A91&"",Base[Ano],H$4) | I91: =SUMIFS(Base[Montante],Base[Fornecedor],$A91&"",Base[Ano],I$4) | J91: =SUMIFS(Base[Montante],Base[Fornecedor],$A91&"",Base[Ano],J$4) | K91: =SUM(D91:J91)
A92: 107311 | B92: BRS SUPRIMENTOS CORPORATIVOS S A | C92: =IFERROR(INDEX(DePara[Categoria],MATCH(TEXT(A92,"0"),DePara[Fornecedor_txt],0)),"(sem categoria)") | D92: =SUMIFS(Base[Montante],Base[Fornecedor],$A92&"",Base[Ano],D$4) | E92: =SUMIFS(Base[Montante],Base[Fornecedor],$A92&"",Base[Ano],E$4) | F92: =SUMIFS(Base[Montante],Base[Fornecedor],$A92&"",Base[Ano],F$4) | G92: =SUMIFS(Base[Montante],Base[Fornecedor],$A92&"",Base[Ano],G$4) | H92: =SUMIFS(Base[Montante],Base[Fornecedor],$A92&"",Base[Ano],H$4) | I92: =SUMIFS(Base[Montante],Base[Fornecedor],$A92&"",Base[Ano],I$4) | J92: =SUMIFS(Base[Montante],Base[Fornecedor],$A92&"",Base[Ano],J$4) | K92: =SUM(D92:J92)
A93: EM000792 | B93: BRUNO INÁCIO LOURENÇO | C93: =IFERROR(INDEX(DePara[Categoria],MATCH(TEXT(A93,"0"),DePara[Fornecedor_txt],0)),"(sem categoria)") | D93: =SUMIFS(Base[Montante],Base[Fornecedor],$A93&"",Base[Ano],D$4) | E93: =SUMIFS(Base[Montante],Base[Fornecedor],$A93&"",Base[Ano],E$4) | F93: =SUMIFS(Base[Montante],Base[Fornecedor],$A93&"",Base[Ano],F$4) | G93: =SUMIFS(Base[Montante],Base[Fornecedor],$A93&"",Base[Ano],G$4) | H93: =SUMIFS(Base[Montante],Base[Fornecedor],$A93&"",Base[Ano],H$4) | I93: =SUMIFS(Base[Montante],Base[Fornecedor],$A93&"",Base[Ano],I$4) | J93: =SUMIFS(Base[Montante],Base[Fornecedor],$A93&"",Base[Ano],J$4) | K93: =SUM(D93:J93)
A94: EM000390 | B94: BRUNO RAFAEL REBOUCAS DE SOUZA | C94: =IFERROR(INDEX(DePara[Categoria],MATCH(TEXT(A94,"0"),DePara[Fornecedor_txt],0)),"(sem categoria)") | D94: =SUMIFS(Base[Montante],Base[Fornecedor],$A94&"",Base[Ano],D$4) | E94: =SUMIFS(Base[Montante],Base[Fornecedor],$A94&"",Base[Ano],E$4) | F94: =SUMIFS(Base[Montante],Base[Fornecedor],$A94&"",Base[Ano],F$4) | G94: =SUMIFS(Base[Montante],Base[Fornecedor],$A94&"",Base[Ano],G$4) | H94: =SUMIFS(Base[Montante],Base[Fornecedor],$A94&"",Base[Ano],H$4) | I94: =SUMIFS(Base[Montante],Base[Fornecedor],$A94&"",Base[Ano],I$4) | J94: =SUMIFS(Base[Montante],Base[Fornecedor],$A94&"",Base[Ano],J$4) | K94: =SUM(D94:J94)
A95: EM000081 | B95: BRUNO VINICIUS MOREIRA CARDOSO | C95: =IFERROR(INDEX(DePara[Categoria],MATCH(TEXT(A95,"0"),DePara[Fornecedor_txt],0)),"(sem categoria)") | D95: =SUMIFS(Base[Montante],Base[Fornecedor],$A95&"",Base[Ano],D$4) | E95: =SUMIFS(Base[Montante],Base[Fornecedor],$A95&"",Base[Ano],E$4) | F95: =SUMIFS(Base[Montante],Base[Fornecedor],$A95&"",Base[Ano],F$4) | G95: =SUMIFS(Base[Montante],Base[Fornecedor],$A95&"",Base[Ano],G$4) | H95: =SUMIFS(Base[Montante],Base[Fornecedor],$A95&"",Base[Ano],H$4) | I95: =SUMIFS(Base[Montante],Base[Fornecedor],$A95&"",Base[Ano],I$4) | J95: =SUMIFS(Base[Montante],Base[Fornecedor],$A95&"",Base[Ano],J$4) | K95: =SUM(D95:J95)
A96: 101826 | B96: BUNZL EQUIP DE PROTECÃO INDIVIDUAL | C96: =IFERROR(INDEX(DePara[Categoria],MATCH(TEXT(A96,"0"),DePara[Fornecedor_txt],0)),"(sem categoria)") | D96: =SUMIFS(Base[Montante],Base[Fornecedor],$A96&"",Base[Ano],D$4) | E96: =SUMIFS(Base[Montante],Base[Fornecedor],$A96&"",Base[Ano],E$4) | F96: =SUMIFS(Base[Montante],Base[Fornecedor],$A96&"",Base[Ano],F$4) | G96: =SUMIFS(Base[Montante],Base[Fornecedor],$A96&"",Base[Ano],G$4) | H96: =SUMIFS(Base[Montante],Base[Fornecedor],$A96&"",Base[Ano],H$4) | I96: =SUMIFS(Base[Montante],Base[Fornecedor],$A96&"",Base[Ano],I$4) | J96: =SUMIFS(Base[Montante],Base[Fornecedor],$A96&"",Base[Ano],J$4) | K96: =SUM(D96:J96)
A97: 101632 | B97: BVQI DO BRASIL SOCIEDADE CERTIFICAD | C97: =IFERROR(INDEX(DePara[Categoria],MATCH(TEXT(A97,"0"),DePara[Fornecedor_txt],0)),"(sem categoria)") | D97: =SUMIFS(Base[Montante],Base[Fornecedor],$A97&"",Base[Ano],D$4) | E97: =SUMIFS(Base[Montante],Base[Fornecedor],$A97&"",Base[Ano],E$4) | F97: =SUMIFS(Base[Montante],Base[Fornecedor],$A97&"",Base[Ano],F$4) | G97: =SUMIFS(Base[Montante],Base[Fornecedor],$A97&"",Base[Ano],G$4) | H97: =SUMIFS(Base[Montante],Base[Fornecedor],$A97&"",Base[Ano],H$4) | I97: =SUMIFS(Base[Montante],Base[Fornecedor],$A97&"",Base[Ano],I$4) | J97: =SUMIFS(Base[Montante],Base[Fornecedor],$A97&"",Base[Ano],J$4) | K97: =SUM(D97:J97)
A98: 101765 | B98: C DA SILVA CARVALHO E FILHA LTDA | C98: =IFERROR(INDEX(DePara[Categoria],MATCH(TEXT(A98,"0"),DePara[Fornecedor_txt],0)),"(sem categoria)") | D98: =SUMIFS(Base[Montante],Base[Fornecedor],$A98&"",Base[Ano],D$4) | E98: =SUMIFS(Base[Montante],Base[Fornecedor],$A98&"",Base[Ano],E$4) | F98: =SUMIFS(Base[Montante],Base[Fornecedor],$A98&"",Base[Ano],F$4) | G98: =SUMIFS(Base[Montante],Base[Fornecedor],$A98&"",Base[Ano],G$4) | H98: =SUMIFS(Base[Montante],Base[Fornecedor],$A98&"",Base[Ano],H$4) | I98: =SUMIFS(Base[Montante],Base[Fornecedor],$A98&"",Base[Ano],I$4) | J98: =SUMIFS(Base[Montante],Base[Fornecedor],$A98&"",Base[Ano],J$4) | K98: =SUM(D98:J98)
A99: 102426 | B99: CAFE COM COMPRADOR CONSULTORIA EMPR | C99: =IFERROR(INDEX(DePara[Categoria],MATCH(TEXT(A99,"0"),DePara[Fornecedor_txt],0)),"(sem categoria)") | D99: =SUMIFS(Base[Montante],Base[Fornecedor],$A99&"",Base[Ano],D$4) | E99: =SUMIFS(Base[Montante],Base[Fornecedor],$A99&"",Base[Ano],E$4) | F99: =SUMIFS(Base[Montante],Base[Fornecedor],$A99&"",Base[Ano],F$4) | G99: =SUMIFS(Base[Montante],Base[Fornecedor],$A99&"",Base[Ano],G$4) | H99: =SUMIFS(Base[Montante],Base[Fornecedor],$A99&"",Base[Ano],H$4) | I99: =SUMIFS(Base[Montante],Base[Fornecedor],$A99&"",Base[Ano],I$4) | J99: =SUMIFS(Base[Montante],Base[Fornecedor],$A99&"",Base[Ano],J$4) | K99: =SUM(D99:J99)
A100: EM003594 | B100: CAIO GEANDERSON MACIEL MARTINS | C100: =IFERROR(INDEX(DePara[Categoria],MATCH(TEXT(A100,"0"),DePara[Fornecedor_txt],0)),"(sem categoria)") | D100: =SUMIFS(Base[Montante],Base[Fornecedor],$A100&"",Base[Ano],D$4) | E100: =SUMIFS(Base[Montante],Base[Fornecedor],$A100&"",Base[Ano],E$4) | F100: =SUMIFS(Base[Montante],Base[Fornecedor],$A100&"",Base[Ano],F$4) | G100: =SUMIFS(Base[Montante],Base[Fornecedor],$A100&"",Base[Ano],G$4) | H100: =SUMIFS(Base[Montante],Base[Fornecedor],$A100&"",Base[Ano],H$4) | I100: =SUMIFS(Base[Montante],Base[Fornecedor],$A100&"",Base[Ano],I$4) | J100: =SUMIFS(Base[Montante],Base[Fornecedor],$A100&"",Base[Ano],J$4) | K100: =SUM(D100:J100)
A101: 102087 | B101: CAIXA ECONOMICA FEDERAL | C101: =IFERROR(INDEX(DePara[Categoria],MATCH(TEXT(A101,"0"),DePara[Fornecedor_txt],0)),"(sem categoria)") | D101: =SUMIFS(Base[Montante],Base[Fornecedor],$A101&"",Base[Ano],D$4) | E101: =SUMIFS(Base[Montante],Base[Fornecedor],$A101&"",Base[Ano],E$4) | F101: =SUMIFS(Base[Montante],Base[Fornecedor],$A101&"",Base[Ano],F$4) | G101: =SUMIFS(Base[Montante],Base[Fornecedor],$A101&"",Base[Ano],G$4) | H101: =SUMIFS(Base[Montante],Base[Fornecedor],$A101&"",Base[Ano],H$4) | I101: =SUMIFS(Base[Montante],Base[Fornecedor],$A101&"",Base[Ano],I$4) | J101: =SUMIFS(Base[Montante],Base[Fornecedor],$A101&"",Base[Ano],J$4) | K101: =SUM(D101:J101)
A102: 100621 | B102: CALTER ENGENHARIA LTDA | C102: =IFERROR(INDEX(DePara[Categoria],MATCH(TEXT(A102,"0"),DePara[Fornecedor_txt],0)),"(sem categoria)") | D102: =SUMIFS(Base[Montante],Base[Fornecedor],$A102&"",Base[Ano],D$4) | E102: =SUMIFS(Base[Montante],Base[Fornecedor],$A102&"",Base[Ano],E$4) | F102: =SUMIFS(Base[Montante],Base[Fornecedor],$A102&"",Base[Ano],F$4) | G102: =SUMIFS(Base[Montante],Base[Fornecedor],$A102&"",Base[Ano],G$4) | H102: =SUMIFS(Base[Montante],Base[Fornecedor],$A102&"",Base[Ano],H$4) | I102: =SUMIFS(Base[Montante],Base[Fornecedor],$A102&"",Base[Ano],I$4) | J102: =SUMIFS(Base[Montante],Base[Fornecedor],$A102&"",Base[Ano],J$4) | K102: =SUM(D102:J102)
A103: 100161 | B103: CAMARA DE COM E IND BRASIL ALEMANHA | C103: =IFERROR(INDEX(DePara[Categoria],MATCH(TEXT(A103,"0"),DePara[Fornecedor_txt],0)),"(sem categoria)") | D103: =SUMIFS(Base[Montante],Base[Fornecedor],$A103&"",Base[Ano],D$4) | E103: =SUMIFS(Base[Montante],Base[Fornecedor],$A103&"",Base[Ano],E$4) | F103: =SUMIFS(Base[Montante],Base[Fornecedor],$A103&"",Base[Ano],F$4) | G103: =SUMIFS(Base[Montante],Base[Fornecedor],$A103&"",Base[Ano],G$4) | H103: =SUMIFS(Base[Montante],Base[Fornecedor],$A103&"",Base[Ano],H$4) | I103: =SUMIFS(Base[Montante],Base[Fornecedor],$A103&"",Base[Ano],I$4) | J103: =SUMIFS(Base[Montante],Base[Fornecedor],$A103&"",Base[Ano],J$4) | K103: =SUM(D103:J103)
A104: 101056 | B104: CAMARA DE COMER ENERGIA ELETRICA CC | C104: =IFERROR(INDEX(DePara[Categoria],MATCH(TEXT(A104,"0"),DePara[Fornecedor_txt],0)),"(sem categoria)") | D104: =SUMIFS(Base[Montante],Base[Fornecedor],$A104&"",Base[Ano],D$4) | E104: =SUMIFS(Base[Montante],Base[Fornecedor],$A104&"",Base[Ano],E$4) | F104: =SUMIFS(Base[Montante],Base[Fornecedor],$A104&"",Base[Ano],F$4) | G104: =SUMIFS(Base[Montante],Base[Fornecedor],$A104&"",Base[Ano],G$4) | H104: =SUMIFS(Base[Montante],Base[Fornecedor],$A104&"",Base[Ano],H$4) | I104: =SUMIFS(Base[Montante],Base[Fornecedor],$A104&"",Base[Ano],I$4) | J104: =SUMIFS(Base[Montante],Base[Fornecedor],$A104&"",Base[Ano],J$4) | K104: =SUM(D104:J104)
A105: EM000550 | B105: CAMILA ROCHA | C105: =IFERROR(INDEX(DePara[Categoria],MATCH(TEXT(A105,"0"),DePara[Fornecedor_txt],0)),"(sem categoria)") | D105: =SUMIFS(Base[Montante],Base[Fornecedor],$A105&"",Base[Ano],D$4) | E105: =SUMIFS(Base[Montante],Base[Fornecedor],$A105&"",Base[Ano],E$4) | F105: =SUMIFS(Base[Montante],Base[Fornecedor],$A105&"",Base[Ano],F$4) | G105: =SUMIFS(Base[Montante],Base[Fornecedor],$A105&"",Base[Ano],G$4) | H105: =SUMIFS(Base[Montante],Base[Fornecedor],$A105&"",Base[Ano],H$4) | I105: =SUMIFS(Base[Montante],Base[Fornecedor],$A105&"",Base[Ano],I$4) | J105: =SUMIFS(Base[Montante],Base[Fornecedor],$A105&"",Base[Ano],J$4) | K105: =SUM(D105:J105)
A106: EM000143 | B106: CARLOS ADRIANO SILVA DE OLIVEIRA | C106: =IFERROR(INDEX(DePara[Categoria],MATCH(TEXT(A106,"0"),DePara[Fornecedor_txt],0)),"(sem categoria)") | D106: =SUMIFS(Base[Montante],Base[Fornecedor],$A106&"",Base[Ano],D$4) | E106: =SUMIFS(Base[Montante],Base[Fornecedor],$A106&"",Base[Ano],E$4) | F106: =SUMIFS(Base[Montante],Base[Fornecedor],$A106&"",Base[Ano],F$4) | G106: =SUMIFS(Base[Montante],Base[Fornecedor],$A106&"",Base[Ano],G$4) | H106: =SUMIFS(Base[Montante],Base[Fornecedor],$A106&"",Base[Ano],H$4) | I106: =SUMIFS(Base[Montante],Base[Fornecedor],$A106&"",Base[Ano],I$4) | J106: =SUMIFS(Base[Montante],Base[Fornecedor],$A106&"",Base[Ano],J$4) | K106: =SUM(D106:J106)
A107: EM000093 | B107: CARLOS ALVES DE AZEVEDO | C107: =IFERROR(INDEX(DePara[Categoria],MATCH(TEXT(A107,"0"),DePara[Fornecedor_txt],0)),"(sem categoria)") | D107: =SUMIFS(Base[Montante],Base[Fornecedor],$A107&"",Base[Ano],D$4) | E107: =SUMIFS(Base[Montante],Base[Fornecedor],$A107&"",Base[Ano],E$4) | F107: =SUMIFS(Base[Montante],Base[Fornecedor],$A107&"",Base[Ano],F$4) | G107: =SUMIFS(Base[Montante],Base[Fornecedor],$A107&"",Base[Ano],G$4) | H107: =SUMIFS(Base[Montante],Base[Fornecedor],$A107&"",Base[Ano],H$4) | I107: =SUMIFS(Base[Montante],Base[Fornecedor],$A107&"",Base[Ano],I$4) | J107: =SUMIFS(Base[Montante],Base[Fornecedor],$A107&"",Base[Ano],J$4) | K107: =SUM(D107:J107)
A108: EM000458 | B108: CARLOS CESAR FONSECA MACHADO | C108: =IFERROR(INDEX(DePara[Categoria],MATCH(TEXT(A108,"0"),DePara[Fornecedor_txt],0)),"(sem categoria)") | D108: =SUMIFS(Base[Montante],Base[Fornecedor],$A108&"",Base[Ano],D$4) | E108: =SUMIFS(Base[Montante],Base[Fornecedor],$A108&"",Base[Ano],E$4) | F108: =SUMIFS(Base[Montante],Base[Fornecedor],$A108&"",Base[Ano],F$4) | G108: =SUMIFS(Base[Montante],Base[Fornecedor],$A108&"",Base[Ano],G$4) | H108: =SUMIFS(Base[Montante],Base[Fornecedor],$A108&"",Base[Ano],H$4) | I108: =SUMIFS(Base[Montante],Base[Fornecedor],$A108&"",Base[Ano],I$4) | J108: =SUMIFS(Base[Montante],Base[Fornecedor],$A108&"",Base[Ano],J$4) | K108: =SUM(D108:J108)
A109: 108017 | B109: CARLOS DIAS DOS SANTOS | C109: =IFERROR(INDEX(DePara[Categoria],MATCH(TEXT(A109,"0"),DePara[Fornecedor_txt],0)),"(sem categoria)") | D109: =SUMIFS(Base[Montante],Base[Fornecedor],$A109&"",Base[Ano],D$4) | E109: =SUMIFS(Base[Montante],Base[Fornecedor],$A109&"",Base[Ano],E$4) | F109: =SUMIFS(Base[Montante],Base[Fornecedor],$A109&"",Base[Ano],F$4) | G109: =SUMIFS(Base[Montante],Base[Fornecedor],$A109&"",Base[Ano],G$4) | H109: =SUMIFS(Base[Montante],Base[Fornecedor],$A109&"",Base[Ano],H$4) | I109: =SUMIFS(Base[Montante],Base[Fornecedor],$A109&"",Base[Ano],I$4) | J109: =SUMIFS(Base[Montante],Base[Fornecedor],$A109&"",Base[Ano],J$4) | K109: =SUM(D109:J109)
A110: EM000310 | B110: CARLOS EDUARDO LAUREANO | C110: =IFERROR(INDEX(DePara[Categoria],MATCH(TEXT(A110,"0"),DePara[Fornecedor_txt],0)),"(sem categoria)") | D110: =SUMIFS(Base[Montante],Base[Fornecedor],$A110&"",Base[Ano],D$4) | E110: =SUMIFS(Base[Montante],Base[Fornecedor],$A110&"",Base[Ano],E$4) | F110: =SUMIFS(Base[Montante],Base[Fornecedor],$A110&"",Base[Ano],F$4) | G110: =SUMIFS(Base[Montante],Base[Fornecedor],$A110&"",Base[Ano],G$4) | H110: =SUMIFS(Base[Montante],Base[Fornecedor],$A110&"",Base[Ano],H$4) | I110: =SUMIFS(Base[Montante],Base[Fornecedor],$A110&"",Base[Ano],I$4) | J110: =SUMIFS(Base[Montante],Base[Fornecedor],$A110&"",Base[Ano],J$4) | K110: =SUM(D110:J110)
A111: EM000423 | B111: CARLOS GUILHERME RODRIGUES DA SILVA | C111: =IFERROR(INDEX(DePara[Categoria],MATCH(TEXT(A111,"0"),DePara[Fornecedor_txt],0)),"(sem categoria)") | D111: =SUMIFS(Base[Montante],Base[Fornecedor],$A111&"",Base[Ano],D$4) | E111: =SUMIFS(Base[Montante],Base[Fornecedor],$A111&"",Base[Ano],E$4) | F111: =SUMIFS(Base[Montante],Base[Fornecedor],$A111&"",Base[Ano],F$4) | G111: =SUMIFS(Base[Montante],Base[Fornecedor],$A111&"",Base[Ano],G$4) | H111: =SUMIFS(Base[Montante],Base[Fornecedor],$A111&"",Base[Ano],H$4) | I111: =SUMIFS(Base[Montante],Base[Fornecedor],$A111&"",Base[Ano],I$4) | J111: =SUMIFS(Base[Montante],Base[Fornecedor],$A111&"",Base[Ano],J$4) | K111: =SUM(D111:J111)
...

Sheet Detalhe
A1: DRILL-DOWN
A2: Composicao de qualquer saldo
A3: Use as setas de filtro no cabecalho da tabela abaixo para filtrar por Fornecedor, Categoria, Conta ou Ano — filtro nativo do Excel, 100% compativel.
A5: Fornecedor | B5: Nome do fornecedor | C5: Conta | D5: Categoria | E5: Documento | F5: Referencia | G5: Tipo doc | H5: Montante | I5: Data documento | J5: Data vencimento | K5: Texto
A6: IC1000 | B6: NORDEX ENERGY SE & CO KG | C6: 2122100000 | D6: Intercompany | E6: 1008418 | G6: AB | H6: 33462.83 | I6: 45227 | J6: 45227 | K6: Clearing document NORDEX ENERGY SE & CO. KG
A7: IC4420 | B7: NORDEX ENERGY SPAIN S A U | C7: 2122100000 | D7: Intercompany | E7: 1008419 | G7: AB | H7: 93546.45 | I7: 45227 | J7: 45227 | K7: Clearing document NORDEX ENERGY SPAIN S.A.U.
A8: IC4420 | B8: NORDEX ENERGY SPAIN S A U | C8: 2122100000 | D8: Intercompany | E8: 1008419 | G8: AB | H8: 63508.45 | I8: 45227 | J8: 45227 | K8: Clearing document NORDEX ENERGY SPAIN S.A.U.
A9: IC4420 | B9: NORDEX ENERGY SPAIN S A U | C9: 2122100000 | D9: Intercompany | E9: 5000001 | F9: 4025008482 | G9: RE | H9: -181492.25 | I9: 45964 | J9: 45994 | K9: 0846/25
A10: IC4420 | B10: NORDEX ENERGY SPAIN S A U | C10: 2122100000 | D10: Intercompany | E10: 5000003 | F10: 4025008480 | G10: RE | H10: -95934.74 | I10: 45964 | J10: 45994 | K10: 0842/25
A11: IC4420 | B11: NORDEX ENERGY SPAIN S A U | C11: 2122100000 | D11: Intercompany | E11: 5000005 | F11: 4025008261 | G11: RE | H11: -251289.79 | I11: 45957 | J11: 45987 | K11: 0826/25
A12: IC4420 | B12: NORDEX ENERGY SPAIN S A U | C12: 2122100000 | D12: Intercompany | E12: 5000072 | F12: 4025008229 | G12: RE | H12: -3838623.1 | I12: 45954 | J12: 45984 | K12: 0852/25
A13: IC4420 | B13: NORDEX ENERGY SPAIN S A U | C13: 2122100000 | D13: Intercompany | E13: 5000180 | F13: 4025008478 | G13: RE | H13: -1330.48 | I13: 45964 | J13: 45994 | K13: 0844/25
A14: IC4420 | B14: NORDEX ENERGY SPAIN S A U | C14: 2122100000 | D14: Intercompany | E14: 5000181 | F14: 4025008476 | G14: RE | H14: -118914.41 | I14: 45964 | J14: 45994 | K14: 0844/25
A15: IC4420 | B15: NORDEX ENERGY SPAIN S A U | C15: 2122100000 | D15: Intercompany | E15: 5000188 | F15: 4025009533 | G15: RE | H15: -2357 | I15: 46000 | J15: 46030 | K15: 0926/25
A16: IC4420 | B16: NORDEX ENERGY SPAIN S A U | C16: 2122100000 | D16: Intercompany | E16: 5000190 | F16: 4025009569 | G16: RE | H16: -6504.31 | I16: 46001 | J16: 46031 | K16: 0921/25
A17: IC4420 | B17: NORDEX ENERGY SPAIN S A U | C17: 2122100000 | D17: Intercompany | E17: 5000236 | F17: 4025009111 | G17: RE | H17: -826.41 | I17: 45987 | J17: 46017 | K17: 0890/25
A18: IC4420 | B18: NORDEX ENERGY SPAIN S A U | C18: 2122100000 | D18: Intercompany | E18: 5000246 | F18: 4025008477 | G18: RE | H18: -9145.39 | I18: 45964 | J18: 45994 | K18: 0845/25
A19: IC4420 | B19: NORDEX ENERGY SPAIN S A U | C19: 2122100000 | D19: Intercompany | E19: 5000263 | F19: 4025008479 | G19: RE | H19: -193802.69 | I19: 45964 | J19: 45994 | K19: 0843/25
A20: IC4420 | B20: NORDEX ENERGY SPAIN S A U | C20: 2122100000 | D20: Intercompany | E20: 5000284 | F20: 4025009104 | G20: RE | H20: -33691.24 | I20: 45987 | J20: 46017 | K20: 0908/25
... A1502: IC1000 | B1502: NORDEX ENERGY SE & CO KG | C1502: 2122100000 | D1502: Intercompany | E1502: 1100039894 | F1502: 5004195 | G1502: AB | H1502: -2470822.1 | I1502: 45901 | J1502: 45901 | K1502: 4012420609
A1503: IC4420 | B1503: NORDEX ENERGY SPAIN S A U | C1503: 2122100000 | D1503: Intercompany | E1503: 1300002549 | G1503: KZ | H1503: -329597.97 | I1503: 46098 | J1503: 46098 | K1503: Vendor payment NORDEX ENERGY SPAIN S A U
A1504: IC1000 | B1504: NORDEX ENERGY SE & CO KG | C1504: 2122100000 | D1504: Intercompany | E1504: 1300003079 | F1504: CORREÇÃO ADT | G1504: KZ | H1504: 13354.9 | I1504: 45480 | J1504: 45480 | K1504: Vendor payment NORDEX ENERGY SE & CO KG CORREÇÃO A
A1505: ICBRWA | B1505: NORDEX ENERGY BRASIL - COMERCIO E I | C1505: 2114340000 | D1505: Employee-Related Liabilities | E1505: 303357 | F1505: CONCILIAÇÃO IC | G1505: KZ | H1505: 884873.89 | I1505: 45260 | J1505: 45260 | K1505: Vendor payment NORDEX ENERGY BRASIL - COMERCIO E I
A1506: ICBRWA | B1506: NORDEX ENERGY BRASIL - COMERCIO E I | C1506: 2114340000 | D1506: Employee-Related Liabilities | E1506: 5003599 | F1506: F0231012024 | G1506: KR | H1506: -7275.3 | I1506: 45322 | J1506: 45322 | K1506: Fatura do fornecedor NORDEX ENERGY BRASIL - COMERC
A1507: ICBRWA | B1507: NORDEX ENERGY BRASIL - COMERCIO E I | C1507: 2114340000 | D1507: Employee-Related Liabilities | E1507: 5004551 | F1507: F0121022024.2 | G1507: KR | H1507: -63562.56 | I1507: 45328 | J1507: 45387 | K1507: Fatura do fornecedor NORDEX ENERGY BRASIL - COMERC
A1508: EM000093 | B1508: CARLOS ALVES DE AZEVEDO | C1508: 2114340000 | D1508: Nordex Employees | E1508: 5005215 | F1508: 23215 | G1508: KR | H1508: -7617.89 | I1508: 45140 | J1508: 45170 | K1508: Fatura do fornecedor CARLOS ALVES DE AZEVEDO 23215
A1509: EM000093 | B1509: CARLOS ALVES DE AZEVEDO | C1509: 2114340000 | D1509: Nordex Employees | E1509: 5005216 | F1509: 22724 | G1509: KR | H1509: -1524.06 | I1509: 45117 | J1509: 45147 | K1509: Fatura do fornecedor CARLOS ALVES DE AZEVEDO 22724
A1510: ICBRWA | B1510: NORDEX ENERGY BRASIL - COMERCIO E I | C1510: 2114340000 | D1510: Employee-Related Liabilities | E1510: 5011668 | F1510: FE0108072026 | G1510: KR | H1510: -132869 | I1510: 46203 | J1510: 46211 | K1510: ESTORNAR PERIODO FECHADO
A1511: ICBRWA | B1511: NORDEX ENERGY BRASIL - COMERCIO E I | C1511: 2114340000 | D1511: Employee-Related Liabilities | E1511: 5015367 | F1511: CONCILIAÇÃO IC | G1511: KR | H1511: -896715.03 | I1511: 45260 | J1511: 45260 | K1511: Vendor Invoice NORDEX ENERGY BRASIL - COMERCIO E I
A1512: ICBRWA | B1512: NORDEX ENERGY BRASIL - COMERCIO E I | C1512: 2114340000 | D1512: Employee-Related Liabilities | E1512: 5015870 | F1512: F02092026 | G1512: KR | H1512: -56519 | I1512: 46259 | J1512: 46267 | K1512: Folha de pagamento | F02092026
A1513: EM000095 | B1513: DEYMSON ROBSON AMARAL BEZERRA | C1513: 2114340000 | D1513: Nordex Employees | E1513: 5015937 | F1513: 54777 | G1513: KR | H1513: -245.27 | I1513: 46260 | J1513: 46267 | K1513: Vendor Invoice DEYMSON ROBSON AMARAL BEZERRA 54777
A1514: EM000015 | B1514: IZACK DEYVID DIAS VIANA | C1514: 2114340000 | D1514: Nordex Employees | E1514: 5016113 | F1514: FF 07.2026 | G1514: KR | H1514: -1687.3 | I1514: 46262 | J1514: 46267 | K1514: Fatura do fornecedor IZACK DEYVID DIAS VIANA FF 07
A1515: EM000440 | B1515: DIEGO LEON DA SILVA BARACHO | C1515: 2114340000 | D1515: Nordex Employees | E1515: 5016143 | F1515: FF 07.26 - 08.26 | G1515: KR | H1515: -1641.92 | I1515: 46262 | J1515: 46267 | K1515: Fatura do fornecedor DIEGO LEON DA SILVA BARACHO F
... A1544: EM000955 | B1544: JOE MAGNI FREITAS SANTOS | C1544: 2114340000 | D1544: Nordex Employees | E1544: 1100023350 | F1544: ADT VISTO EUA | G1544: AB | H1544: -91.69 | I1544: 45752 | J1544: 45752 | K1544: Partida individual JOE MAGNI FREITAS SANTOS ADT VI
A1545: EM000365 | B1545: LUCIANA OLIVEIRA COSTA LOREDO | C1545: 2114340000 | D1545: Nordex Employees | E1545: 1100026465 | G1545: AB | H1545: -465.92 | I1545: 45763 | J1545: 45775 | K1545: Partida individual LUCIANA OLIVEIRA COSTA LOREDO
A1546: EM003090 | B1546: VALQUIRIA STRAHLR DA SILVA | C1546: 2114340000 | D1546: Nordex Employees | E1546: 1100050063 | F1546: REEMBOLSO VAL | G1546: AB | H1546: -425.2 | I1546: 46013 | J1546: 46013 | K1546: Partida individual VALQUIRIA STRAHLR DA SILVA REEM
A1547: ICBRWA | B1547: NORDEX ENERGY BRASIL - COMERCIO E I | C1547: 2114340000 | D1547: Employee-Related Liabilities | E1547: 1300002970 | G1547: KZ | H1547: 60564.54 | I1547: 46128 | J1547: 46128 | K1547: Pagamento fornecedor NORDEX ENERGY BRASIL - COMERC
A1548: ICBRWA | B1548: NORDEX ENERGY BRASIL - COMERCIO E I | C1548: 2114340000 | D1548: Employee-Related Liabilities | E1548: 1300003059 | G1548: KZ | H1548: -60564.54 | I1548: 46128 | J1548: 46128 | K1548: Pagamento fornecedor NORDEX ENERGY BRASIL - COMERC
A1549: 106430 | B1549: HIDRAULICA CONSTRUCCION Y CONSERVAC SA | C1549: 2112000000 | D1549: Operational Suppliers (Wind Farms) | E1549: 5004251 | F1549: EXD25003BR | G1549: RE | H1549: -190471.73 | I1549: 46001 | J1549: 46001 | K1549: 0932/25
A1550: 106430 | B1550: HIDRAULICA CONSTRUCCION Y CONSERVAC SA | C1550: 2112000000 | D1550: Operational Suppliers (Wind Farms) | E1550: 5004257 | F1550: EXD26004BR | G1550: RE | H1550: -30710.53 | I1550: 46062 | J1550: 46062 | K1550: 0079/26
A1551: 107793 | B1551: RUDLOFF STRONGFORCE STRUCTURAL SYST L.L.C | C1551: 2112000000 | D1551: Operational Suppliers (Wind Farms) | E1551: 5012181 | F1551: 49 | G1551: RE | H1551: -219597.5 | I1551: 46176 | J1551: 46191 | K1551: Fatura - bruto RUDLOFF STRONGFORCE STRUCTURAL SYST
A1552: 100393 | B1552: DISTRIBUIDORA DE PRODUCTOS DE ELEVA | C1552: 2112000000 | D1552: Other Suppliers | E1552: 5015223 | F1552: 32332 | G1552: RE | H1552: -20047.21 | I1552: 45247 | J1552: 45277 | K1552: 0073/24
A1553: 100400 | B1553: TECHNICAL UNIVERSITY OF DENMARK DTU | C1553: 2112000000 | D1553: Other Suppliers | E1553: 5016099 | F1553: 51039130 | G1553: RE | H1553: -10231.28 | I1553: 46253 | J1553: 46283 | K1553: Fatura - bruto TECHNICAL UNIVERSITY OF DENMARK DTU
A1554: 100393 | B1554: DISTRIBUIDORA DE PRODUCTOS DE ELEVA | C1554: 2112000000 | D1554: Other Suppliers | E1554: 5052933 | F1554: 37819 | G1554: RE | H1554: -8116.19 | I1554: 45567 | J1554: 45631 | K1554: 1012/24
A1555: 100908 | B1555: Unimacts Global LLC | C1555: 2112000000 | D1555: Operational Suppliers (Wind Farms) | E1555: 200001452 | F1555: 7889 | G1555: UE | H1555: -31414.42 | I1555: 44648 | J1555: 44648 | K1555: 000001808002
A1556: 100973 | B1556: MUNGI ENGINEERS PVT LTD | C1556: 2112000000 | D1556: Operational Suppliers (Wind Farms) | E1556: 200001652 | F1556: 8068 | G1556: UE | H1556: -62708.75 | I1556: 44687 | J1556: 44687 | K1556: 000001899002
A1557: 101937 | B1557: ALONSO DOLDAN INGENIERIA Y SERVICIO | C1557: 2112000000 | D1557: Operational Suppliers (Wind Farms) | E1557: 200011549 | F1557: 16429 | G1557: UE | H1557: -4737.34 | I1557: 45078 | J1557: 45078 | K1557: 1172599
A1558: 101937 | B1558: ALONSO DOLDAN INGENIERIA Y SERVICIO | C1558: 2112000000 | D1558: Operational Suppliers (Wind Farms) | E1558: 200011551 | F1558: 16430 | G1558: UE | H1558: -4737.34 | I1558: 45078 | J1558: 45078 | K1558: 1172602
A1559: 101937 | B1559: ALONSO DOLDAN INGENIERIA Y SERVICIO | C1559: 2112000000 | D1559: Operational Suppliers (Wind Farms) | E1559: 200011552 | F1559: 16431 | G1559: UE | H1559: -4737.34 | I1559: 45078 | J1559: 45078 | K1559: 1172607
A1560: 101937 | B1560: ALONSO DOLDAN INGENIERIA Y SERVICIO | C1560: 2112000000 | D1560: Operational Suppliers (Wind Farms) | E1560: 200011553 | F1560: 16432 | G1560: UE | H1560: -4060.58 | I1560: 45078 | J1560: 45078 | K1560: 1172612
... A1565: 103702 | B1565: INTERNATIONAL CHAMBER OF COMMERCE | C1565: 2112000000 | D1565: Other Suppliers | E1565: 1100041925 | F1565: DEV ICC | G1565: AB | H1565: -6678.13 | I1565: 45929 | J1565: 45929 | K1565: Partida individual INTERNATIONAL CHAMBER OF COMMER
A1566: 105667 | B1566: TERMOPLAST PLASTIK ENJEKSIYON VE | C1566: 2112000000 | D1566: Operational Suppliers (Wind Farms) | E1566: 1100050075 | G1566: AB | H1566: -678.25 | I1566: 46020 | J1566: 46020 | K1566: Clearing document TERMOPLAST PLASTIK ENJEKSIYON VE
A1567: EM000012 | B1567: EDERSON GOMES XABIER BARBALHO | C1567: 2111000000 | D1567: Nordex Employees | E1567: 209060 | F1567: 28051 | G1567: SA | H1567: -400 | I1567: 45515 | J1567: 45515 | K1567: G/L Account Document EDERSON GOMES XABIER BARBALHO
A1568: 102074 | B1568: TAGUS TEC SERVIÇOS TECNOLOGIA LTDA | C1568: 2111000000 | D1568: Other Suppliers | E1568: 300304 | F1568: 775009 | G1568: KZ | H1568: -906.75 | I1568: 45313 | J1568: 45313 | K1568: Pagamento fornecedor TAGUS TEC SERVIÇOS TECNOLOGIA
A1569: 100406 | B1569: APS COMPONENTES ELETRICOS SA | C1569: 2111000000 | D1569: Other Suppliers | E1569: 5000009 | F1569: 000212369-1 | G1569: RE | H1569: -402.63 | I1569: 45692 | J1569: 45721 | K1569: Fatura - bruto APS COMPONENTES ELETRICOS SA 000212
A1570: 101790 | B1570: FERRAMENTAS GERAIS COM IMP DE FER E | C1570: 2111000000 | D1570: Operational Suppliers (Wind Farms) | E1570: 5000175 | F1570: 001275873-1 | G1570: RE | H1570: 2333.97 | I1570: 46028 | J1570: 46028 | K1570: Fatura - bruto FERRAMENTAS GERAIS COM IMP DE FER E
A1571: 101790 | B1571: FERRAMENTAS GERAIS COM IMP DE FER E | C1571: 2111000000 | D1571: Operational Suppliers (Wind Farms) | E1571: 5000176 | F1571: 001275689-1 | G1571: RE | H1571: 3049.83 | I1571: 46028 | J1571: 46028 | K1571: Fatura - bruto FERRAMENTAS GERAIS COM IMP DE FER E
A1572: 101790 | B1572: FERRAMENTAS GERAIS COM IMP DE FER E | C1572: 2111000000 | D1572: Operational Suppliers (Wind Farms) | E1572: 5000177 | F1572: 001275648-1 | G1572: RE | H1572: 6240.94 | I1572: 46028 | J1572: 46028 | K1572: Fatura - bruto FERRAMENTAS GERAIS COM IMP DE FER E
A1573: 101763 | B1573: MUNICIPIO DE LAGOA DO BARRO DO PIAU | C1573: 2111000000 | D1573: Taxes Payable | E1573: 5000222 | F1573: 404904 | G1573: KR | H1573: -1198.92 | I1573: 44988 | J1573: 44988 | K1573: TFC TOOLS FOR COMPOSITE GMBH
A1574: 101888 | B1574: BANCO SANTANDER BRASIL SA | C1574: 2111000000 | D1574: Corporate Card Payments | E1574: 5000227 | F1574: CC UBER 09.2023 | G1574: KR | H1574: -35170.94 | I1574: 45151 | J1574: 45197 | K1574: Vendor Invoice BANCO SANTANDER BRASIL SA UBER 09/2
A1575: 102087 | B1575: CAIXA ECONOMICA FEDERAL | C1575: 2111000000 | D1575: Social charges | E1575: 5000340 | F1575: FGTS-DISSIDIO 12 | G1575: KR | H1575: -10621.81 | I1575: 45296 | J1575: 45296 | K1575: Fatura do fornecedor CAIXA ECONOMICA FEDERAL FGTS-
A1576: 104122 | B1576: POLIMATEC MECANICA INDUSTRIAL LTDA 30108394000167 | C1576: 2111000000 | D1576: Other Suppliers | E1576: 5000694 | F1576: 000002082-1 | G1576: RE | H1576: -850.48 | I1576: 45838 | J1576: 45874 | K1576: Fatura - bruto POLIMATEC MECANICA INDUSTRIAL LTDA
A1577: 101358 | B1577: MUNICIPIO DE LAJES | C1577: 2111000000 | D1577: Taxes Payable | E1577: 5002496 | F1577: ISS 2022/2025 | G1577: KR | H1577: -219058.53 | I1577: 46052 | J1577: 46052 | K1577: Vendor Invoice MUNICIPIO DE LAJES ISS 2022/2025
A1578: 108019 | B1578: GERSON PEDRO DOS SANTOS OLIVEIRA -M | C1578: 2111000000 | D1578: Other Suppliers | E1578: 5002922 | F1578: 24 | G1578: RE | H1578: -18750 | I1578: 46071 | J1578: 46071 | K1578: Fatura - bruto GERSON PEDRO DOS SANTOS OLIVEIRA -M
... A3790: 101685 | B3790: POLIMIX CONCRETO LTDA | C3790: 2111000000 | D3790: Other Suppliers | E3790: 200036702 | F3790: 20850 | G3790: UE | H3790: -13867.51 | I3790: 44477 | J3790: 44477 | K3790: 000355884010
A3791: EM000324 | B3791: LUIZ EDUARDO PEREIRA DA SILVA | C3791: 2111000000 | D3791: Nordex Employees | E3791: 1100001158 | G3791: AB | H3791: -157.47 | I3791: 45730 | J3791: 45730 | K3791: Clearing document LUIZ EDUARDO PEREIRA DA SILVA
A3792: EM000105 | B3792: THIAGO CARVALHO | C3792: 2111000000 | D3792: Nordex Employees | E3792: 1100001380 | F3792: PLANO 30396 | G3792: AB | H3792: -390 | I3792: 45451 | J3792: 45451 | K3792: Partida individual THIAGO CARVALHO PLANO 30396
A3793: EM000041 | B3793: FLAVIO BELLOLI | C3793: 2111000000 | D3793: Nordex Employees | E3793: 1100001915 | G3793: AB | H3793: -59.14 | I3793: 45459 | J3793: 45459 | K3793: Clearing document FLAVIO BELLOLI
A3794: EM000271 | B3794: PABLO SUEIRAS BLANCO | C3794: 2111000000 | D3794: Nordex Employees | E3794: 1100002430 | F3794: 29608.1 | G3794: AB | H3794: -52 | I3794: 45507 | J3794: 45507 | K3794: Partida individual PABLO SUEIRAS BLANCO 29608.1
A3795: 101604 | B3795: PREFEITURA SANTA VITORIA DO PALMAR | C3795: 2111000000 | D3795: Taxes Payable | E3795: 1100003660 | G3795: AB | H3795: -121392.76 | I3795: 46053 | J3795: 46053 | K3795: Clearing document PREFEITURA SANTA VITORIA DO PALM
A3796: 100992 | B3796: P W GESTAO DE SAUDE E SEGURANÇA LTD | C3796: 2111000000 | D3796: Other Suppliers | E3796: 1100020540 | F3796: 18 | G3796: AB | H3796: 11611.76 | I3796: 46242 | J3796: 46242 | K3796: Saldo a ser descontado da NF de 09.26 ( NF101667)
A3797: 105984 | B3797: TRADEWORKS SERVICOS DE COMERCIO EXT 04955748000107 | C3797: 2111000000 | D3797: Customs Brokerage – Overall | E3797: 1100022427 | F3797: 0413/26 | G3797: AB | H3797: 196.55 | I3797: 46265 | J3797: 46265 | K3797: Partida individual TRADEWORKS SERVICOS DE COMERCIO
A3798: 105984 | B3798: TRADEWORKS SERVICOS DE COMERCIO EXT 04955748000107 | C3798: 2111000000 | D3798: Customs Brokerage – Overall | E3798: 1100022428 | F3798: 0419/26 | G3798: AB | H3798: 145754.77 | I3798: 46265 | J3798: 46265 | K3798: Partida individual TRADEWORKS SERVICOS DE COMERCIO
A3799: 101420 | B3799: MEDEIROS GALVAO SOLUÇÕES LTDA | C3799: 2111000000 | D3799: Customs Brokerage – Overall | E3799: 1100032821 | F3799: 019859 | G3799: AB | H3799: 32240.11 | I3799: 45836 | J3799: 45836 | K3799: Partida individual MEDEIROS GALVAO SOLUÇÕES LTDA 0
A3800: 101632 | B3800: BVQI DO BRASIL SOCIEDADE CERTIFICAD | C3800: 2111000000 | D3800: Other Suppliers | E3800: 1100034256 | F3800: 0113389 | G3800: AB | H3800: -1553.7 | I3800: 45861 | J3800: 45861 | K3800: Partida individual BVQI DO BRASIL SOCIEDADE CERTIF
A3801: 101632 | B3801: BVQI DO BRASIL SOCIEDADE CERTIFICAD | C3801: 2111000000 | D3801: Other Suppliers | E3801: 1100034257 | F3801: 0107788 | G3801: AB | H3801: -4229.85 | I3801: 45861 | J3801: 45861 | K3801: Partida individual BVQI DO BRASIL SOCIEDADE CERTIF
A3802: 101632 | B3802: BVQI DO BRASIL SOCIEDADE CERTIFICAD | C3802: 2111000000 | D3802: Other Suppliers | E3802: 1100034258 | F3802: 0112856 | G3802: AB | H3802: -4998.2 | I3802: 45861 | J3802: 45861 | K3802: Partida individual BVQI DO BRASIL SOCIEDADE CERTIF
A3803: 101071 | B3803: CUSTOM COMERCIO INTERNACIONAL LTDA | C3803: 2111000000 | D3803: Customs Brokerage – Overall | E3803: 1100036425 | F3803: 4023002662 | G3803: AB | H3803: 155470.21 | I3803: 45871 | J3803: 45871 | K3803: CUSTOM A DEVOLVER
A3804: 101071 | B3804: CUSTOM COMERCIO INTERNACIONAL LTDA | C3804: 2111000000 | D3804: Customs Brokerage – Overall | E3804: 1100036520 | F3804: OEM0209 | G3804: AB | H3804: 119283.6 | I3804: 45871 | J3804: 45871 | K3804: CUSTOM A DEVOLVER
A3805: 101071 | B3805: CUSTOM COMERCIO INTERNACIONAL LTDA | C3805: 2111000000 | D3805: Customs Brokerage – Overall | E3805: 1100036537 | F3805: 4012318402 | G3805: AB | H3805: 12987.43 | I3805: 45871 | J3805: 45871 | K3805: CUSTOM A DEVOLVER
A3806: 101071 | B3806: CUSTOM COMERCIO INTERNACIONAL LTDA | C3806: 2111000000 | D3806: Customs Brokerage – Overall | E3806: 1100036543 | F3806: CAJUII012T | G3806: AB | H3806: 52018.67 | I3806: 45871 | J3806: 45871 | K3806: CUSTOM A DEVOLVER
A3807: 101071 | B3807: CUSTOM COMERCIO INTERNACIONAL LTDA | C3807: 2111000000 | D3807: Customs Brokerage – Overall | E3807: 1100036590 | F3807: LDVV006A1 | G3807: AB | H3807: 609264 | I3807: 45871 | J3807: 45871 | K3807: CUSTOM A DEVOLVER
... A3862: 101071 | B3862: CUSTOM COMERCIO INTERNACIONAL LTDA | C3862: 2111000000 | D3862: Customs Brokerage – Overall | E3862: 1100038597 | F3862: 4023002702 | G3862: AB | H3862: 2135.3 | I3862: 45871 | J3862: 45871 | K3862: CUSTOM A DEVOLVER
A3863: 101848 | B3863: KLUBER LUBRICATION LUBRIF ESPECIAIS | C3863: 2111000000 | D3863: Other Suppliers | E3863: 1100041754 | G3863: AB | H3863: -132699.65 | I3863: 45919 | J3863: 45919 | K3863: nota de devolução
A3864: 101052 | B3864: MEGALIFT LOCACAO E TRANSP INTERM LT | C3864: 2111000000 | D3864: Other Suppliers | E3864: 1100041922 | F3864: 125001 | G3864: AB | H3864: -111.65 | I3864: 45929 | J3864: 45996 | K3864: 125001
A3865: 101485 | B3865: RUDLOFF SISTEMA DE PROTENSAO LTDA | C3865: 2111000000 | D3865: Operational Suppliers (Wind Farms) | E3865: 1100041923 | F3865: 1914 | G3865: AB | H3865: -763.75 | I3865: 45929 | J3865: 45966 | K3865: Partida individual RUDLOFF SISTEMA DE PROTENSAO LT
A3866: 101053 | B3866: NLA LATINOAMERICANA LOGISTICA LTDA | C3866: 2111000000 | D3866: Operational Suppliers (Wind Farms) | E3866: 1100041924 | F3866: 2658000 | G3866: AB | H3866: -1415.61 | I3866: 45929 | J3866: 45996 | K3866: Partida individual NLA LATINOAMERICANA LOGISTICA L
A3867: 101432 | B3867: CONSTRUTORA MD EIRELI | C3867: 2111000000 | D3867: Operational Suppliers (Wind Farms) | E3867: 1100041926 | F3867: 26 E 25 | G3867: AB | H3867: -38721.58 | I3867: 45929 | J3867: 45966 | K3867: NAO PAGAR
A3868: 102143 | B3868: FARDIER LOGISTICA ESP EM CARGAS EPE | C3868: 2111000000 | D3868: Operational Suppliers (Wind Farms) | E3868: 1100041927 | F3868: FW FARDIER | G3868: AB | H3868: -650000 | I3868: 45929 | J3868: 45996 | K3868: Partida individual FARDIER LOGISTICA ESP EM CARGAS
A3869: 102087 | B3869: CAIXA ECONOMICA FEDERAL | C3869: 2111000000 | D3869: Social charges | E3869: 1100050074 | F3869: FGTS DEVOLVIDO | G3869: AB | H3869: -1409.07 | I3869: 45993 | J3869: 45993 | K3869: Partida individual CAIXA ECONOMICA FEDERAL FGTS DE
A3870: 101918 | B3870: MUNICIPIO DE AREIA BRANCA | C3870: 2111000000 | D3870: Taxes Payable | E3870: 1300000108 | G3870: KZ | H3870: 26554.9 | I3870: 46029 | J3870: 46029 | K3870: Pagamento fornecedor MUNICIPIO DE AREIA BRANCA
A3871: 101918 | B3871: MUNICIPIO DE AREIA BRANCA | C3871: 2111000000 | D3871: Taxes Payable | E3871: 1300000109 | G3871: KZ | H3871: 143975.21 | I3871: 46029 | J3871: 46029 | K3871: Pagamento fornecedor MUNICIPIO DE AREIA BRANCA
A3872: 101918 | B3872: MUNICIPIO DE AREIA BRANCA | C3872: 2111000000 | D3872: Taxes Payable | E3872: 1300000122 | G3872: KZ | H3872: -26554.9 | I3872: 46029 | J3872: 46029 | K3872: Pagamento fornecedor MUNICIPIO DE AREIA BRANCA
A3873: 101918 | B3873: MUNICIPIO DE AREIA BRANCA | C3873: 2111000000 | D3873: Taxes Payable | E3873: 1300000123 | G3873: KZ | H3873: -143975.21 | I3873: 46029 | J3873: 46029 | K3873: Pagamento fornecedor MUNICIPIO DE AREIA BRANCA
A3874: 102209 | B3874: ENEL GREEN POWER V DE SANTA ANGELA 29711059000250 | C3874: 2111000000 | D3874: Other Suppliers | E3874: 1300002066 | G3874: DZ | H3874: -5470.92 | I3874: 45741 | J3874: 45741 | K3874: INSS NÃO RETIDO NF 2944 DEVOLVER AO CLIENTE
A3875: 105589 | B3875: ENEL GREEN POWER VENTOS DE SAO ROQU 36051515000249 | C3875: 2111000000 | D3875: Facilities | E3875: 1300007749 | G3875: DZ | H3875: -4923.03 | I3875: 45975 | J3875: 45975 | K3875: Customer Payment ENEL GREEN POWER VENTOS DE SAO RO
A3876: 102080 | B3876: RECEITA FEDERAL DO BRASIL | C3876: 2111000000 | D3876: Customs Brokerage – Overall | E3876: 1400000058 | F3876: 0000229558 | G3876: JP | H3876: 0 | I3876: 46009 | K3876: Journal Posting OSGT 0000229558
A3877: 102080 | B3877: RECEITA FEDERAL DO BRASIL | C3877: 2111000000 | D3877: Customs Brokerage – Overall | E3877: 1400000080 | F3877: 0000200000 | G3877: JP | H3877: 0 | I3877: 46028 | K3877: Journal Posting OSGT 0000200000
A3878: 102080 | B3878: RECEITA FEDERAL DO BRASIL | C3878: 2111000000 | D3878: Customs Brokerage – Overall | E3878: 1400000111 | F3878: 0000230647 | G3878: JP | H3878: 0 | I3878: 46014 | K3878: Journal Posting OSGT 0000230647
A3879: 102080 | B3879: RECEITA FEDERAL DO BRASIL | C3879: 2111000000 | D3879: Customs Brokerage – Overall | E3879: 1400000130 | F3879: 0000230724 | G3879: JP | H3879: 0 | I3879: 46006 | K3879: Journal Posting OSGT 0000230724
...

Sheet Cadastro Fornecedores
A1: CADASTRO DE FORNECEDORES
A2: Lista de fornecedores com saldo em aberto na Base. Filtre a coluna Categoria para ver os sem classificacao.
A4: Fornecedor | B4: Nome do fornecedor | C4: Categoria | D4: Itens | E4: Valor
A5: IC1000 | B5: NORDEX ENERGY SE & CO KG | C5: =IFERROR(INDEX(DePara[Categoria],MATCH(TEXT(A5,"0"),DePara[Fornecedor_txt],0)),"(sem categoria)") | D5: =COUNTIF(Base[Fornecedor],A5&"") | E5: =SUMIF(Base[Fornecedor],A5&"",Base[Montante])
A6: IC4420 | B6: NORDEX ENERGY SPAIN S A U | C6: =IFERROR(INDEX(DePara[Categoria],MATCH(TEXT(A6,"0"),DePara[Fornecedor_txt],0)),"(sem categoria)") | D6: =COUNTIF(Base[Fornecedor],A6&"") | E6: =SUMIF(Base[Fornecedor],A6&"",Base[Montante])
A7: IC5000 | B7: NORDEX SE | C7: =IFERROR(INDEX(DePara[Categoria],MATCH(TEXT(A7,"0"),DePara[Fornecedor_txt],0)),"(sem categoria)") | D7: =COUNTIF(Base[Fornecedor],A7&"") | E7: =SUMIF(Base[Fornecedor],A7&"",Base[Montante])
A8: IC4600 | B8: NORDEX USA INC 4650 | C8: =IFERROR(INDEX(DePara[Categoria],MATCH(TEXT(A8,"0"),DePara[Fornecedor_txt],0)),"(sem categoria)") | D8: =COUNTIF(Base[Fornecedor],A8&"") | E8: =SUMIF(Base[Fornecedor],A8&"",Base[Montante])
A9: IC4665 | B9: NORDEX WINDPOWER PERU SA | C9: =IFERROR(INDEX(DePara[Categoria],MATCH(TEXT(A9,"0"),DePara[Fornecedor_txt],0)),"(sem categoria)") | D9: =COUNTIF(Base[Fornecedor],A9&"") | E9: =SUMIF(Base[Fornecedor],A9&"",Base[Montante])
A10: IC4441 | B10: Nordex Concrete Towers, S.L. | C10: =IFERROR(INDEX(DePara[Categoria],MATCH(TEXT(A10,"0"),DePara[Fornecedor_txt],0)),"(sem categoria)") | D10: =COUNTIF(Base[Fornecedor],A10&"") | E10: =SUMIF(Base[Fornecedor],A10&"",Base[Montante])
A11: IC4680 | B11: NORDEX ENERGY MEXICO S DE RL DE CV | C11: =IFERROR(INDEX(DePara[Categoria],MATCH(TEXT(A11,"0"),DePara[Fornecedor_txt],0)),"(sem categoria)") | D11: =COUNTIF(Base[Fornecedor],A11&"") | E11: =SUMIF(Base[Fornecedor],A11&"",Base[Montante])
A12: IC4670 | B12: NORDEX ENERGY CHILE SA | C12: =IFERROR(INDEX(DePara[Categoria],MATCH(TEXT(A12,"0"),DePara[Fornecedor_txt],0)),"(sem categoria)") | D12: =COUNTIF(Base[Fornecedor],A12&"") | E12: =SUMIF(Base[Fornecedor],A12&"",Base[Montante])
A13: ICBRWA | B13: NORDEX ENERGY BRASIL - COMERCIO E I | C13: =IFERROR(INDEX(DePara[Categoria],MATCH(TEXT(A13,"0"),DePara[Fornecedor_txt],0)),"(sem categoria)") | D13: =COUNTIF(Base[Fornecedor],A13&"") | E13: =SUMIF(Base[Fornecedor],A13&"",Base[Montante])
A14: EM000093 | B14: CARLOS ALVES DE AZEVEDO | C14: =IFERROR(INDEX(DePara[Categoria],MATCH(TEXT(A14,"0"),DePara[Fornecedor_txt],0)),"(sem categoria)") | D14: =COUNTIF(Base[Fornecedor],A14&"") | E14: =SUMIF(Base[Fornecedor],A14&"",Base[Montante])
A15: EM000095 | B15: DEYMSON ROBSON AMARAL BEZERRA | C15: =IFERROR(INDEX(DePara[Categoria],MATCH(TEXT(A15,"0"),DePara[Fornecedor_txt],0)),"(sem categoria)") | D15: =COUNTIF(Base[Fornecedor],A15&"") | E15: =SUMIF(Base[Fornecedor],A15&"",Base[Montante])
A16: EM000015 | B16: IZACK DEYVID DIAS VIANA | C16: =IFERROR(INDEX(DePara[Categoria],MATCH(TEXT(A16,"0"),DePara[Fornecedor_txt],0)),"(sem categoria)") | D16: =COUNTIF(Base[Fornecedor],A16&"") | E16: =SUMIF(Base[Fornecedor],A16&"",Base[Montante])
... A42: EM003090 | B42: VALQUIRIA STRAHLR DA SILVA | C42: =IFERROR(INDEX(DePara[Categoria],MATCH(TEXT(A42,"0"),DePara[Fornecedor_txt],0)),"(sem categoria)") | D42: =COUNTIF(Base[Fornecedor],A42&"") | E42: =SUMIF(Base[Fornecedor],A42&"",Base[Montante])
A43: 106430 | B43: HIDRAULICA CONSTRUCCION Y CONSERVAC SA | C43: =IFERROR(INDEX(DePara[Categoria],MATCH(TEXT(A43,"0"),DePara[Fornecedor_txt],0)),"(sem categoria)") | D43: =COUNTIF(Base[Fornecedor],A43&"") | E43: =SUMIF(Base[Fornecedor],A43&"",Base[Montante])
A44: 107793 | B44: RUDLOFF STRONGFORCE STRUCTURAL SYST L.L.C | C44: =IFERROR(INDEX(DePara[Categoria],MATCH(TEXT(A44,"0"),DePara[Fornecedor_txt],0)),"(sem categoria)") | D44: =COUNTIF(Base[Fornecedor],A44&"") | E44: =SUMIF(Base[Fornecedor],A44&"",Base[Montante])
A45: 100393 | B45: DISTRIBUIDORA DE PRODUCTOS DE ELEVA | C45: =IFERROR(INDEX(DePara[Categoria],MATCH(TEXT(A45,"0"),DePara[Fornecedor_txt],0)),"(sem categoria)") | D45: =COUNTIF(Base[Fornecedor],A45&"") | E45: =SUMIF(Base[Fornecedor],A45&"",Base[Montante])
A46: 100400 | B46: TECHNICAL UNIVERSITY OF DENMARK DTU | C46: =IFERROR(INDEX(DePara[Categoria],MATCH(TEXT(A46,"0"),DePara[Fornecedor_txt],0)),"(sem categoria)") | D46: =COUNTIF(Base[Fornecedor],A46&"") | E46: =SUMIF(Base[Fornecedor],A46&"",Base[Montante])
A47: 100908 | B47: Unimacts Global LLC | C47: =IFERROR(INDEX(DePara[Categoria],MATCH(TEXT(A47,"0"),DePara[Fornecedor_txt],0)),"(sem categoria)") | D47: =COUNTIF(Base[Fornecedor],A47&"") | E47: =SUMIF(Base[Fornecedor],A47&"",Base[Montante])
A48: 100973 | B48: MUNGI ENGINEERS PVT LTD | C48: =IFERROR(INDEX(DePara[Categoria],MATCH(TEXT(A48,"0"),DePara[Fornecedor_txt],0)),"(sem categoria)") | D48: =COUNTIF(Base[Fornecedor],A48&"") | E48: =SUMIF(Base[Fornecedor],A48&"",Base[Montante])
A49: 101937 | B49: ALONSO DOLDAN INGENIERIA Y SERVICIO | C49: =IFERROR(INDEX(DePara[Categoria],MATCH(TEXT(A49,"0"),DePara[Fornecedor_txt],0)),"(sem categoria)") | D49: =COUNTIF(Base[Fornecedor],A49&"") | E49: =SUMIF(Base[Fornecedor],A49&"",Base[Montante])
A50: 101271 | B50: UNYVERSE PTE LTD | C50: =IFERROR(INDEX(DePara[Categoria],MATCH(TEXT(A50,"0"),DePara[Fornecedor_txt],0)),"(sem categoria)") | D50: =COUNTIF(Base[Fornecedor],A50&"") | E50: =SUMIF(Base[Fornecedor],A50&"",Base[Montante])
A51: 103702 | B51: INTERNATIONAL CHAMBER OF COMMERCE | C51: =IFERROR(INDEX(DePara[Categoria],MATCH(TEXT(A51,"0"),DePara[Fornecedor_txt],0)),"(sem categoria)") | D51: =COUNTIF(Base[Fornecedor],A51&"") | E51: =SUMIF(Base[Fornecedor],A51&"",Base[Montante])
A52: 105667 | B52: TERMOPLAST PLASTIK ENJEKSIYON VE | C52: =IFERROR(INDEX(DePara[Categoria],MATCH(TEXT(A52,"0"),DePara[Fornecedor_txt],0)),"(sem categoria)") | D52: =COUNTIF(Base[Fornecedor],A52&"") | E52: =SUMIF(Base[Fornecedor],A52&"",Base[Montante])
A53: EM000012 | B53: EDERSON GOMES XABIER BARBALHO | C53: =IFERROR(INDEX(DePara[Categoria],MATCH(TEXT(A53,"0"),DePara[Fornecedor_txt],0)),"(sem categoria)") | D53: =COUNTIF(Base[Fornecedor],A53&"") | E53: =SUMIF(Base[Fornecedor],A53&"",Base[Montante])
A54: 102074 | B54: TAGUS TEC SERVIÇOS TECNOLOGIA LTDA | C54: =IFERROR(INDEX(DePara[Categoria],MATCH(TEXT(A54,"0"),DePara[Fornecedor_txt],0)),"(sem categoria)") | D54: =COUNTIF(Base[Fornecedor],A54&"") | E54: =SUMIF(Base[Fornecedor],A54&"",Base[Montante])
A55: 100406 | B55: APS COMPONENTES ELETRICOS SA | C55: =IFERROR(INDEX(DePara[Categoria],MATCH(TEXT(A55,"0"),DePara[Fornecedor_txt],0)),"(sem categoria)") | D55: =COUNTIF(Base[Fornecedor],A55&"") | E55: =SUMIF(Base[Fornecedor],A55&"",Base[Montante])
A56: 101790 | B56: FERRAMENTAS GERAIS COM IMP DE FER E | C56: =IFERROR(INDEX(DePara[Categoria],MATCH(TEXT(A56,"0"),DePara[Fornecedor_txt],0)),"(sem categoria)") | D56: =COUNTIF(Base[Fornecedor],A56&"") | E56: =SUMIF(Base[Fornecedor],A56&"",Base[Montante])
A57: 101763 | B57: MUNICIPIO DE LAGOA DO BARRO DO PIAU | C57: =IFERROR(INDEX(DePara[Categoria],MATCH(TEXT(A57,"0"),DePara[Fornecedor_txt],0)),"(sem categoria)") | D57: =COUNTIF(Base[Fornecedor],A57&"") | E57: =SUMIF(Base[Fornecedor],A57&"",Base[Montante])
A58: 101888 | B58: BANCO SANTANDER BRASIL SA | C58: =IFERROR(INDEX(DePara[Categoria],MATCH(TEXT(A58,"0"),DePara[Fornecedor_txt],0)),"(sem categoria)") | D58: =COUNTIF(Base[Fornecedor],A58&"") | E58: =SUMIF(Base[Fornecedor],A58&"",Base[Montante])
A59: 102087 | B59: CAIXA ECONOMICA FEDERAL | C59: =IFERROR(INDEX(DePara[Categoria],MATCH(TEXT(A59,"0"),DePara[Fornecedor_txt],0)),"(sem categoria)") | D59: =COUNTIF(Base[Fornecedor],A59&"") | E59: =SUMIF(Base[Fornecedor],A59&"",Base[Montante])
A60: 104122 | B60: POLIMATEC MECANICA INDUSTRIAL LTDA 30108394000167 | C60: =IFERROR(INDEX(DePara[Categoria],MATCH(TEXT(A60,"0"),DePara[Fornecedor_txt],0)),"(sem categoria)") | D60: =COUNTIF(Base[Fornecedor],A60&"") | E60: =SUMIF(Base[Fornecedor],A60&"",Base[Montante])
A61: 101358 | B61: MUNICIPIO DE LAJES | C61: =IFERROR(INDEX(DePara[Categoria],MATCH(TEXT(A61,"0"),DePara[Fornecedor_txt],0)),"(sem categoria)") | D61: =COUNTIF(Base[Fornecedor],A61&"") | E61: =SUMIF(Base[Fornecedor],A61&"",Base[Montante])
A62: 108019 | B62: GERSON PEDRO DOS SANTOS OLIVEIRA -M | C62: =IFERROR(INDEX(DePara[Categoria],MATCH(TEXT(A62,"0"),DePara[Fornecedor_txt],0)),"(sem categoria)") | D62: =COUNTIF(Base[Fornecedor],A62&"") | E62: =SUMIF(Base[Fornecedor],A62&"",Base[Montante])
A63: 108017 | B63: CARLOS DIAS DOS SANTOS | C63: =IFERROR(INDEX(DePara[Categoria],MATCH(TEXT(A63,"0"),DePara[Fornecedor_txt],0)),"(sem categoria)") | D63: =COUNTIF(Base[Fornecedor],A63&"") | E63: =SUMIF(Base[Fornecedor],A63&"",Base[Montante])
A64: 107632 | B64: PMI SOUTH AMERICA CONSUMER GOODS LT | C64: =IFERROR(INDEX(DePara[Categoria],MATCH(TEXT(A64,"0"),DePara[Fornecedor_txt],0)),"(sem categoria)") | D64: =COUNTIF(Base[Fornecedor],A64&"") | E64: =SUMIF(Base[Fornecedor],A64&"",Base[Montante])
A65: 100759 | B65: MUNICIPIO DE UIBAI | C65: =IFERROR(INDEX(DePara[Categoria],MATCH(TEXT(A65,"0"),DePara[Fornecedor_txt],0)),"(sem categoria)") | D65: =COUNTIF(Base[Fornecedor],A65&"") | E65: =SUMIF(Base[Fornecedor],A65&"",Base[Montante])
... A280: 101948 | B280: INSTITUTO BRAS DO MEIO AMBIEN E DOS | C280: =IFERROR(INDEX(DePara[Categoria],MATCH(TEXT(A280,"0"),DePara[Fornecedor_txt],0)),"(sem categoria)") | D280: =COUNTIF(Base[Fornecedor],A280&"") | E280: =SUMIF(Base[Fornecedor],A280&"",Base[Montante])
A281: EM000394 | B281: WAGNER DELLA FLORA GROSS | C281: =IFERROR(INDEX(DePara[Categoria],MATCH(TEXT(A281,"0"),DePara[Fornecedor_txt],0)),"(sem categoria)") | D281: =COUNTIF(Base[Fornecedor],A281&"") | E281: =SUMIF(Base[Fornecedor],A281&"",Base[Montante])
A282: 104134 | B282: B&M LOGISTICA INTERNACIONAL LTDA 07720307000106 | C282: =IFERROR(INDEX(DePara[Categoria],MATCH(TEXT(A282,"0"),DePara[Fornecedor_txt],0)),"(sem categoria)") | D282: =COUNTIF(Base[Fornecedor],A282&"") | E282: =SUMIF(Base[Fornecedor],A282&"",Base[Montante])
A283: 103904 | B283: EDSON MELO | C283: =IFERROR(INDEX(DePara[Categoria],MATCH(TEXT(A283,"0"),DePara[Fornecedor_txt],0)),"(sem categoria)") | D283: =COUNTIF(Base[Fornecedor],A283&"") | E283: =SUMIF(Base[Fornecedor],A283&"",Base[Montante])
A284: 102077 | B284: SINDICATO IND MET MEC E MAT EL NO E | C284: =IFERROR(INDEX(DePara[Categoria],MATCH(TEXT(A284,"0"),DePara[Fornecedor_txt],0)),"(sem categoria)") | D284: =COUNTIF(Base[Fornecedor],A284&"") | E284: =SUMIF(Base[Fornecedor],A284&"",Base[Montante])
A285: 101855 | B285: GERDAU ACOS LONGOS SA | C285: =IFERROR(INDEX(DePara[Categoria],MATCH(TEXT(A285,"0"),DePara[Fornecedor_txt],0)),"(sem categoria)") | D285: =COUNTIF(Base[Fornecedor],A285&"") | E285: =SUMIF(Base[Fornecedor],A285&"",Base[Montante])
A286: 100555 | B286: MAC CONSULTORIA E LOGISTICA LTDA | C286: =IFERROR(INDEX(DePara[Categoria],MATCH(TEXT(A286,"0"),DePara[Fornecedor_txt],0)),"(sem categoria)") | D286: =COUNTIF(Base[Fornecedor],A286&"") | E286: =SUMIF(Base[Fornecedor],A286&"",Base[Montante])
A287: 103744 | B287: J G SERVICOS DE HOSPEDAGEM LTDA | C287: =IFERROR(INDEX(DePara[Categoria],MATCH(TEXT(A287,"0"),DePara[Fornecedor_txt],0)),"(sem categoria)") | D287: =COUNTIF(Base[Fornecedor],A287&"") | E287: =SUMIF(Base[Fornecedor],A287&"",Base[Montante])
A288: 101813 | B288: TECON RIO GRANDE SA | C288: =IFERROR(INDEX(DePara[Categoria],MATCH(TEXT(A288,"0"),DePara[Fornecedor_txt],0)),"(sem categoria)") | D288: =COUNTIF(Base[Fornecedor],A288&"") | E288: =SUMIF(Base[Fornecedor],A288&"",Base[Montante])
A289: 102485 | B289: SUATA SERVICO UNIFICADO DE ARMAZENA | C289: =IFERROR(INDEX(DePara[Categoria],MATCH(TEXT(A289,"0"),DePara[Fornecedor_txt],0)),"(sem categoria)") | D289: =COUNTIF(Base[Fornecedor],A289&"") | E289: =SUMIF(Base[Fornecedor],A289&"",Base[Montante])
A290: 100920 | B290: DSV SOLUTIONS BRASIL SERVICOS DE LO | C290: =IFERROR(INDEX(DePara[Categoria],MATCH(TEXT(A290,"0"),DePara[Fornecedor_txt],0)),"(sem categoria)") | D290: =COUNTIF(Base[Fornecedor],A290&"") | E290: =SUMIF(Base[Fornecedor],A290&"",Base[Montante])
A291: 102030 | B291: TECON SALVADOR SA | C291: =IFERROR(INDEX(DePara[Categoria],MATCH(TEXT(A291,"0"),DePara[Fornecedor_txt],0)),"(sem categoria)") | D291: =COUNTIF(Base[Fornecedor],A291&"") | E291: =SUMIF(Base[Fornecedor],A291&"",Base[Montante])
A292: 101969 | B292: SECRETARIA DE ESTADO DA FAZENDA RN | C292: =IFERROR(INDEX(DePara[Categoria],MATCH(TEXT(A292,"0"),DePara[Fornecedor_txt],0)),"(sem categoria)") | D292: =COUNTIF(Base[Fornecedor],A292&"") | E292: =SUMIF(Base[Fornecedor],A292&"",Base[Montante])
A293: 101858 | B293: PAULO FRANCO SOCIEDADE DE ADVOGADOS | C293: =IFERROR(INDEX(DePara[Categoria],MATCH(TEXT(A293,"0"),DePara[Fornecedor_txt],0)),"(sem categoria)") | D293: =COUNTIF(Base[Fornecedor],A293&"") | E293: =SUMIF(Base[Fornecedor],A293&"",Base[Montante])
... A343: 101685 | B343: POLIMIX CONCRETO LTDA | C343: =IFERROR(INDEX(DePara[Categoria],MATCH(TEXT(A343,"0"),DePara[Fornecedor_txt],0)),"(sem categoria)") | D343: =COUNTIF(Base[Fornecedor],A343&"") | E343: =SUMIF(Base[Fornecedor],A343&"",Base[Montante])
A344: EM000324 | B344: LUIZ EDUARDO PEREIRA DA SILVA | C344: =IFERROR(INDEX(DePara[Categoria],MATCH(TEXT(A344,"0"),DePara[Fornecedor_txt],0)),"(sem categoria)") | D344: =COUNTIF(Base[Fornecedor],A344&"") | E344: =SUMIF(Base[Fornecedor],A344&"",Base[Montante])
A345: EM000105 | B345: THIAGO CARVALHO | C345: =IFERROR(INDEX(DePara[Categoria],MATCH(TEXT(A345,"0"),DePara[Fornecedor_txt],0)),"(sem categoria)") | D345: =COUNTIF(Base[Fornecedor],A345&"") | E345: =SUMIF(Base[Fornecedor],A345&"",Base[Montante])
A346: EM000041 | B346: FLAVIO BELLOLI | C346: =IFERROR(INDEX(DePara[Categoria],MATCH(TEXT(A346,"0"),DePara[Fornecedor_txt],0)),"(sem categoria)") | D346: =COUNTIF(Base[Fornecedor],A346&"") | E346: =SUMIF(Base[Fornecedor],A346&"",Base[Montante])
A347: EM000271 | B347: PABLO SUEIRAS BLANCO | C347: =IFERROR(INDEX(DePara[Categoria],MATCH(TEXT(A347,"0"),DePara[Fornecedor_txt],0)),"(sem categoria)") | D347: =COUNTIF(Base[Fornecedor],A347&"") | E347: =SUMIF(Base[Fornecedor],A347&"",Base[Montante])
A348: 101604 | B348: PREFEITURA SANTA VITORIA DO PALMAR | C348: =IFERROR(INDEX(DePara[Categoria],MATCH(TEXT(A348,"0"),DePara[Fornecedor_txt],0)),"(sem categoria)") | D348: =COUNTIF(Base[Fornecedor],A348&"") | E348: =SUMIF(Base[Fornecedor],A348&"",Base[Montante])
A349: 100992 | B349: P W GESTAO DE SAUDE E SEGURANÇA LTD | C349: =IFERROR(INDEX(DePara[Categoria],MATCH(TEXT(A349,"0"),DePara[Fornecedor_txt],0)),"(sem categoria)") | D349: =COUNTIF(Base[Fornecedor],A349&"") | E349: =SUMIF(Base[Fornecedor],A349&"",Base[Montante])
A350: 101632 | B350: BVQI DO BRASIL SOCIEDADE CERTIFICAD | C350: =IFERROR(INDEX(DePara[Categoria],MATCH(TEXT(A350,"0"),DePara[Fornecedor_txt],0)),"(sem categoria)") | D350: =COUNTIF(Base[Fornecedor],A350&"") | E350: =SUMIF(Base[Fornecedor],A350&"",Base[Montante])
A351: 101071 | B351: CUSTOM COMERCIO INTERNACIONAL LTDA | C351: =IFERROR(INDEX(DePara[Categoria],MATCH(TEXT(A351,"0"),DePara[Fornecedor_txt],0)),"(sem categoria)") | D351: =COUNTIF(Base[Fornecedor],A351&"") | E351: =SUMIF(Base[Fornecedor],A351&"",Base[Montante])
A352: 101052 | B352: MEGALIFT LOCACAO E TRANSP INTERM LT | C352: =IFERROR(INDEX(DePara[Categoria],MATCH(TEXT(A352,"0"),DePara[Fornecedor_txt],0)),"(sem categoria)") | D352: =COUNTIF(Base[Fornecedor],A352&"") | E352: =SUMIF(Base[Fornecedor],A352&"",Base[Montante])
A353: 101485 | B353: RUDLOFF SISTEMA DE PROTENSAO LTDA | C353: =IFERROR(INDEX(DePara[Categoria],MATCH(TEXT(A353,"0"),DePara[Fornecedor_txt],0)),"(sem categoria)") | D353: =COUNTIF(Base[Fornecedor],A353&"") | E353: =SUMIF(Base[Fornecedor],A353&"",Base[Montante])
A354: 101053 | B354: NLA LATINOAMERICANA LOGISTICA LTDA | C354: =IFERROR(INDEX(DePara[Categoria],MATCH(TEXT(A354,"0"),DePara[Fornecedor_txt],0)),"(sem categoria)") | D354: =COUNTIF(Base[Fornecedor],A354&"") | E354: =SUMIF(Base[Fornecedor],A354&"",Base[Montante])
A355: 101432 | B355: CONSTRUTORA MD EIRELI | C355: =IFERROR(INDEX(DePara[Categoria],MATCH(TEXT(A355,"0"),DePara[Fornecedor_txt],0)),"(sem categoria)") | D355: =COUNTIF(Base[Fornecedor],A355&"") | E355: =SUMIF(Base[Fornecedor],A355&"",Base[Montante])
A356: 102143 | B356: FARDIER LOGISTICA ESP EM CARGAS EPE | C356: =IFERROR(INDEX(DePara[Categoria],MATCH(TEXT(A356,"0"),DePara[Fornecedor_txt],0)),"(sem categoria)") | D356: =COUNTIF(Base[Fornecedor],A356&"") | E356: =SUMIF(Base[Fornecedor],A356&"",Base[Montante])
A357: 102209 | B357: ENEL GREEN POWER V DE SANTA ANGELA 29711059000250 | C357: =IFERROR(INDEX(DePara[Categoria],MATCH(TEXT(A357,"0"),DePara[Fornecedor_txt],0)),"(sem categoria)") | D357: =COUNTIF(Base[Fornecedor],A357&"") | E357: =SUMIF(Base[Fornecedor],A357&"",Base[Montante])
A358: 105589 | B358: ENEL GREEN POWER VENTOS DE SAO ROQU 36051515000249 | C358: =IFERROR(INDEX(DePara[Categoria],MATCH(TEXT(A358,"0"),DePara[Fornecedor_txt],0)),"(sem categoria)") | D358: =COUNTIF(Base[Fornecedor],A358&"") | E358: =SUMIF(Base[Fornecedor],A358&"",Base[Montante])
A359: 102080 | B359: RECEITA FEDERAL DO BRASIL | C359: =IFERROR(INDEX(DePara[Categoria],MATCH(TEXT(A359,"0"),DePara[Fornecedor_txt],0)),"(sem categoria)") | D359: =COUNTIF(Base[Fornecedor],A359&"") | E359: =SUMIF(Base[Fornecedor],A359&"",Base[Montante])
A360: 104069 | B360: MUNICIPIO DE POCINHOS 08741688000172 | C360: =IFERROR(INDEX(DePara[Categoria],MATCH(TEXT(A360,"0"),DePara[Fornecedor_txt],0)),"(sem categoria)") | D360: =COUNTIF(Base[Fornecedor],A360&"") | E360: =SUMIF(Base[Fornecedor],A360&"",Base[Montante])
A361: EM000029 | B361: RENATO BRUNO LIMA DE FARIAS | C361: =IFERROR(INDEX(DePara[Categoria],MATCH(TEXT(A361,"0"),DePara[Fornecedor_txt],0)),"(sem categoria)") | D361: =COUNTIF(Base[Fornecedor],A361&"") | E361: =SUMIF(Base[Fornecedor],A361&"",Base[Montante])
A362: EM000129 | B362: JOCIVAN DE SOUZA SILVA | C362: =IFERROR(INDEX(DePara[Categoria],MATCH(TEXT(A362,"0"),DePara[Fornecedor_txt],0)),"(sem categoria)") | D362: =COUNTIF(Base[Fornecedor],A362&"") | E362: =SUMIF(Base[Fornecedor],A362&"",Base[Montante])
A363: EM000272 | B363: JOBSON BARBOSA DE OLIVEIRA | C363: =IFERROR(INDEX(DePara[Categoria],MATCH(TEXT(A363,"0"),DePara[Fornecedor_txt],0)),"(sem categoria)") | D363: =COUNTIF(Base[Fornecedor],A363&"") | E363: =SUMIF(Base[Fornecedor],A363&"",Base[Montante])
A364: EM000724 | B364: EMMANOEL LELIS EZIAS DOS SANTOS | C364: =IFERROR(INDEX(DePara[Categoria],MATCH(TEXT(A364,"0"),DePara[Fornecedor_txt],0)),"(sem categoria)") | D364: =COUNTIF(Base[Fornecedor],A364&"") | E364: =SUMIF(Base[Fornecedor],A364&"",Base[Montante])
A365: EM000018 | B365: ALESSANDRO SANTANA CORTES | C365: =IFERROR(INDEX(DePara[Categoria],MATCH(TEXT(A365,"0"),DePara[Fornecedor_txt],0)),"(sem categoria)") | D365: =COUNTIF(Base[Fornecedor],A365&"") | E365: =SUMIF(Base[Fornecedor],A365&"",Base[Montante])
A366: EM000024 | B366: GUILLERMO ROSSI | C366: =IFERROR(INDEX(DePara[Categoria],MATCH(TEXT(A366,"0"),DePara[Fornecedor_txt],0)),"(sem categoria)") | D366: =COUNTIF(Base[Fornecedor],A366&"") | E366: =SUMIF(Base[Fornecedor],A366&"",Base[Montante])
A367: EM000026 | B367: DIEGO ALAN DE OLIVEIRA DA SILVA | C367: =IFERROR(INDEX(DePara[Categoria],MATCH(TEXT(A367,"0"),DePara[Fornecedor_txt],0)),"(sem categoria)") | D367: =COUNTIF(Base[Fornecedor],A367&"") | E367: =SUMIF(Base[Fornecedor],A367&"",Base[Montante])
A368: EM000059 | B368: CRISOSTOMO CUNHA DE SOUSA | C368: =IFERROR(INDEX(DePara[Categoria],MATCH(TEXT(A368,"0"),DePara[Fornecedor_txt],0)),"(sem categoria)") | D368: =COUNTIF(Base[Fornecedor],A368&"") | E368: =SUMIF(Base[Fornecedor],A368&"",Base[Montante])
A369: EM000065 | B369: JOABE MACEDO DA SILVA | C369: =IFERROR(INDEX(DePara[Categoria],MATCH(TEXT(A369,"0"),DePara[Fornecedor_txt],0)),"(sem categoria)") | D369: =COUNTIF(Base[Fornecedor],A369&"") | E369: =SUMIF(Base[Fornecedor],A369&"",Base[Montante])
A370: EM000076 | B370: MOISES MELO DOS SANTOS | C370: =IFERROR(INDEX(DePara[Categoria],MATCH(TEXT(A370,"0"),DePara[Fornecedor_txt],0)),"(sem categoria)") | D370: =COUNTIF(Base[Fornecedor],A370&"") | E370: =SUMIF(Base[Fornecedor],A370&"",Base[Montante])
A371: EM000080 | B371: SAIRON DOS SANTOS BASTOS | C371: =IFERROR(INDEX(DePara[Categoria],MATCH(TEXT(A371,"0"),DePara[Fornecedor_txt],0)),"(sem categoria)") | D371: =COUNTIF(Base[Fornecedor],A371&"") | E371: =SUMIF(Base[Fornecedor],A371&"",Base[Montante])
A372: EM000108 | B372: GISLANIO GOMES DA SILVA | C372: =IFERROR(INDEX(DePara[Categoria],MATCH(TEXT(A372,"0"),DePara[Fornecedor_txt],0)),"(sem categoria)") | D372: =COUNTIF(Base[Fornecedor],A372&"") | E372: =SUMIF(Base[Fornecedor],A372&"",Base[Montante])
... A377: EM000155 | B377: IAGO TEIXEIRA MORGADO | C377: =IFERROR(INDEX(DePara[Categoria],MATCH(TEXT(A377,"0"),DePara[Fornecedor_txt],0)),"(sem categoria)") | D377: =COUNTIF(Base[Fornecedor],A377&"") | E377: =SUMIF(Base[Fornecedor],A377&"",Base[Montante])
A378: 107672 | B378: WONGTSCHOWSKI KLEIMAN ADVOGADOS | C378: =IFERROR(INDEX(DePara[Categoria],MATCH(TEXT(A378,"0"),DePara[Fornecedor_txt],0)),"(sem categoria)") | D378: =COUNTIF(Base[Fornecedor],A378&"") | E378: =SUMIF(Base[Fornecedor],A378&"",Base[Montante])
A379: EM000127 | B379: GUSTAVO FERNANDES LIMA | C379: =IFERROR(INDEX(DePara[Categoria],MATCH(TEXT(A379,"0"),DePara[Fornecedor_txt],0)),"(sem categoria)") | D379: =COUNTIF(Base[Fornecedor],A379&"") | E379: =SUMIF(Base[Fornecedor],A379&"",Base[Montante])
A380: EM000281 | B380: VANESSA REGINA DE CAMARGO | C380: =IFERROR(INDEX(DePara[Categoria],MATCH(TEXT(A380,"0"),DePara[Fornecedor_txt],0)),"(sem categoria)") | D380: =COUNTIF(Base[Fornecedor],A380&"") | E380: =SUMIF(Base[Fornecedor],A380&"",Base[Montante])
A381: EM000663 | B381: MARCELO DA COSTA BRAS | C381: =IFERROR(INDEX(DePara[Categoria],MATCH(TEXT(A381,"0"),DePara[Fornecedor_txt],0)),"(sem categoria)") | D381: =COUNTIF(Base[Fornecedor],A381&"") | E381: =SUMIF(Base[Fornecedor],A381&"",Base[Montante])
A382: EM000431 | B382: HERVERTON CAVALCANTE LIMA | C382: =IFERROR(INDEX(DePara[Categoria],MATCH(TEXT(A382,"0"),DePara[Fornecedor_txt],0)),"(sem categoria)") | D382: =COUNTIF(Base[Fornecedor],A382&"") | E382: =SUMIF(Base[Fornecedor],A382&"",Base[Montante])
A383: 101269 | B383: CERTISIGN CERTIFICADORA DIGITAL SA | C383: =IFERROR(INDEX(DePara[Categoria],MATCH(TEXT(A383,"0"),DePara[Fornecedor_txt],0)),"(sem categoria)") | D383: =COUNTIF(Base[Fornecedor],A383&"") | E383: =SUMIF(Base[Fornecedor],A383&"",Base[Montante])
A384: 101265 | B384: NET2PHONE BRASIL TELECOMUNICAÇÕES L | C384: =IFERROR(INDEX(DePara[Categoria],MATCH(TEXT(A384,"0"),DePara[Fornecedor_txt],0)),"(sem categoria)") | D384: =COUNTIF(Base[Fornecedor],A384&"") | E384: =SUMIF(Base[Fornecedor],A384&"",Base[Montante])
A385: 102140 | B385: SERASA SA | C385: =IFERROR(INDEX(DePara[Categoria],MATCH(TEXT(A385,"0"),DePara[Fornecedor_txt],0)),"(sem categoria)") | D385: =COUNTIF(Base[Fornecedor],A385&"") | E385: =SUMIF(Base[Fornecedor],A385&"",Base[Montante])
A386: 102084 | B386: TELEFONICA BRASIL SA | C386: =IFERROR(INDEX(DePara[Categoria],MATCH(TEXT(A386,"0"),DePara[Fornecedor_txt],0)),"(sem categoria)") | D386: =COUNTIF(Base[Fornecedor],A386&"") | E386: =SUMIF(Base[Fornecedor],A386&"",Base[Montante])
A387: 102001 | B387: TRIBUNAL REGIONAL TRABALHO 21A REGI | C387: =IFERROR(INDEX(DePara[Categoria],MATCH(TEXT(A387,"0"),DePara[Fornecedor_txt],0)),"(sem categoria)") | D387: =COUNTIF(Base[Fornecedor],A387&"") | E387: =SUMIF(Base[Fornecedor],A387&"",Base[Montante])
A388: 102486 | B388: F&F ATIVIDADES ESPORTIVAS LTDA | C388: =IFERROR(INDEX(DePara[Categoria],MATCH(TEXT(A388,"0"),DePara[Fornecedor_txt],0)),"(sem categoria)") | D388: =COUNTIF(Base[Fornecedor],A388&"") | E388: =SUMIF(Base[Fornecedor],A388&"",Base[Montante])
A389: EM000121 | B389: WILLIAM VICENTE DA SILVA | C389: =IFERROR(INDEX(DePara[Categoria],MATCH(TEXT(A389,"0"),DePara[Fornecedor_txt],0)),"(sem categoria)") | D389: =COUNTIF(Base[Fornecedor],A389&"") | E389: =SUMIF(Base[Fornecedor],A389&"",Base[Montante])
A390: EM000020 | B390: JOAO JORGE DA SILVA TEMOTEO | C390: =IFERROR(INDEX(DePara[Categoria],MATCH(TEXT(A390,"0"),DePara[Fornecedor_txt],0)),"(sem categoria)") | D390: =COUNTIF(Base[Fornecedor],A390&"") | E390: =SUMIF(Base[Fornecedor],A390&"",Base[Montante])
A391: 101287 | B391: TELEFONICA BRASIL SA | C391: =IFERROR(INDEX(DePara[Categoria],MATCH(TEXT(A391,"0"),DePara[Fornecedor_txt],0)),"(sem categoria)") | D391: =COUNTIF(Base[Fornecedor],A391&"") | E391: =SUMIF(Base[Fornecedor],A391&"",Base[Montante])
A392: 101159 | B392: DOCUSIGN BRASIL SOLUCOES EM TECNOLO 05516218000117 | C392: =IFERROR(INDEX(DePara[Categoria],MATCH(TEXT(A392,"0"),DePara[Fornecedor_txt],0)),"(sem categoria)") | D392: =COUNTIF(Base[Fornecedor],A392&"") | E392: =SUMIF(Base[Fornecedor],A392&"",Base[Montante])
A393: 101976 | B393: SAO PAULO TRIBUNAL DE JUSTICA | C393: =IFERROR(INDEX(DePara[Categoria],MATCH(TEXT(A393,"0"),DePara[Fornecedor_txt],0)),"(sem categoria)") | D393: =COUNTIF(Base[Fornecedor],A393&"") | E393: =SUMIF(Base[Fornecedor],A393&"",Base[Montante])
...

Sheet Pendências
A1: PENDENCIAS
A2: Fornecedores sem classificacao
A3: Contagem automatica abaixo. Para ver a lista, abra "Cadastro Fornecedores" e filtre a coluna Categoria = "(sem categoria)".
A5: Fornecedores pendentes: | B5: =COUNTIF('Cadastro Fornecedores'!C5:C676,"(sem categoria)")
